Workbook
Name _1Schubmaststap: '[1]master data equipment'!#REF!
Name _2Schubmaststap: '[2]master data equipment'!#REF!
Name _2Schubmaststap: '[1]master data equipment'!#REF!
Name _2Schubmaststap: '[1]master data equipment'!#REF!
Name _DAT10: '[3]AfA + Zinsen'!#REF!
Name _DAT11: '[3]AfA + Zinsen'!#REF!
Name _DAT12: '[3]AfA + Zinsen'!#REF!
Name _DAT14: '[3]AfA + Zinsen'!#REF!
Name _DAT16: '[3]AfA + Zinsen'!#REF!
Name _DAT17: '[3]AfA + Zinsen'!#REF!
Name _DAT18: '[3]AfA + Zinsen'!#REF!
Name _DAT19: '[3]AfA + Zinsen'!#REF!
Name _DAT20: '[3]AfA + Zinsen'!#REF!
Name _DAT21: '[3]AfA + Zinsen'!#REF!
Name _DAT7: '[3]AfA + Zinsen'!#REF!
Name _DAT8: '[3]AfA + Zinsen'!#REF!
Name _DAT9: '[3]AfA + Zinsen'!#REF!
Name _dlr: [4]Allg!$G$3
Name _dlr: [5]Allg!$G$3
Name _eur1: #REF!
Name _ts1: #REF!
Name A_SEC_VPL_TEIL_STAT_020806: #REF!
Name Abladebereiche: #REF!
Name Ablage: #REF!
Name Add_Zeile: #REF!
Name Additional_Packaging: '[8]basic data packaging'!$B$8:$B$116
Name AL35M7_01: [9]Thailand!#REF!
Name AL35M7_02: [9]Thailand!#REF!
Name AL35M7_03: [9]Thailand!#REF!
Name AL35M7_04: [9]Thailand!#REF!
Name AL35M7_05: [9]Thailand!#REF!
Name AL35M7_06: [9]Thailand!#REF!
Name AL35M7_07: [9]Thailand!#REF!
Name AL35M7_08: [9]Thailand!#REF!
Name AL35M7_09: [9]Thailand!#REF!
Name AL35M7_10: [9]Thailand!#REF!
Name AL35M7_11: [9]Thailand!#REF!
Name AL35M7_12: [9]Thailand!#REF!
Name AL35M7_Gesamt: [9]Thailand!#REF!
Name Anlauf6: [10]Kalkulationsbasis!$S$196
Name Anlauf6: [11]Kalkulationsbasis!$S$196
Name Arbeitsbereich: #REF!
Name Arbeitstage_Februar: [12]Eing_BASIS!$D$8
Name Arbeitstage_Februar: [13]Eing_BASIS!$D$8
Name Arbeitstage_Januar: [12]Eing_BASIS!$C$8
Name Arbeitstage_Januar: [13]Eing_BASIS!$C$8
Name Arbeitstage_März: [12]Eing_BASIS!$E$8
Name Arbeitstage_März: [13]Eing_BASIS!$E$8
Name AT_Jahr: [14]Parameter!$B$4
Name ATL_Basis_SAM_Fertig: #REF!
Name Ausführender: #REF!
Name Ausgangsdaten: [15]Ergebnis!$E$3:$AK$6
Name Ausgangsdaten: [16]Ergebnis!$E$3:$AK$6
Name Ausgangsregionen: [15]Ergebnis!$E$3:$E$6
Name Ausgangsregionen: [16]Ergebnis!$E$3:$E$6
Name Ausschuß: #REF!
Name Ausschuß: #REF!
Name Basic: #REF!
Name Basisjahr: #REF!
Name Bearbeitungsstand: [17]Basic_Units!$S$3:$S$6

Sheet Cover Sheet
A6: Exhibit 03
A8: Volume Information
A10: Logistics Services Agreement
A12: Regional Distribution Centre Ningbo
A14: P.R. of China
A17: Annotation
A18: The volume information which is mentioned in this Exhibit of that contract has been compiled by BBA to the best of BBA’s knowledge. Nevertheless it should be understood just as planning basis for the Contractor. The given volumes are indicative and could change. Therefore they cannot be guaranteed.

Sheet 问题清单
A1: # | B1: Source | C1: Category | D1: Question | E1: Critial | F1: On-site checking | G1: Answer
A2: 1 | B2: Appendix 23_Shanghai warehouse layout | C2: Storage | D2: 提供仓库的长度/宽度，标注每个storage area的长宽数据，最好可以提供CAD文件 | E2: Y
A3: 2 | B3: Appendix 23_Shanghai warehouse layout | C3: Storage | D3: 标书提到了对现有布局及货架的优化，但是目前我们没有在表述中看到目前的库存数据、每种货架类型的货位情况等； | E3: Y | F3: Y | G3: the optimizations in regards to the cost reduction, space utilization, efficiency increasing, etc. are always more than welcome to us. please take the opptunities of warehouse visit to see our operations and raised your ideas in proposal
A4: 3 | B4: Appendix 23_Shanghai warehouse layout | C4: Storage | D4: 现场了解相关情况，以及目前各类货架的利用率情况，痛点和瓶颈 | E4: Y | F4: Y | G4: 现场货架利用率目测大于85%，痛点和瓶颈未回复
A5: 4 | B5: Appendix 23_Shanghai warehouse layout | C5: Storage | D5: 在layout图看到Cross Docking Area 94平方米，请问cross docking有多少量？ | G5: 0.05
A6: 5 | B6: Appendix 3_Warehouse operation data | D6: 我们的操作能力需要在日平均的基础上考虑多少高峰加成？ | G6: 未明确回复，满足RFP文档中的货量需求即可
A7: 6 | B7: Appendix 3_Warehouse operation data Appendix 2_Inbound volume | C7: Inbound | D7: Appendix 2_Inbound volume 中Order Type分为Stock和Express，但是Appendix 3_Warehouse operation data中"Inbound Lines Express per working day (average)"是用Inbound Lines per year总量除以293天，是否可以分别提供Stock和Express的量 | E7: Y | H7: ~50% goods in container has pallet, and ~50% carton are mix SKU carton
A8: 7 | B8: Appendix 3_Warehouse operation data | C8: Inbound | D8: 每周到货的kolli数量，或Avergae # of orderline/kolli | E8: Y | G8: just for reference Large/Bulky 58% M2 14% M1 6% Small 14% ust for reference small 9 pcs/line M1 36 pcs/line M2 40 pcs/line Large 4pcs/line
A9: 8 | B9: Appendix 3_Warehouse operation data | C9: Inbound | D9: 是否只有当carton 外包装破损的什么情况下需要full inspection | G9: full inspection rate 3%~8%
A10: 9 | B10: Appendix 3_Warehouse operation data | C10: Inbound | D10: 到货orderline存放到不同区域的比列（Shelves area/Medium Parts Racking area/Large Parts Racking Area/Floor Storage area） | E10: Y
A11: 10 | B11: Appendix 3_Warehouse operation data | C11: Outbound | D11: "Outbound Lines (Dealer orders)"是否包含VOR? VOR的比列是多少？ | E11: Y
A12: 11 | B12: Appendix 9 Warehouse Quotation table | C12: Outbound | D12: Outbound # of packing cartons 是否可以参照3_packaging cost中第1-12行Avg. consumption/month作为包装出货量计算 | E12: Y
A13: 12 | B13: Appendix 9 Warehouse Quotation table | C13: Outbound | D13: Outbound # of packing cartons 是否可以参照3_packaging cost中第1-3行Small-Avg. consumption/month作为VOR包装出货量计算 | E13: Y
A14: 13 | B14: Appendix 3_Warehouse operation data | C14: Outbound | D14: 分别从不同区域picking的orderline比列（Shelves area/Medium Parts Racking area/Large Parts Racking Area/Floor Storage area） | E14: Y | G14: Large/Bulky 30% M2 27% M1 12% Small 29%
A15: 14 | B15: 00_Tender Document Porsche China Shanghai Lingang warehouse | D15: 目前的CCTV等监控设备是否会留用？ | F15: Y | G15: CCTV system needs to be replaced Tempreture&humidity sensor need to be setup furnitures&office renovation, security system belong to current 3PL
A16: 15 | B16: 00_Tender Document Porsche China Shanghai Lingang warehouse | D16: 关于地坪，现场需评估和讨论一下如何包括地坪成本 | F16: Y | G16: No need for newly floor coating renovation, but supplier will be responsible for the repair in case of damage following the requirements in appendix
A17: 16 | B17: 00_Tender Document Porsche China Shanghai Lingang warehouse | D17: 总体了解一下关于可能搬新仓的问题，因为设计到货架的重新布局安装，旧货架拆除，场地恢复，库位标签更改地坪，搬仓费用，盘点费用等等； 这部分，除了新货架按报价表，其他部分是否到时另行报价 | F17: Y | G17: 不考虑搬仓
A18: 17 | B18: 00_Tender Document Porsche China Shanghai Lingang warehouse | D18: 整体关于目前的操作流程有哪些痛点和瓶颈，需要在以后的操作中予以解决 | F18: Y
A19: 18 | B19: 00_Tender Document Porsche China Shanghai Lingang warehouse | D19: Appendix 8 中提到了AGV和数字孪生，需要现场了解一下具体的内容。包括但不限于， a) 目前AGV的使用场景，具体到步骤；具体台数及配套设施和系统情况 b) 新合同期内AGV以后会留用在仓库么？ | E19: Y | F19: Y | G19: 1.仓库无AGV及任何自动化设备。如果供应商投入AGV，网络，服务器等需要供应商单独配置，保时捷不兼容。 2.保时捷的PDMS平台有孪生系统，会有拣货，库存，破损登记，工作量等数据显示，效率没有体现，也不是实时显示。仓库操作EWMS系统，没有与孪生系统对接（不支持对接）。
A20: 19 | B20: 00_Tender Document Porsche China Shanghai Lingang warehouse | D20: 需要澄清一下水电是否需要包括在报价中？ | E20: Y | G20: utilites cost is covered by PCN
A21: 20 | B21: 00_Tender Document Porsche China Shanghai Lingang warehouse | D21: 此外按理解例如虫控、垃圾清运等费用都属于运营费用，需要包括在报价中，请确认 | E21: Y
A22: 21 | B22: Appendix 5 _ Rack system Requirements | D22: 2.2.1 Large parts 第一到第三层是否为picking location? | E22: Y | F22: Y | G22: 没有拣货位和补货位的设置，一二层为快流件 | H22: 不补货？
A23: 22 | B23: Appendix 5 _ Rack system Requirements | D23: 2.2.2 Medium parts II 第一到第三层是否为picking location? | E23: Y | F23: Y | G23: 没有拣货位和补货位的设置，一二层为快流件
A24: 23 | B24: Appendix 4_Warehouse scope of service | D24: 2.3.8 Matrix of Responsibilities IT- Equipment – PC, label printer and laser printer Office decoration Office furniture & equipment, phone, internet access Cabling in warehouse and office areas Security and Alarm system 因为是现有仓库，以上这些是不是已经涵盖，还是需要重新装修配置？ | E24: Y | G24: security system，SP should put the quotation in quotation sheet “1.3 Start-up cost” office furniture needs to be included
A25: 24 | B25: Appendix 4_Warehouse scope of service | D25: 2.3.8 Matrix of Responsibilities Insurance是否需要包含inventory财产险，需提供inventory value
A26: 25 | B26: Appendix 9 Warehouse Quotation table | C26: DG warehouse | D26: DG rental根据面积大小报价，请问是否可以接受share DG warehouse，还是必须dedicated warehouse | E26: Y | G26: 可以
C27: DG warehouse | D27: Inbound DG processing/Outbound DG processing是否包含C5仓库的操作以及external DG warehouse操作？ | E27: Y | G27: 不包含C5
D29: This is our understanding for inbound process, please clarify if correct or not: 100% unloading by full pallet>>outer box visual check and count at carton level>>all inbound cartons are mix sku carton, need to open carton and check sku/quantity/quality/shelf life by unit level>>sorting small unit by sku and put into sorted tote or new empty pallet>>putaway onto shelf or rack | E29: goods in container are mixed, not in pallatization, ~50% goods in container has pallet, and ~50% carton are mix SKU carton
D30: How many DG inbound pieces per inbound orderline? | E30: ~1.7
D31: How many DG inbound orderline per year? Does following inbound orderlines already include DG? | E31: DG is included. rate is around 8%
D32: Average how many lines per inbound HU? | E32: 2.4
D33: How many order lines per outbound pack on average? | E33: 5
D34: How many DG outbound orderline per year per Y2026 forecast? | E34: ~14360
D35: How many DG outbound pieces in Y2026 forecast? | E35: ~27000
D36: What is the proportion of DG Warehouse in the provided order lines? 请提供货量中DG仓库的订单行数、及每个订单行的平均件数等数据 | E36: ~2%, 1.69
D37: We noted that Porsche’s contract does not allow any amendments and prohibits the inclusion of a liability cap.Could Porsche kindly confirm whether it would be open to negotiating the retention of a liability-cap clause? | E37: 1.Clause 16.2 Loss or Damage of PCN Goods In case you want to set a liability cap under this term, please pay attention to below statements. PCN’s average inventory value is approximately RMB 400 million. In addition to the obligations set forth in the Agreement, the Service Provider (SP) shall maintain a minimum liability cap sufficient to cover the full value of PCN’s inventory at risk, such that the sum of: (a) the SP’s insurance coverage limit for loss or damage to PCN Goods, and (b) the SP’s direct financial liability (i.e., the liability cap beyond insurance) shall in total be no less than RMB 400 million (or its equivalent in Euro). This liability cap in respect of loss or damage of PCN Goods aims to ensures that PCN is fully compensated for any loss or damage resulting from the SP’s acts, omissions, negligence, improper handling, operational faults, or breach of contract — including any amounts not covered, partially covered, or rejected by insurance. The SP shall provide evidence of its current insurance coverage and confirm its ability to meet the required liability cap as part of its bid submission. Should the SP’s existing insurance be insufficient, it must procure additional coverage or demonstrate equivalent financial capacity to meet the total liability requirement. The cost of any such measures must be fully reflected in the SP’s final pricing proposal. PCN reserves the right to review and verify the SP’s insurance coverage and financial liability capacity at any time during the contract term. Any adjustment to the liability cap for loss or damage of PCN Goods due to changes in inventory value shall be mutually agreed in writing by both parties, and may result in a corresponding, mutually agreed adjustment to service fees. 2. Clause 16.5 Limitation of Liability PCN does not accept any changes or negotiations
D38: How many security guards and cleaner HC in current normal warehouse? | E38: 4+1
D39: “Inventory (Counting lines per year)” include cycle count and stock take? | E39: no, annal stock take volume is excluded
D40: Please provide the qty of storage locations corresponding to different types of storage racks/shelves in the current warehouse. 请提供现有仓库不同货位类型货位的货位数量，以便计算交接盘点的资源数量 | E40: Shelves 22863 Medium 8505 Large 6979 Bulky 387
D41: pls provide the % of inbound and outbound order lines for warehouses C1, C2, and C5? C1 和C2,C5 仓库入库和出库订单行比例分别是多少? | E41: C1+C2 2% C5 2%
D42: Total SKU count? Number of large, medium, and small SKUs? Average number of medium and small items per box? Average number of medium and small items per pallet? Average box weight for medium and small items? Average pallet weight for medium and small items? SKU总数量？大件、中件、小件SKU分别数量？中、小件每箱平均分别多少件？中、小件每拖盘平均分别多少箱？中小件平均箱重？中小件平均拖盘重？ | E42: SKU ~25000 large 23% m2 20% m1 27% small 30%
D43: How many order lines of the inbound orders are subject to shelf-life management ? 效期管理的零部件占总入库订单行的比例为多少？ | E43: ~9%
D44: Please provide the value of goods stored in the warehouse (Main Warehouse and DG Warehouse respectively). 请分别提供主仓和DG仓库（不同危品级别）存储货物的货值 | E44: main 353 mio DG 47 mio
D45: Please provide the operating requirements and annual pieces of engraved steal seal 请提供”engraved steal seal“操作的需求及年操作量 | E45: at most 12pc/year
... D52: C5是危品仓库吗？RFQ里需求重新查找危品库，是否该C5库房需要取消？ Is C5 a hazardous goods warehouse? In the RFQ, it requires a re-search for the hazardous goods warehouse. Should the C5 warehouse be cancelled? | E52: C5 stores some non-critical parts, e.g. oil, no need to store in Hazardous goods warehouse

Sheet Prod check
A1: Cross checking
A2: 1. Putaway productivity adjust to 17 line/hour
A3: 2. Picking productivity adjust to 27 line/hour
A4: 3. Packing productivity adjust to 39 line/hour
A5: 4. indirect labour - 可考虑减少1个Supervisor的配置
B7: Productivity Reference | F7: Porsche Productivity
A8: Main Process | B8: Cal. FTE (9.2 hours/WD) | C8: Workload% | D8: Daily line/2026 | E8: Productivity (line/hour) | F8: Cal. FTE (6.8 hours/WD) BEFORE | G8: Cal. FTE (6.8 hours/WD) AFTER | H8: Workload% | I8: Daily line/2026 | J8: Productivity (line/hour) BEFORE | K8: Productivity (line/hour) AFTER | L8: Productivity Porche vs. Reference | M8: Cal. Workload Hours (impact by space) | N8: Cal. Productivity (impact by space)
A9: Receiving, Sorting & Labeling | B9: 7 | C9: =B9/$B$15 -> 0.074468085 | D9: 1141 | E9: 17.7 | G9: =SUM(Process!P2:P29) -> 5.5178831 | H9: =G9/$G$15 -> 0.15691622 | I9: =Volume!B9/Parameter!$P$4 -> 750.54266 | K9: =I9/G9/Parameter!$P$6/Parameter!$P$7 -> 20.002947 | L9: =K9/E9 -> 1.13011
A10: Put away | B10: 11 | C10: =B10/$B$15 -> 0.11702128 | E10: 11.3 | F10: 5.5971972 | G10: =SUM(Process!P30:P72) -> 6.2944072 | H10: =G10/$G$15 -> 0.17899883 | J10: 19.719498 | K10: =I9/G10/Parameter!$P$6/Parameter!$P$7 -> 17.535237 | L10: =K10/E10 -> 1.5517909 | M10: =B10*9.2*($B$21*$B$20+(1-$B$21)) -> 70.84 | N10: =D9/M10 -> 16.106719
A11: Sub. Inbound | B11: =SUM(B9:B10) -> 18 | C11: =SUM(C9:C10) -> 0.19148936 | D11: / | E11: 6.9 | G11: =SUM(G9:G10) -> 11.81229 | H11: =SUM(H9:H10) -> 0.33591505 | I11: / | K11: =I9/G11/Parameter!$P$6/Parameter!$P$7 -> 9.3439899 | L11: =K11/E11 -> 1.3542014
A12: Picking | B12: 47 | C12: =B12/$B$15 -> 0.5 | D12: 8271 | E12: 19.1 | F12: 9.835593 | G12: =SUM(Process!O73:P124) -> 12.927094 | H12: =G12/$G$15 -> 0.36761757 | I12: =Volume!B58/Parameter!$P$4 -> 2437.5631 | J12: 36.44571 | K12: =I12/G12/Parameter!$P$6/Parameter!$P$7 -> 27.729756 | L12: =K12/E12 -> 1.4518197 | M12: =B12*9.2*($B$21*$B$20+(1-$B$21)) -> 302.68 | N12: =D12/M12 -> 27.325889
A13: Packing | B13: 24 | C13: =B13/$B$15 -> 0.25531915 | E13: 37.5 | F13: 10.446309 | G13: =SUM(Process!P125:P149) -> 9.0936252 | H13: =G13/$G$15 -> 0.25860231 | J13: 34.315006 | K13: =I12/G13/Parameter!$P$6/Parameter!$P$7 -> 39.419391 | L13: =K13/E13 -> 1.0511838
A14: Sub. Outbound | B14: 71 | C14: =SUM(C12:C13) -> 0.75531915 | D14: / | E14: 12.7 | G14: =SUM(G12:G13) -> 22.020719 | H14: =SUM(H12:H13) -> 0.62621989 | I14: / | K14: =I12/G14/Parameter!$P$6/Parameter!$P$7 -> 16.27854 | L14: =K14/E14 -> 1.2817748
A15: Overall DC (incl. inventory) | B15: 94 | C15: =C11+C14 -> 0.94680851 | D15: =D9+D12 -> 9412 | E15: 10.9 | F15: 32.728489 | G15: =SUM(G11,G14,Process!P152:P164) -> 35.164516 | H15: =H11+H14 -> 0.96213494 | I15: =I9+I12 -> 3188.1058 | J15: 14.325106 | K15: =I15/G15/Parameter!$P$6/Parameter!$P$7 -> 13.332732 | L15: =K15/E15 -> 1.2231865
G16: =G10-F10 -> 0.69720998
G17: =G12-F12 -> 3.0915012
G18: =G13-F13 -> -1.3526842
A20: Assume warehouse space comparison % | B20: 0.5
A21: Assume space/distance impact on the productivity | B21: 0.6
A25: Name | B25: Net workload | C25: Volume | D25: Unit | E25: Share
A26: 1-A Full pallets unloading - 40' trailers (seafreight) | B26: 117.0202 | C26: 6755.651 | D26: order lines | E26: 0.01932927 | F26: =SUM(E26:E31) -> 0.18804948 | G26: Receiving
A27: 1-B Bulk unloading with pallet - truck (airfreight) | B27: 24.638365 | C27: 15077.682 | D27: order lines | E27: 0.0038160784
A28: 2-A Sorting (Full Package) | B28: 29.784326 | C28: 4252.0339 | D28: order lines | E28: 0.0054244929
A29: 2-B Sorting (Mixed Package) | B29: 842.91319 | C29: 14416.08 | D29: order lines | E29: 0.12722453
A30: 2-C Sorting (Bulk Package) | B30: 212.49636 | C30: 3165.2199 | D30: order lines | E30: 0.032255109
A31: 2-D Sorting (X-docking) | B31: 0 | C31: 0 | D31: order lines | E31: 0
A32: 3-A Put away in Mezzanine with RF | B32: 82.485411 | C32: 14416.08 | D32: order lines | E32: 0.011963865 | F32: =SUM(E32:E37) -> 0.079471444 | G32: Putaway
A33: 3-B Put away in racks and cantilevers with RF | B33: 459.1067 | C33: 7308.0871 | D33: order lines | E33: 0.066816648
A34: 3-C Put away in floor storage area with RF | B34: 4.7474837 | C34: 109.16667 | D34: order lines | E34: 0.00069093077
A35: 3-D Put away in Locked room with RF | B35: 0 | C35: 0 | D35: order lines | E35: 0
A36: 3-E Put away in DG area with RF | B36: 0 | C36: 0 | D36: order lines | E36: 0
A37: 3-F Put away in X-dock area with RF | B37: 0 | C37: 0 | D37: order lines | E37: 0
A38: 4-A Mixed cases prep. with RF, picking from Mezzanine/Carousel, manual case building | B38: 1459.4318 | C38: 40607.125 | D38: order lines | E38: 0.23235286 | F38: =SUM(E38:E42,E46) -> 0.43872334 | G38: Picking
A39: 4-B Picking from Floor with RF | B39: 16.523335 | C39: 307.5 | D39: order lines | E39: 0.002417094
A40: 4-C Picking from Racking/Cantilever, with RF | B40: 1193.4923 | C40: 20585.375 | D40: order lines | E40: 0.17445232
A41: 4-D Mixed cases prep. with RF, picking from Locked area, manual case building | B41: 0 | C41: 0 | D41: order lines | E41: 0
A42: 4-E Picking from Racking in DG room, with RF | B42: 0 | C42: 0 | D42: order lines | E42: 0
A43: 5 Packing | B43: 1623.9572 | C43: 61500 | D43: order lines | E43: 0.23884155 | F43: =SUM(E43:E44) -> 0.24373543 | G43: Packing
A44: 6 Loading pallets | B44: 32.075329 | C44: 61500 | D44: order lines | E44: 0.0048938762
A45: 7 Inventory per location with RF | B45: 137.74186 | C45: 4371.7667 | D45: location | E45: 0.026112593
A46: Full boxes replenishment for pieces picking | B46: 202.61964 | C46: 61500 | D46: order lines | E46: 0.029501065
A47: 9 Key Cutting | B47: 13.533333 | C47: 116.66667 | D47: piece | E47: 0.023302893
A48: 10-Warrenty and Return | B48: 0 | C48: 0 | D48: order lines | E48: 0.00067040615
F49: =SUM(F26:F48) -> 0.94997969

Sheet Rate sheet
B4: PCN Warehousing Quotation Sheet
B6: 1.1. Storage Systems
C7: This quotation covers all the costs incurred for storage infrastructure installation, equipment & maintanence, etc
C11: Additional Storage System (Racking and Shelving) | J11: Racking brand: OTL | T11: Remarks
T12: The quotation only refers to new racking setup in future
C13: a) Pallet Racking | F13: RMB per large parts location (avg. 1900*1300*1700mm) per Month
F15: RMB per medium parts location (avg. 1300*800*520*) per Month
C17: b) Shelves | F17: RMB per modules (300mm depth) per Month, including all accessories like shelves, dividers or boxes, etc
F19: RMB per modules (600mm depth) per Month, including all accessories like shelves, dividers or boxes, etc
F21: RMB per modules (1000mm depth) per Month, including all accessories like shelves, dividers or boxes, etc
C23: The pallet location size mentioned above is for reference only, there may be 20% deviation in actual
C24: Shelves is set up to 2.5m high for each floor in warehouse, and levelers and dividers qty. depends on actual requirements
B26: 1.2. Operation
C27: This quotation covers all the costs incurred for warehouse processing (inbound, outbound, special handling), include payments for all services that are not included under Section 1.1 & 1.3
D29: 有些流程可以不分配mhe, 手动改报价，看P&L；例如：labelling | J29: From cost allocation
C30: a) Inbound Processing | E30: ='Cost Allocation'!U12 -> 8.1632846 | F30: RMB per inbound order line | J30: ='Cost Allocation'!U12 -> 8.1632846 | T30: Remark
C31: b) Inbound DG Processing | E31: 0 | F31: RMB per inbound order line | T31: All the cost which is not related to warehouse storage equipment should be covered in Operation cost.
C33: c) Outbound Processing | E33: ='Cost Allocation'!U14 -> 6.5369352 | F33: RMB per outbound order line | J33: ='Cost Allocation'!U14 -> 6.5369352
C34: d) Outbound DG Processing | E34: 0 | F34: RMB per outbound order line
C36: e) Warrenty & Return | E36: ='Cost Allocation'!U15 -> 23.523858 | F36: RMB per processed line | J36: ='Cost Allocation'!U15 -> 23.523858
C37: f) Warrenty & Return DG | E37: ='Cost Allocation'!U16 -> 26.812908 | F37: RMB per processed line | J37: ='Cost Allocation'!U16 -> 26.812908
C39: g) Key cutting handling | E39: ='Cost Allocation'!U13 -> 45.028662 | F39: RMB per key piece | J39: ='Cost Allocation'!U13 -> 45.028662
C41: h) Chinese labelling | E41: 0.15 | F41: RMB per label pieces | J41: ='Cost Allocation'!U7 -> 0.25057427
C43: i) Engraved steal seal | E43: ='Cost Allocation'!U10 -> 45.028662 | F43: RMB per piece | J43: ='Cost Allocation'!U10 -> 45.028662
C45: j) Customs inspection | E45: ='Cost Allocation'!U9 -> 8.9376361 | F45: RMB per inbound lines | J45: ='Cost Allocation'!U9 -> 8.9376361
B47: 1.3 Customer care service
C48: h) Customer care service | F48: RMB per position
B50: 1.3 Start-up cost
T51: Remark
C52: Charged items | F52: Note | O52: Expenses | T52: This quotation covers all the services of SP's responsibilities that have listed in the Matrix of Responsibilities (point 6) Any other cost that may incurred during the warehouse start-up phase should also be invloved, like office renovation, security, trainning, handover, etc.
C53: =Startup!B2 -> 1. Pre- on board and training | F53: Including DC manager/supervisor will pre-on board 2 weeks and operators 1 week for traning | O53: =Startup!D2 -> 58704.605
C54: =Startup!B18 -> 2. Stock count for handover | F54: Stock count with current vendor and confirm handover | O54: =Startup!D18 -> 53478.967
C55: 3. Office setup | F55: 3PL's office setup cost | O55: ='MHE&INV list'!K30*(1+'Cost Allocation'!R4) -> 457600
C56: 4. Security system | O56: ='MHE&INV list'!K26*(1+'Cost Allocation'!R4) -> 644644
B60: Tax rate (%): | E60: (Tax type shall be VAT, if not, please specify) | I60: (bidder to fill up)

Sheet P&L Sheet
C2: Subsequent Years Costs
C4: Yr1 | D4: Yr2 | E4: Yr3 | F4: Yr4 | G4: Yr5 | H4: Yr6 | I4: Yr7 | J4: Yr8 | K4: Yr9 | L4: Yr10 | M4: Total
B5: ='Rate sheet'!C30 -> a) Inbound Processing | C5: ='Rate sheet'!$E$30*Volume!B7 -> 1687469 | D5: ='Rate sheet'!$E$30*Volume!C7 -> 1636844.9 | E5: ='Rate sheet'!$E$30*Volume!D7 -> 1587739.5 | F5: ='Rate sheet'!$E$30*Volume!E7 -> 1635371.7 | G5: ='Rate sheet'!$E$30*Volume!F7 -> 1684432.9 | M5: =SUM(C5:L5) -> 8231858 | N5: =M5/$M$19 -> 0.22433791
B6: ='Rate sheet'!C31 -> b) Inbound DG Processing | C6: ='Rate sheet'!$E$31*Volume!B8 -> 0 | D6: ='Rate sheet'!$E$31*Volume!C8 -> 0 | E6: ='Rate sheet'!$E$31*Volume!D8 -> 0 | F6: ='Rate sheet'!$E$31*Volume!E8 -> 0 | G6: ='Rate sheet'!$E$31*Volume!F8 -> 0 | M6: =SUM(C6:L6) -> 0 | N6: =M6/$M$19 -> 0
B7: ='Rate sheet'!C33 -> c) Outbound Processing | C7: ='Rate sheet'!$E$33*Volume!B56 -> 4575344 | D7: ='Rate sheet'!$E$33*Volume!C56 -> 4438083.7 | E7: ='Rate sheet'!$E$33*Volume!D56 -> 4304941.1 | F7: ='Rate sheet'!$E$33*Volume!E56 -> 4434089.4 | G7: ='Rate sheet'!$E$33*Volume!F56 -> 4567112.1 | M7: =SUM(C7:L7) -> 22319570 | N7: =M7/$M$19 -> 0.60826193
B8: ='Rate sheet'!C34 -> d) Outbound DG Processing | C8: ='Rate sheet'!$E$37*Volume!B57 -> 382998.8 | D8: ='Rate sheet'!$E$37*Volume!C57 -> 371508.83 | E8: ='Rate sheet'!$E$37*Volume!D57 -> 360363.57 | F8: ='Rate sheet'!$E$37*Volume!E57 -> 371174.48 | G8: ='Rate sheet'!$E$37*Volume!F57 -> 382309.71 | M8: =SUM(C8:L8) -> 1868355.4 | N8: =M8/$M$19 -> 0.050917175
B9: ='Rate sheet'!C36 -> e) Warrenty & Return | C9: ='Rate sheet'!$E$36*Volume!B84 -> 304469.3 | D9: ='Rate sheet'!$E$36*Volume!C84 -> 295335.22 | E9: ='Rate sheet'!$E$36*Volume!D84 -> 286475.16 | F9: ='Rate sheet'!$E$36*Volume!E84 -> 295069.42 | G9: ='Rate sheet'!$E$36*Volume!F84 -> 303921.5 | M9: =SUM(C9:L9) -> 1485270.6 | N9: =M9/$M$19 -> 0.040477193
B10: ='Rate sheet'!C37 -> f) Warrenty & Return DG | C10: ='Rate sheet'!$E$37*Volume!B84*Volume!$J$26 -> 20822.368 | D10: ='Rate sheet'!$E$37*Volume!C84*Volume!$J$26 -> 20197.697 | E10: ='Rate sheet'!$E$37*Volume!D84*Volume!$J$26 -> 19591.766 | F10: ='Rate sheet'!$E$37*Volume!E84*Volume!$J$26 -> 20179.519 | G10: ='Rate sheet'!$E$37*Volume!F84*Volume!$J$26 -> 20784.905 | M10: =SUM(C10:L10) -> 101576.26 | N10: =M10/$M$19 -> 0.0027681971
B11: ='Rate sheet'!C39 -> g) Key cutting handling | C11: ='Rate sheet'!$E$39*Volume!B87 -> 129682.55 | D11: ='Rate sheet'!$E$39*Volume!C87 -> 125765.05 | E11: ='Rate sheet'!$E$39*Volume!D87 -> 116984.46 | F11: ='Rate sheet'!$E$39*Volume!E87 -> 111130.74 | G11: ='Rate sheet'!$E$39*Volume!F87 -> 105547.18 | M11: =SUM(C11:L11) -> 589109.98 | N11: =M11/$M$19 -> 0.016054663
B12: ='Rate sheet'!C41 -> h) Chinese labelling | C12: ='Rate sheet'!$E$41*Volume!B85 -> 296497.8 | D12: ='Rate sheet'!$E$41*Volume!C85 -> 287602.87 | E12: ='Rate sheet'!$E$41*Volume!D85 -> 278974.78 | F12: ='Rate sheet'!$E$41*Volume!E85 -> 287344.02 | G12: ='Rate sheet'!$E$41*Volume!F85 -> 295964.34 | M12: =SUM(C12:L12) -> 1446383.8 | N12: =M12/$M$19 -> 0.039417435
B13: ='Rate sheet'!C43 -> i) Engraved steal seal | C13: ='Rate sheet'!E43*第二轮数据!C60 -> 540.34394 | D13: =C13 -> 540.34394 | E13: =D13 -> 540.34394 | F13: =E13 -> 540.34394 | G13: =F13 -> 540.34394 | M13: =SUM(C13:L13) -> 2701.7197 | N13: =M13/$M$19 -> 7.3628355e-05
B14: ='Rate sheet'!C45 -> j) Customs inspection | C14: ='Rate sheet'!$E$45*Volume!B86 -> 16087.745 | D14: ='Rate sheet'!$E$45*Volume!C86 -> 15605.113 | E14: ='Rate sheet'!$E$45*Volume!D86 -> 15131.418 | F14: ='Rate sheet'!$E$45*Volume!E86 -> 15891.117 | G14: ='Rate sheet'!$E$45*Volume!F86 -> 16686.567 | M14: =SUM(C14:L14) -> 79401.959 | N14: =M14/$M$19 -> 0.0021638942
B15: Startup | C15: {='Rate sheet'!O53:P53+'Rate sheet'!O54:P54+'Rate sheet'!O55:P55} -> 569783.57 | D15: 0 | M15: =SUM(C15:L15) -> 569783.57 | N15: =M15/$M$19 -> 0.015527972
B16: Packaging | M16: =SUM(C16:L16) -> 0 | N16: =M16/$M$19 -> 0
M17: =SUM(C17:L17) -> 0 | N17: =M17/$M$19 -> 0
M18: =SUM(C18:L18) -> 0 | N18: =M18/$M$19 -> 0
B19: Total Rev. | C19: =SUM(C5:C18) -> 7983695.4 | D19: =SUM(D5:D18) -> 7191483.7 | E19: =SUM(E5:E18) -> 6970742.2 | F19: =SUM(F5:F18) -> 7170790.7 | G19: =SUM(G5:G18) -> 7377299.5 | H19: =SUM(H5:H18) -> 0 | I19: =SUM(I5:I18) -> 0 | J19: 0 | K19: 0 | L19: 0 | M19: =SUM(C19:L19) -> 36694012
B21: DIRECT COST
B22: Labour/Management | C22: =SUM(C23:C24) -> 4729186 | D22: =SUM(D23:D24) -> 4897287.9 | E22: =SUM(E23:E24) -> 4894762.8 | F22: =SUM(F23:F24) -> 4994782.5 | G22: =SUM(G23:G24) -> 5202365.6 | H22: =SUM(H23:H26) -> 0 | I22: =SUM(I23:I26) -> 0 | J22: 0 | K22: 0 | L22: 0 | M22: =SUM(C22:K22) -> 24718385
B23: Direct | C23: =SUM(Process!AB:AB) -> 3319786 | D23: =SUM(Process!AC:AC) -> 3445605.9 | E23: =SUM(Process!AD:AD) -> 3399530.4 | F23: =SUM(Process!AE:AE) -> 3454693.1 | G23: =SUM(Process!AF:AF) -> 3616073.4 | H23: =$P$23*W23 -> 0 | I23: =$P$23*X23 -> 0 | J23: 0 | K23: 0 | L23: 0 | M23: =SUM(C23:L23) -> 17235689
B24: Indirect | C24: =SUM(Parameter!V19:V22) -> 1409400 | D24: =SUM(Parameter!W19:W22) -> 1451682 | E24: =SUM(Parameter!X19:X22) -> 1495232.5 | F24: =SUM(Parameter!Y19:Y22) -> 1540089.4 | G24: =SUM(Parameter!Z19:Z22) -> 1586292.1 | H24: =$P$23*W24 -> 0 | I24: =$P$23*X24 -> 0 | J24: 0 | K24: 0 | L24: 0 | M24: =SUM(C24:L24) -> 7482696
B26: Gross margin
B28: Equipment | C28: =C29+C30 -> 2741746.1 | D28: =D29+D30 -> 1706584 | E28: =E29+E30 -> 1700317.3 | F28: =F29+F30 -> 1561161.8 | G28: =G29+G30 -> 1555929.8 | H28: 0 | I28: 0 | J28: 0 | K28: 0 | L28: 0 | M28: =SUM(C28:L28) -> 9265739.1
B29: Lease/ Consume | C29: =SUMIF('MHE&INV list'!$B:$B,"Lease/Consume",'MHE&INV list'!K:K) -> 1577782.7 | D29: =SUMIF('MHE&INV list'!$B:$B,"Lease/Consume",'MHE&INV list'!L:L) -> 1571625.8 | E29: =SUMIF('MHE&INV list'!$B:$B,"Lease/Consume",'MHE&INV list'!M:M) -> 1566393.8 | F29: =SUMIF('MHE&INV list'!$B:$B,"Lease/Consume",'MHE&INV list'!N:N) -> 1561161.8 | G29: =SUMIF('MHE&INV list'!$B:$B,"Lease/Consume",'MHE&INV list'!O:O) -> 1555929.8 | H29: 0 | I29: 0 | J29: 0 | K29: 0 | L29: 0 | M29: =SUM(C29:L29) -> 7832893.8
B30: Depreciation | C30: =SUMIF('MHE&INV list'!$B:$B,"Purchase",'MHE&INV list'!K:K) -> 1163963.5 | D30: =SUMIF('MHE&INV list'!$B:$B,"Purchase",'MHE&INV list'!L:L) -> 134958.22 | E30: =SUMIF('MHE&INV list'!$B:$B,"Purchase",'MHE&INV list'!M:M) -> 133923.53 | F30: =SUMIF('MHE&INV list'!$B:$B,"Purchase",'MHE&INV list'!N:N) -> 0 | G30: =SUMIF('MHE&INV list'!$B:$B,"Purchase",'MHE&INV list'!O:O) -> 0 | H30: 0 | I30: 0 | J30: 0 | K30: 0 | L30: 0 | M30: =SUM(C30:L30) -> 1432845.2
M31: =SUM(C31:L31) -> 0
B32: Occupancy/Warehouse Facility Costs | C32: =C34 -> 0 | D32: =D34 -> 0 | E32: =E34 -> 0 | F32: =F34 -> 0 | G32: =G34 -> 0 | H32: =H34 -> 0 | I32: =I34 -> 0 | J32: 0 | K32: 0 | L32: 0 | M32: =SUM(C32:L32) -> 0
B33: Rent | C33: 0 | D33: 0 | E33: 0 | F33: 0 | G33: 0 | H33: 0 | I33: 0 | J33: 0 | K33: 0 | L33: 0 | M33: =SUM(C33:L33) -> 0
B34: Other | C34: 0 | D34: 0 | E34: 0 | F34: 0 | G34: 0 | H34: 0 | I34: 0 | J34: 0 | K34: 0 | L34: 0 | M34: =SUM(C34:L34) -> 0
M35: =SUM(C35:L35) -> 0
B36: Packaging | C36: 0 | D36: 0 | E36: 0 | F36: 0 | G36: 0 | H36: 0 | I36: 0 | J36: 0 | K36: 0 | L36: 0 | M36: =SUM(C36:L36) -> 0
M37: =SUM(C37:L37) -> 0
B38: Start up | C38: =Startup!D2+Startup!D18+Startup!D32 -> 387360.43 | D38: 0 | E38: 0 | F38: 0 | G38: 0 | H38: 0 | I38: 0 | J38: 0 | K38: 0 | L38: 0 | M38: =SUM(C38:L38) -> 387360.43
M39: =SUM(C39:L39) -> 0
M40: =SUM(C40:L40) -> 0
M41: =SUM(C41:L41) -> 0
M42: =SUM(C42:L42) -> 0
M43: =SUM(C43:L43) -> 0
B44: Total Costs | C44: =C38+C36+C32+C28+C22 -> 7858292.6 | D44: =D38+D36+D32+D28+D22 -> 6603871.9 | E44: =E38+E36+E32+E28+E22 -> 6595080.2 | F44: =F38+F36+F32+F28+F22 -> 6555944.3 | G44: =G38+G36+G32+G28+G22 -> 6758295.4 | H44: =H38+H36+H32+H28+H22 -> 0 | I44: =I38+I36+I32+I28+I22 -> 0 | J44: =J38+J36+J32+J28+J22 -> 0 | ... M44: =M38+M36+M32+M28+M22 -> 34371484
B45: Total Rev. - Total Costs | C45: =C19-C44 -> 125402.83 | D45: =D19-D44 -> 587611.75 | E45: =E19-E44 -> 375662.04 | F45: =F19-F44 -> 614846.42 | G45: =G19-G44 -> 619004.14 | H45: =H19-H44 -> 0 | I45: =I19-I44 -> 0 | J45: 0 | K45: 0 | L45: 0 | M45: =SUM(C45:L45) -> 2322527.2
B46: EBITA | C46: =C45/C19 -> 0.015707366 | D46: =D45/D19 -> 0.081709391 | E46: =E45/E19 -> 0.053891254 | F46: =F45/F19 -> 0.085743183 | G46: =G45/G19 -> 0.083906603 | H46: =H45/H19 -> #DIV/0! | I46: =I45/I19 -> #DIV/0! | J46: =J45/J19 -> #DIV/0! | ... M46: =M45/M19 -> 0.063294447

Sheet Cost Allocation
A1: (ALL COST IS ANNUAL COST)
B3: Profit （%） | N3: Profit （%） | O3: Profit （%） | Q3: Profit （%） | R3: Profit （%）
B4: 0.1 | N4: 0.1 | O4: 0.1 | Q4: 0.1 | R4: 0.1
E5: 求和项:FTE | F5: 列标签 | N5: MHE | O5: Packing | P5: Charge FTE+MHE | Q5: Charge Indirect Labor | R5: Other inv. | S5: Total Charge | T5: Annual Volume | U5: Unit rate
A6: 行标签 | B6: FTE cost (Y1) | C6: %WorkLoad | D6: % (adjust) | E6: 行标签 | F6: CB | G6: CB - DG | H6: Manual | I6: OP-move | J6: OP-raise/down | K6: Rider on | L6: R-Truck | M6: Trolley | N6: (Y1) | P6: (Y1) | Q6: (Y1) | R6: (Y1) | S6: (Y1) | T6: (Y1) | U6: (Y1)
A7: Chinese labelling | B7: 206448.15 | C7: 0.065891632 | D7: =C7/(1-$C$8) -> 0.068508681 | E7: Chinese labelling | F7: 0.020665526 | G7: 0 | H7: 0.12345472 | I7: 0 | J7: 0 | K7: 0 | L7: 0 | M7: 0 | N7: =SUMPRODUCT(F7:M7,$F$22:$M$22) -> 4265.3645 | P7: =$P$18*D7 -> 316722.04 | Q7: =D7*$Q$18 -> 106211.75 | R7: =$R$18*D7 -> 72364.332 | S7: =P7+Q7+R7 -> 495298.13 | T7: =Volume!B85 -> 1976652 | U7: =S7/T7 -> 0.25057427
A8: Count | B8: 135524.91 | C8: 0.038200254 | E8: Count | F8: 0.00085405103 | G8: 0.008722168 | H8: 0.05715381 | I8: 0 | J8: 0.10694336 | K8: 0.023448853 | L8: 0 | M8: 0.00087520169 | N8: =SUMPRODUCT(F8:M8,$F$22:$M$22) -> 14960.915 | P8: =$P$18*D8 -> 0 | Q8: =D8*$Q$18 -> 0 | R8: =$R$18*D8 -> 0 | S8: =P8+Q8+R8 -> 0
A9: Customs inspection | B9: 9491.2114 | C9: 0.0021402216 | D9: =C9/(1-$C$8) -> 0.0022252258 | E9: Customs inspection | F9: 0 | G9: 0 | H9: 0.0041520117 | I9: 0 | J9: 0 | K9: 0 | L9: 0 | M9: 0 | N9: =SUMPRODUCT(F9:M9,$F$22:$M$22) -> 0 | P9: =$P$18*D9 -> 10287.427 | Q9: =D9*$Q$18 -> 3449.8566 | R9: =$R$18*D9 -> 2350.461 | S9: =P9+Q9+R9 -> 16087.745 | T9: =Volume!B86 -> 1800 | U9: =S9/T9 -> 8.9376361
A10: Engraved steal seal | B10: 255.02734 | C10: 7.188427e-05 | D10: =C10/(1-$C$8) -> 7.4739331e-05 | E10: Engraved steal seal | F10: 0 | G10: 0 | H10: 0.00013286437 | I10: 0 | J10: 0 | K10: 0 | L10: 0 | M10: 3.1877215e-05 | N10: =SUMPRODUCT(F10:M10,$F$22:$M$22) -> 0.12865337 | P10: =$P$18*D10 -> 345.52692 | Q10: =D10*$Q$18 -> 115.87137 | R10: =$R$18*D10 -> 78.945642 | S10: =P10+Q10+R10 -> 540.34394 | T10: =第二轮数据!C60 -> 12 | U10: =S10/T10 -> 45.028662
A11: Inbound DG processing | C11: 0 | D11: =C11/(1-$C$8) -> 0 | E11: Inbound DG processing | F11: 0 | G11: 0 | H11: 0 | I11: 0 | J11: 0 | K11: 0 | L11: 0 | M11: 0 | N11: =SUMPRODUCT(F11:M11,$F$22:$M$22) -> 0 | P11: =$P$18*D11 -> 0 | Q11: =D11*$Q$18 -> 0 | R11: =$R$18*D11 -> 0 | S11: =P11+Q11+R11 -> 0 | T11: =Volume!B8 -> 13194.54 | U11: =S11/T11 -> 0
A12: Inbound processing | B12: 777532.98 | C12: 0.22449123 | D12: =C12/(1-$C$8) -> 0.23340745 | E12: Inbound processing | F12: 0.50886175 | G12: 0.62636912 | H12: 0.058743661 | I12: 0 | J12: 0.31828581 | K12: 0 | L12: 1 | M12: 0.21202593 | N12: =SUMPRODUCT(F12:M12,$F$22:$M$22) -> 443532.29 | P12: =$P$18*D12 -> 1079064.5 | Q12: =D12*$Q$18 -> 361860.91 | R12: =$R$18*D12 -> 246543.56 | S12: =P12+Q12+R12 -> 1687469 | T12: =Volume!B7 -> 206714.46 | U12: =S12/T12 -> 8.1632846
A13: Key cutting handling | B13: 61206.563 | C13: 0.017252225 | D13: =C13/(1-$C$8) -> 0.017937439 | E13: Key cutting handling | F13: 0 | G13: 0 | H13: 0.03188745 | I13: 0 | J13: 0 | K13: 0 | L13: 0 | M13: 0.0076505316 | N13: =SUMPRODUCT(F13:M13,$F$22:$M$22) -> 30.876808 | P13: =$P$18*D13 -> 82926.462 | Q13: =D13*$Q$18 -> 27809.13 | R13: =$R$18*D13 -> 18946.954 | S13: =P13+Q13+R13 -> 129682.55 | T13: =Volume!B87 -> 2880 | U13: =S13/T13 -> 45.028662
A14: Outbound processing | B14: 1939873.3 | C14: 0.60867761 | D14: =C14/(1-$C$8) -> 0.63285275 | E14: Outbound processing | F14: 0.46961867 | G14: 0.36490871 | H14: 0.64052246 | I14: 1 | J14: 0.57477083 | K14: 0.97655115 | L14: 0 | M14: 0.77941646 | N14: =SUMPRODUCT(F14:M14,$F$22:$M$22) -> 366366.33 | O14: =SUM('MHE&INV list'!K13:K14,'MHE&INV list'!K20:K25)*C14/(C15+C14) -> 50509.281 | P14: =$P$18*D14 -> 2925737.5 | Q14: =D14*$Q$18 -> 981136.93 | R14: =$R$18*D14 -> 668469.54 | S14: =P14+Q14+R14 -> 4575344 | T14: =Volume!B56 -> 699921.88 | U14: =S14/T14 -> 6.5369352
A15: Warranty & Return | B15: 179626.32 | C15: 0.040504855 | D15: =C15/(1-$C$8) -> 0.042113605 | E15: Warranty & Return | F15: 0 | G15: 0 | H15: 0.078579073 | I15: 0 | J15: 0 | K15: 0 | L15: 0 | M15: 0 | N15: =SUMPRODUCT(F15:M15,$F$22:$M$22) -> 0 | O15: =SUM('MHE&INV list'!K13:K14,'MHE&INV list'!K20:K25)*C15/(C15+C14) -> 3361.1735 | P15: =$P$18*D15 -> 194695.14 | Q15: =D15*$Q$18 -> 65290.407 | R15: =$R$18*D15 -> 44483.749 | S15: =P15+Q15+R15 -> 304469.3 | T15: =Volume!B84 -> 12943 | U15: =S15/T15 -> 23.523858
A16: Warranty & Return DG | B16: 9827.58 | C16: 0.0027700889 | D16: =C16/(1-$C$8) -> 0.0028801098 | E16: Warranty & Return DG | F16: 0 | G16: 0 | H16: 0.0053739488 | I16: 0 | J16: 0 | K16: 0 | L16: 0 | M16: 0 | N16: =SUMPRODUCT(F16:M16,$F$22:$M$22) -> 0 | P16: =$P$18*D16 -> 13315.017 | Q16: =D16*$Q$18 -> 4465.1494 | R16: =$R$18*D16 -> 3042.2017 | S16: =P16+Q16+R16 -> 20822.368 | T16: =T15*Volume!J26 -> 776.58 | U16: =S16/T16 -> 26.812908
A17: Outbound DG processing | C17: 0 | D17: =C17/(1-$C$8) -> 0 | E17: Outbound DG processing | F17: 0 | G17: 0 | H17: 0 | I17: 0 | J17: 0 | K17: 0 | L17: 0 | M17: 0 | N17: =SUMPRODUCT(F17:M17,$F$22:$M$22) -> 0 | P17: =$P$18*D17 -> 0 | Q17: =D17*$Q$18 -> 0 | R17: =$R$18*D17 -> 0 | S17: =P17+Q17+R17 -> 0 | T17: 0 | U17: 0
A18: 总计 | B18: 3319786 | C18: 1 | D18: =SUM(D7:D17) -> 1 | E18: 总计 | F18: 1 | G18: 1 | H18: 1 | I18: 1 | J18: 1 | K18: 1 | L18: 1 | M18: 1 | N18: =SUM(N7:N17) -> 829155.9 | O18: =SUM(O7:O17) -> 53870.454 | P18: =N18*(1+$B$4)+O18*(1+$N$4)+B18*(1+$O$4) -> 4623093.6 | Q18: =SUM(Parameter!V19:V22)*(1+Q4) -> 1550340 | R18: =SUM('MHE&INV list'!K25:K53)*(1+R4)-SUMIF('MHE&INV list'!A:A,"Startup",'MHE&INV list'!K:K) -> 1056279.8 | S18: =R18+P18+Q18 -> 7229713.4 | T18: / | U18: /
E22: MHE: Y1 cost | F22: =VLOOKUP(F$6,'MHE&INV list'!$C$2:$K$10,9,0) -> 206400 | G22: =VLOOKUP(G$6,'MHE&INV list'!$C$2:$K$10,9,0) -> 120000 | I22: =VLOOKUP(I$6,'MHE&INV list'!$C$2:$K$10,9,0) -> 41520 | J22: =VLOOKUP(J$6,'MHE&INV list'!$C$2:$K$10,9,0) -> 100800 | K22: =VLOOKUP(K$6,'MHE&INV list'!$C$2:$K$10,9,0) -> 126000 | L22: =VLOOKUP(L$6,'MHE&INV list'!$C$2:$K$10,9,0) -> 230400 | M22: =VLOOKUP(M$6,'MHE&INV list'!$C$2:$K$10,9,0) -> 4035.9036
B36: Chinese labelling
B37: Count
B38: Customs inspection
B39: Engraved steal seal
B40: Inbound DG processing
B41: Inbound processing
B42: Key cutting handling
B43: Outbound processing
B44: Warranty & Return
B45: Warranty & Return DG
B46: Outbound DG processing

Sheet Volume
A2: 1. Inbound | M2: assumptions
B3: Start from 2026, Aug | M3: given
A4: Delivery lines inbound to PDC Shanghai | B4: 2026 | C4: 2027 | D4: 2028 | E4: 2029 | F4: 2030 | M4: calculation
A5: VOR | B5: =B7-B6 -> 28940.024 | C5: =C7-C6 -> 28071.824 | D5: =D7-D6 -> 27229.669 | E5: =E7-E6 -> 28046.559 | F5: =F7-F6 -> 28887.956
A6: VOL | B6: =B7*第二轮数据!$C$10 -> 177774.44 | C6: =C7*第二轮数据!$C$10 -> 172441.2 | D6: =D7*第二轮数据!$C$10 -> 167267.97 | E6: =E7*第二轮数据!$C$10 -> 172286.01 | F6: =F7*第二轮数据!$C$10 -> 177454.59
A7: Inbound normal | B7: =B9-B8 -> 206714.46 | C7: =C9-C8 -> 200513.03 | D7: =D9-D8 -> 194497.64 | E7: =E9-E8 -> 200332.56 | F7: =F9-F8 -> 206342.54
A8: Inbound DG lines | B8: =B9*第二轮数据!$C$8 -> 13194.54 | C8: =C9*第二轮数据!$C$8 -> 12798.704 | D8: =D9*第二轮数据!$C$8 -> 12414.743 | E8: =E9*第二轮数据!$C$8 -> 12787.185 | F8: =F9*第二轮数据!$C$8 -> 13170.801
A9: TTL inbound | B9: 219909 | C9: 213311.73 | D9: 206912.38 | E9: 213119.75 | F9: 219513.34
A10: Warranty and Returns&Scrapping (lines per year) | B10: 12943 | C10: 12554.71 | D10: 12178.069 | E10: 12543.411 | F10: 12919.713
A11: Cross Docking | B11: =B7*$H$11 -> 10335.723 | C11: =C7*$H$11 -> 10025.651 | D11: =D7*$H$11 -> 9724.8818 | E11: =E7*$H$11 -> 10016.628 | F11: =F7*$H$11 -> 10317.127 | H11: 0.05 | I11: cross dock vs. total inbound
A13: Freight CBM inbound to PDC Shanghai | B13: 2026 | H13: Total CBM - 2025
A14: Express (VOR) - Air | B14: 6447.8 | H14: =B14+B15 -> 57857.8
A15: Stock (VOL) - Seafreight | B15: 51410
A17: Freight kg inbound to PDC Shanghai | B17: 2026
A18: Express (VOR) - Air | B18: 414579
A19: Stock (VOL) - Seafreight | B19: 2474631
A21: Inbound Trasnportation Shipments Estimation for 2026
A22: Order type | B22: Shipment type | C22: Truck Size | D22: Loading Space | E22: Shipment Qty | F22: Check | H22: Total trucks/ cntr. - 2026
A23: Stock (VOL) | B23: Seafreight | C23: 40 HQ | E23: 678 | F23: 57.6 | H23: =SUM(E23:E31) -> 1408
A24: Stock (VOL) DG | B24: Seafreight | C24: 40 HQ | E24: 108 | F24: =F23 -> 57.6
A25: Stock (VOL) | B25: Seafreight | C25: 40 HQ | E25: 7 | F25: =F24 -> 57.6 | H25: DG - CBM | I25: DG - % in CBM | J25: DG - % in line
A26: Stock (VOL) DG | B26: Seafreight | C26: 40 HQ | E26: 2 | F26: =F25 -> 57.6 | H26: =(E26+E24)*F24+SUMPRODUCT(E29:E31,F29:F31) -> 9286 | I26: =H26/(B14+B15) -> 0.16049694 | J26: =第二轮数据!C50 -> 0.06
A27: Express (VOR) | B27: Airfreight | C27: 4.2M | D27: 10 cbm | E27: 110 | F27: 10
A28: Express (VOR) | B28: Airfreight | C28: 7.2M | D28: 30 cbm | E28: 266 | F28: 30
A29: Express (VOR) DG | B29: Airfreight | C29: 4.2M | D29: 10 cbm | E29: 203 | F29: 10
A30: Express (VOR) DG | B30: Airfreight | C30: 7.2M | D30: 30 cbm | E30: 29 | F30: 30
A31: Express (VOR) DG | B31: Airfreight | C31: 4.2M | D31: 10 cbm | E31: 5 | F31: 10
F32: =SUMPRODUCT(E23:E31,F23:F31) -> 57822 | G32: =F32-H14 -> -35.8
A33: 1.1 Inbound delivery line ratio depending on storage area
A35: Storage Area | B35: Dangerous Goods | C35: Floor Storage | D35: Locked / Lifestyle | E35: Mezzanine | F35: New Parts | G35: Pallet Racking | H35: Cross-Docking | I35: Coding | J35: Check
A36: Inbound (VOR + VOL) | B36: =第二轮数据!C8 -> 0.06 | C36: 0.3 | D36: 0 | E36: =第二轮数据!C16 -> 0.14 | F36: 0 | G36: 0.48 | H36: 0.02 | I36: 0 | J36: =SUM(B36:I36) -> 1
J37: =SUM(B37:I37) -> 0
J38: =SUM(B38:I38) -> 0
A40: Cal. Put away to zones by order type (lines)
A42: Storage Area | B42: Dangerous Goods | C42: Floor Storage | D42: Locked / Lifestyle | E42: Mezzanine | F42: New Parts | G42: Pallet Racking | H42: Cross-Docking | I42: Coding
A43: =A36 -> Inbound (VOR + VOL) | B43: =$B$7*B36 -> 12402.868 | C43: =$B$7*C36 -> 62014.338 | D43: =$B$7*D36 -> 0 | E43: =$B$7*E36 -> 28940.024 | F43: =$B$7*F36 -> 0 | G43: =$B$7*G36 -> 99222.941 | H43: =$B$7*H36 -> 4134.2892 | I43: =$B$7*I36 -> 0
A44: =A37 -> 0 | B44: =$B$6*B37 -> 0 | C44: =$B$6*C37 -> 0 | D44: =$B$6*D37 -> 0 | E44: =$B$6*E37 -> 0 | F44: =$B$6*F37 -> 0 | G44: =$B$6*G37 -> 0 | H44: =$B$6*H37 -> 0 | I44: =$B$6*I37 -> 0
A45: =A38 -> 0 | B45: =$B$10*B38 -> 0 | C45: =$B$10*C38 -> 0 | D45: =$B$10*D38 -> 0 | E45: =$B$10*E38 -> 0 | F45: =$B$10*F38 -> 0 | G45: =$B$10*G38 -> 0 | H45: =$B$10*H38 -> 0 | I45: =$B$10*I38 -> 0
A46: Sub-total lines - inbound | B46: =SUM(B43:B45) -> 12402.868 | C46: =SUM(C43:C45) -> 62014.338 | D46: =SUM(D43:D45) -> 0 | E46: =SUM(E43:E45) -> 28940.024 | F46: =SUM(F43:F45) -> 0 | G46: =SUM(G43:G45) -> 99222.941 | H46: =SUM(H43:H45) -> 4134.2892 | I46: =SUM(I43:I45) -> 0 | J46: =SUM(B46:I46) -> 206714.46
A47: % by put away zone in lines | B47: =B46/$J$46 -> 0.06 | C47: =C46/$J$46 -> 0.3 | D47: =D46/$J$46 -> 0 | E47: =E46/$J$46 -> 0.14 | F47: =F46/$J$46 -> 0 | G47: =G46/$J$46 -> 0.48 | H47: =H46/$J$46 -> 0.02 | I47: =I46/$J$46 -> 0
A48: % in ttl. Excl. new parts | B48: =B47/(1-$F$47) -> 0.06 | C48: =C47/(1-$F$47) -> 0.3 | D48: =D47/(1-$F$47) -> 0 | E48: =E47/(1-$F$47) -> 0.14 | G48: =G47/(1-$F$47) -> 0.48 | H48: =H47/(1-$F$47) -> 0.02 | I48: =I47/(1-$F$47) -> 0
A50: 2. Outbound
A52: Delivery lines outbound from PDC Shanghai | B52: 2026 | C52: 2027 | D52: 2028 | E52: 2029 | F52: 2030 | G52: % in TTL
A53: VOR | B53: =B56*$G$53 -> 83990.626 | C53: =C56*$G$53 -> 81470.907 | D53: =D56*$G$53 -> 79026.78 | E53: =E56*$G$53 -> 81397.583 | F53: =F56*$G$53 -> 83839.511 | G53: =第二轮数据!C24 -> 0.12
A54: Rush | B54: =B56*$G$54 -> 0 | C54: =C56*$G$54 -> 0 | D54: =D56*$G$54 -> 0 | E54: =E56*$G$54 -> 0 | F54: =F56*$G$54 -> 0 | G54: 0
A55: Stock | B55: =B56*$G$55 -> 615931.25 | C55: =C56*$G$55 -> 597453.32 | D55: =D56*$G$55 -> 579529.72 | E55: =E56*$G$55 -> 596915.61 | F55: =F56*$G$55 -> 614823.08 | G55: =1-G53-G54 -> 0.88
A56: Outbound normal | B56: =B58-B57 -> 699921.88 | C56: =C58-C57 -> 678924.22 | D56: =D58-D57 -> 658556.5 | E56: =E58-E57 -> 678313.19 | F56: =F58-F57 -> 698662.59
A57: Outbound DG lines | B57: =B58*第二轮数据!$C$21 -> 14284.12 | C57: =C58*第二轮数据!$C$21 -> 13855.596 | D57: =D58*第二轮数据!$C$21 -> 13439.929 | E57: =E58*第二轮数据!$C$21 -> 13843.126 | F57: =F58*第二轮数据!$C$21 -> 14258.42
A58: Total outbound lines | B58: 714206 | C58: 692779.82 | D58: 671996.43 | E58: 692156.32 | F58: 712921.01
A64: 2.1 Outbound delivery line ratio depending on storage area based on
A66: Storage Area | B66: Dangerous Goods | C66: Floor Storage | D66: Locked / Lifestyle | E66: Mezzanine | F66: New Parts | G66: Pallet Racking | H66: Cross-Docking | I66: Coding | J66: Check
A67: VOR | B67: =B69 -> 0.02 | C67: 0.15 | D67: 0 | E67: 0.45 | F67: 0 | G67: =G69-15% -> 0.38 | H67: 0 | I67: 0 | J67: =SUM(B67:I67) -> 1
A68: Rush | B68: 0 | C68: 0 | D68: 0 | E68: 0 | F68: 0 | G68: 0 | H68: 0 | I68: 0 | J68: =SUM(B68:I68) -> 0
A69: Stock | B69: =第二轮数据!C21 -> 0.02 | C69: 0.15 | D69: 0.01 | E69: =第二轮数据!C30 -> 0.29 | F69: =F68 -> 0 | G69: =第二轮数据!C28+第二轮数据!C29-1%+15% -> 0.53 | H69: 0 | I69: 0 | J69: =SUM(B69:I69) -> 1
A72: Storage Area | B72: Dangerous Goods | C72: Floor Storage | D72: Locked / Lifestyle | E72: Mezzanine | F72: New Parts | G72: Pallet Racking | H72: Cross-Docking | I72: Coding
A73: VOR | B73: =$B$53*B67 -> 1679.8125 | C73: =$B$53*C67 -> 12598.594 | D73: =$B$53*D67 -> 0 | E73: =$B$53*E67 -> 37795.782 | F73: =$B$53*F67 -> 0 | G73: =$B$53*G67 -> 31916.438 | H73: =$B$53*H67 -> 0 | I73: =$B$53*I67 -> 0
A74: Rush | B74: =$B$54*B68 -> 0 | C74: =$B$54*C68 -> 0 | D74: =$B$54*D68 -> 0 | E74: =$B$54*E68 -> 0 | F74: =$B$54*F68 -> 0 | G74: =$B$54*G68 -> 0 | H74: =$B$54*H68 -> 0 | I74: =$B$54*I68 -> 0
A75: Stock | B75: =$B$55*B69 -> 12318.625 | C75: =$B$55*C69 -> 92389.688 | D75: =$B$55*D69 -> 6159.3125 | E75: =$B$55*E69 -> 178620.06 | F75: =$B$55*F69 -> 0 | G75: =$B$55*G69 -> 326443.56 | H75: =$B$55*H69 -> 0 | I75: =$B$55*I69 -> 0
A76: Sub-total lines - Outbound | B76: =SUM(B73:B75) -> 13998.438 | C76: =SUM(C73:C75) -> 104988.28 | D76: =SUM(D73:D75) -> 6159.3125 | E76: =SUM(E73:E75) -> 216415.85 | F76: =SUM(F73:F75) -> 0 | G76: =SUM(G73:G75) -> 358360 | H76: =SUM(H73:H75) -> 0 | I76: =SUM(I73:I75) -> 0 | J76: =SUM(B76:I76) -> 699921.88
A77: % by picking zone in lines | B77: =B76/$J$76 -> 0.02 | C77: =C76/$J$76 -> 0.15 | D77: =D76/$J$76 -> 0.0088 | E77: =E76/$J$76 -> 0.3092 | F77: =F76/$J$76 -> 0 | G77: =G76/$J$76 -> 0.512 | H77: =H76/$J$76 -> 0 | I77: =I76/$J$76 -> 0
A80: 3. Special Processes
A82: Process | B82: 2026 | C82: 2027 | D82: 2028 | E82: 2029 | F82: 2030
A83: Inventory (Counting lines per year) | B83: 117666 | C83: 114136.02 | D83: 110711.94 | E83: 114033.3 | F83: 117454.3
A84: Warranty and Returns&Scrapping (lines per year) | B84: 12943 | C84: 12554.71 | D84: 12178.069 | E84: 12543.411 | F84: 12919.713
A85: Chinese labeling (pieces per year) | B85: 1976652 | C85: 1917352.4 | D85: 1859831.9 | E85: 1915626.8 | F85: 1973095.6
A86: Customs inspection (lines per year) | B86: 1800 | C86: 1746 | D86: 1693 | E86: 1778 | F86: 1867
A87: Key cutting(per year) | B87: 2880 | C87: 2793 | D87: 2598 | E87: 2468 | F87: 2344

Sheet 第二轮数据
B1: Inbound
B2: unloading - pallet | C2: 0.5
B3: unloading - mix SKU carton | C3: 0.5
B4: inbound orderlines per HU | C4: 2.4
B5: inbound pcs per orderline | C5: 15.19 | E5: 和D19不一样， 用C5
B6: full inspection | C6: 3%-8%
B8: DG rate in overall inbound orderline | C8: 0.06
C9: orderline %
B10: Stock (VOL) | C10: 0.86
B11: Express (VOR) | C11: 0.12
B12: EXPRESS | C12: 0.02 | D12: *这里不懂为什么还有个EXPRSS，建议可以并进VOR
C14: orderline % | D14: pcs/line
B15: Large/Bulky | C15: 0.58 | D15: 4 | F15: 0.3
B16: M2 | C16: 0.14 | D16: 40
B17: M1 | C17: 0.06 | D17: 36 | F17: 0.5
B18: Small | C18: 0.14 | D18: 9
D19: =SUMPRODUCT(C15:C18,D15:D18) -> 11.34
B20: Outbound
B21: DG rate in overall outbound orderline | C21: 0.02
C22: orderline % | E22: Check back
B23: Stock (VOL) | C23: 0.88 | E23: =Parameter!R99 -> 6
B24: Express (VOR) | C24: 0.12 | E24: =Parameter!R94 -> 2
C26: orderline % | E26: check back
B27: Large/Bulky | C27: 0.3 | E27: 1
B28: M2 | C28: 0.27 | E28: =Parameter!R79 -> 6.5
B29: M1 | C29: 0.12 | E29: =E28 -> 6.5
B30: Small | C30: 0.29 | E30: =Parameter!R69 -> 6.5
B32: Outbound pcs per orderline | C32: 4.67 | E32: =SUMPRODUCT(C27:C30,E27:E30) -> 4.72
B33: Outbound orderlines/outbound pack | C33: 5 | E33: =SUMPRODUCT(C23:C24,E23:E24) -> 5.52
B35: Storage
C36: location #
B37: Shelves | C37: 22863 | D37: =C37/SUM($C$37:$C$40) -> 0.59025662
B38: Medium | C38: 8505 | D38: =C38/SUM($C$37:$C$40) -> 0.21957453
B39: Large | C39: 6979 | D39: =C39/SUM($C$37:$C$40) -> 0.18017762
B40: Bulky | C40: 387 | D40: =C40/SUM($C$37:$C$40) -> 0.0099912222
B42: SKU count | C42: 25000
B43: Large/Bulky | C43: 0.23 | D43: 5750
B44: M2 | C44: 0.2 | D44: 5000
B45: M1 | C45: 0.27 | D45: 6750
B46: Small | C46: 0.3 | D46: 7500
B49: DG
B50: Inbound orderline % | C50: 0.06
B51: Inbound pcs/orderline | C51: 1.7
B52: Outbound orderline % | C52: 0.02
B53: Outbound pcs/orderline | C53: 1.69
B54: Outbound orderline Y2026 | C54: 14360
B55: Outbound piece Y2026 | C55: 27000
B58: Shelf life management | C58: 0.09
B60: engraved steal seal volume | C60: 12 | D60: pc/year
B62: Insurance
B63: Inventory value - main | C63: 353mio
B64: Inventory value - DG | C64: 47mio

Sheet Layout 
O9: 187 | P9: Y
O10: 100
O11: 200
O12: 94 | P12: Y
O13: 163 | P13: Y
O14: 243 | P14: Y
O15: 55
O16: 65
O17: 646
O18: 2230
O19: 6561
O20: 115
O21: 55
O22: 1174
O23: 300
O24: 738
O25: 800
O26: 159
... O28: 2470
N30: C3 total | O30: =SUM(O9:O28) -> 22227 | P30: sqm

Sheet Parameter
B2: FACILITY | E2: =E5+J5+J19 -> 28927 | N2: STAFFING
O4: Site working days/year | P4: 293 | V4: [Y(n+1)/Y(n)]
C5: Building | D5: C3 | E5: =SUM(E9:E29) -> 22727 | H5: Building | I5: C2 | J5: =SUM(J9:J17) -> 5200 | O5: Site open time | P5: 8 | V5: Y1 | W5: Y2 | X5: Y3 | Y5: Y4 | Z5: Y5
C6: Nb. Chamber | D6: 4 | E6: =E5/D6 -> 5681.75 | F6: L 60 m x D 90m | H6: Nb. Chamber | I6: 1 | J6: =J5/I6 -> 5200 | K6: L 60 m x D 90m | O6: FTE Working hours/day | P6: 8 | U6: IB+OB growth | V6: 1 | W6: =(Volume!C7+Volume!C56)/(Volume!B7+Volume!B56) -> 0.97 | X6: =(Volume!D7+Volume!D56)/(Volume!C7+Volume!C56) -> 0.97 | Y6: =(Volume!E7+Volume!E56)/(Volume!D7+Volume!D56) -> 1.03 | Z6: =(Volume!F7+Volume!F56)/(Volume!E7+Volume!E56) -> 1.03
O7: Unproductivity rate | P7: 0.85 | U7: Prod. factor | V7: 1 | W7: 1 | X7: 0.98 | Y7: 1 | Z7: 1
C8: No. | D8: Area Name | E8: Space (m2) | F8: Ref. distance (m) | H8: No. | I8: Area Name | J8: Space (m2) | K8: Ref. distance (m) | U8: FTE increase | V8: 1 | W8: =V8*W6*W7 -> 0.97 | X8: =W8*X6*X7 -> 0.922082 | Y8: =X8*Y6*Y7 -> 0.94974446 | Z8: =Y8*Z6*Z7 -> 0.97823679
C9: 1 | D9: QC and return | E9: 187 | H9: 1 | I9: Slow move sto. | J9: 5200 | K9: =SQRT(J9) -> 72.111026
C10: 2 | D10: Home Charging | E10: 100 | O10: Role | P10: TTL. Annual cost | Q10: Salary/month | R10: Company cost % | S10: OT/ year | T10: Annual increase | U10: FTE Qty.-Y1
C11: 3 | D11: Labelling | E11: 200 | O11: Documentation | P11: =Q11*(1+R11)*12+S11 -> 126411.59 | Q11: 7500 | R11: 0.4 | S11: =Q11/(8*20.5)*1.5*6 -> 411.58537 | T11: 1.07 | U11: =SUMIF(Process!O:O,Parameter!O11,Process!P:P) -> 0.29411765 | V11: =SUM(U11:U18) -> 35.176771 | X11: blue collar round up factor
C12: 4 | D12: Cross docking | E12: 94 | O12: IB Planner | P12: =Q12*(1+R12)*12+S12 -> 126068.6 | Q12: 7500 | R12: 0.4 | S12: =Q12/(8*20.5)*1.5 -> 68.597561 | T12: 1.07 | U12: =SUMIF(Process!O:O,Parameter!O12,Process!P:P) -> 2.0395536 | V12: =SUM(U19:U21) -> 5
C13: 5 | D13: Inbound Airfreight | E13: 163 | F13: =SQRT(E13) -> 12.767145 | O13: Inv. Operator | P13: =Q13*(1+R13)*12+S13 -> 100854.88 | Q13: 6000 | R13: 0.4 | S13: =Q13/(8*20.5)*1.5 -> 54.878049 | T13: 1.07 | U13: =SUMIF(Process!O:O,Parameter!O13,Process!P:P) -> 1.3273568 | V13: =V12/V11 -> 0.14213925
C14: 6 | D14: Seafreight Presort | E14: 243 | F14: =SQRT(E14) -> 15.588457 | O14: MHE Driver | P14: =Q14*(1+R14)*12+S14 -> 100854.88 | Q14: 6000 | R14: 0.4 | S14: =Q14/(8*20.5)*1.5 -> 54.878049 | T14: 1.07 | U14: =SUMIF(Process!O:O,Parameter!O14,Process!P:P) -> 11.791417
C15: 7 | D15: PDS Locked Room | E15: 55 | O15: Operator | P15: =Q15*(1+R15)*12+S15 -> 84045.732 | Q15: 5000 | R15: 0.4 | S15: =Q15/(8*20.5)*1.5 -> 45.731707 | T15: 1.07 | U15: =SUMIF(Process!O:O,Parameter!O15,Process!P:P) -> 8.5715752
C16: 8 | D16: Key Cutting Room | E16: 65 | O16: Packer | P16: =Q16*(1+R16)*12+S16 -> 84045.732 | Q16: 5000 | R16: 0.4 | S16: =Q16/(8*20.5)*1.5 -> 45.731707 | T16: 1.07 | U16: =SUMIF(Process!O:O,Parameter!O16,Process!P:P) -> 8.4967736
C17: 9 | D17: Seafreight Unload | E17: 646 | F17: =SQRT(E17) -> 25.41653 | O17: DG operator | P17: =Q17*(1+R17)*12+S17 -> 100854.88 | Q17: 6000 | R17: 0.4 | S17: =Q17/(8*20.5)*1.5 -> 54.878049 | T17: 1.07 | U17: =SUMIF(Process!O:O,Parameter!O17,Process!P:P) -> 2.0465715
C18: 10 | D18: Medium Parts Rack | E18: 2230 | F18: =SQRT(E18) -> 47.222876 | O18: Special handling | P18: =Q18*(1+R18)*12+S18 -> 100854.88 | Q18: 6000 | R18: 0.4 | S18: =Q18/(8*20.5)*1.5 -> 54.878049 | T18: 1.07 | U18: =SUMIF(Process!O:O,Parameter!O18,Process!P:P) -> 0.60940622 | V18: Indirect staffing annual cost
C19: 11 | D19: Large Parts Rack | E19: 6561 | F19: =SQRT(E19) -> 81 | H19: Building | I19: C5 | J19: =SUM(J23:J29) -> 1000 | O19: DC manager | P19: =Q19*(1+R19)*12+S19 -> 435000 | Q19: 25000 | R19: 0.45 | S19: 0 | T19: 1.03 | U19: 1 | V19: =U19*$P19 -> 435000 | W19: =V19*$T19 -> 448050 | X19: =W19*$T19 -> 461491.5 | Y19: =X19*$T19 -> 475336.24 | Z19: =Y19*$T19 -> 489596.33
C20: 12 | D20: Customs inspect | E20: 115 | H20: Nb. Chamber | I20: 1 | J20: =J19/I20 -> 1000 | K20: L 9m x D 11m | O20: Supervisor | P20: =Q20*(1+R20)*12+S20 -> 313200 | Q20: 18000 | R20: 0.45 | S20: 0 | T20: 1.03 | U20: 2 | V20: =U20*$P20 -> 626400 | W20: =V20*$T20 -> 645192 | X20: =W20*$T20 -> 664547.76 | Y20: =X20*$T20 -> 684484.19 | Z20: =Y20*$T20 -> 705018.72 | AA20: 可考虑减少1个Supervisor的配置
C21: 13 | D21: Floor Storage | E21: 555 | F21: =SQRT(E21) -> 23.558438 | O21: Team leader | P21: =Q21*(1+R21)*12+S21 -> 174000 | Q21: 10000 | R21: 0.45 | S21: 0 | T21: 1.03 | U21: =ROUND(SUM(U11:U18)/15,0) -> 2 | V21: =U21*$P21 -> 348000 | W21: =V21*$T21 -> 358440 | X21: =W21*$T21 -> 369193.2 | Y21: =X21*$T21 -> 380269 | Z21: =Y21*$T21 -> 391677.07
C22: 14 | D22: Shelves Area | E22: 1174 | F22: =SQRT(E22) -> 34.263683 | H22: No. | I22: Area Name | J22: Space (m2) | K22: Ref. distance (m) | P22: =Q22*(1+R22)*12+S22 -> 0 | V22: =U22*$P22 -> 0 | W22: =V22*$T22 -> 0 | X22: =W22*$T22 -> 0 | Y22: =X22*$T22 -> 0 | Z22: =Y22*$T22 -> 0
C23: 15 | D23: VOR Packing | E23: 300 | H23: 1 | I23: Non-critical DG | J23: 1000 | K23: =SQRT(J23) -> 31.622777
C24: 16 | D24: Stock Packing C303 | E24: 738
C25: 17 | D25: Stock Packing C302 | E25: 800
C26: 18 | D26: Packaging Storage | E26: 159
C27: 19 | D27: Floor Storage C301 | E27: 5872 | F27: =SQRT(E27) -> 76.628976 | P27: Inbound lines/year | R27: =Volume!B7+Volume!B11 -> 217050.18 | S27: incl. return
C28: 20 | D28: Canopy | E28: 2470 | P28: Inbound lines/day | R28: =R27/Parameter!P4 -> 740.78561
C29: 21 | D29: Other public Area | P29: Outbound lines/year | R29: =Volume!B56 -> 699921.88
P30: Outbound lines/day | R30: =R29/Parameter!P4 -> 2388.8119
H31: Exluding slow moving
C32: Total storage space - non DG | E32: =E18+E19+E21+E22+E27+J5 -> 21592 | F32: =E32/$E$2 -> 0.74643067 | H32: =E32-J5 -> 16392 | I32: % in C3 | O32: Process - Tier 1 | R32: Assumption/ Cal. | S32: UOM
D33: Racking | E33: =E18+E19 -> 8791 | F33: =E33/$E$32 -> 0.40714153 | H33: =E33 -> 8791 | I33: =H33/$H$32 -> 0.53629819 | O33: Inbound processing | P33: Unloading | R33: =(Volume!B7+Volume!B11)/Volume!H23 -> 154.15496 | S33: line per truck/cntr.
D34: Floor | E34: =E21+E27+J5 -> 11627 | F34: =E34/$E$32 -> 0.53848648 | H34: =E34-J5 -> 6427 | I34: =H34/$H$32 -> 0.3920815 | R34: =1.2*0.8*1.5 -> 1.44 | S34: CBM per HU
D35: Shelving | E35: =E22 -> 1174 | F35: =E35/$E$32 -> 0.05437199 | H35: =E35 -> 1174 | I35: =H35/$H$32 -> 0.071620303 | R35: =Volume!H14/Volume!H23/Parameter!R34 -> 28.536241 | S35: HU per truck/cntr. | T35: =R35*Volume!H23/P4 -> 137.12979 | U35: HU per day
C36: Total storage space - DG | E36: =J23 -> 1000 | F36: =E36/$E$2 -> 0.034569779 | R36: 1 | S36: HU per trip
C37: Total packing space | E37: =E23+E24+E25+E26 -> 1997 | F37: =E37/$E$2 -> 0.069035849 | P37: Customs inspection | R37: 1 | S37: lines per trip
C38: Total staging incl. canopy | E38: =E13+E14+E17+E28+E12+E20 -> 3731 | F38: =E38/$E$2 -> 0.12897985 | P38: Sorting ALL | R38: =第二轮数据!C3 -> 0.5 | S38: mixed HU | T38: =T35*R38 -> 68.564894 | U38: Mixed HU
C39: Labelling space | E39: =E11 -> 200 | F39: =E39/$E$2 -> 0.0069139558 | R39: =第二轮数据!C5 -> 15.19 | S39: Piece per line | T39: =T35-T38 -> 68.564894 | U39: Single HU
R40: =(R28-T39)/T38 -> 9.8041531 | S40: line per mixed HU
C41: Distance | P41: New parts handling | R41: =Volume!F47 -> 0 | S41: of total inbound | T41: full inspeciton | U41: 0.06 | V41: (3%~8%)
P42: Warranty and Return | R42: 2 | S42: Piece per line
C43: No. | D43: From | E43: To | F43: Index | G43: Percent | H43: Distance (M-Single trip) | P43: X-dock movement | R43: =Volume!H11 -> 0.05 | S43: on above of total inbound
F44: HDL | H44: 0 | R44: =Parameter!R28*R43 -> 37.03928 | S44: line per day
D45: Inbound Dock | E45: IB Unloading | F45: IBU | G45: 1 | H45: 110 | I45: Y | R45: 1 | S45: lines per trip
C46: 1 | D46: Inbound Dock | E46: IB Sorting | F46: IBS | G46: 1 | H46: 40 | I46: Y
C47: 2 | D47: Inbound Dock | E47: XDO | F47: IBXDO | G47: 1 | H47: 30 | I47: Y | P47: DG - C5 | R47: =Volume!B8/Parameter!P4 -> 45.03256 | S47: lines per day
C48: 3 | D48: Inbound Dock | E48: Packing(Type B) | F48: IBSP | P48: DG - external | T48: TBD
D49: IB Sorting | E49: Floor1 Staging | F49: IBSF1 | G49: 1 | H49: =220/2 -> 110 | I49: Y
D50: IB Sorting | E50: Floor2 Staging | F50: IBSF2 | G50: 0 | I50: Y | P50: Put away - Shelving | Q50: Shelving | R50: =Parameter!R28*Volume!E48 -> 103.70999 | S50: lines per day
C51: 4 | D51: IB Sorting | E51: Floor Staging | F51: IBSF | H51: =H49*G49+H50*G50 -> 110 | I51: Y | R51: 8 | S51: lines per trip
D52: IB Sorting | E52: Racking1 Staging | F52: IBSR1 | G52: 0.6 | H52: =130/2 -> 65 | I52: Y | R52: 0 | S52: lines through elevator
D53: IB Sorting | E53: Racking2 Staging | F53: IBSR2 | G53: 0.4 | H53: =190/2 -> 95 | I53: Y
D54: IB Sorting | E54: Racking3 Staging | F54: IBSR3 | G54: 0 | H54: 0 | I54: Y | P54: Put away - Floor | Q54: Floor | R54: =Parameter!R28*Volume!C48 -> 222.23568 | S54: lines per day
C55: 5 | D55: IB Sorting | E55: Racking Staging | F55: IBSR | H55: =H52*G52+H53*G53+H54*G54 -> 77 | I55: Y | R55: 1 | S55: lines per trip
D56: IB Sorting | E56: VNA1_P&D | F56: IBSV1
D57: IB Sorting | E57: VNA2_P&D | F57: IBSV2 | P57: Put away - Racking | R57: =Parameter!R28*Volume!G48 -> 355.57709 | S57: lines per day
D58: IB Sorting | E58: VNA3_P&D | F58: IBSV3 | P58: a) by pallet | R58: 1 | S58: lines per trip
C59: 6 | D59: IB Sorting | E59: VNA P&D | F59: IBSV | H59: =H56*G56+H57*G57+H58*G58 -> 0 | P59: b) by case | R59: 0.2 | S59: of total racking put away lines
C60: 7 | D60: IB Sorting | E60: Mezzanine Staging | F60: IBSM | G60: 1 | H60: 150 | I60: Y | R60: 4 | S60: case/line
C61: 8 | D61: IB Sorting | E61: C5 staging | F61: IBSC | H61: 320 | I61: Y
C62: 9 | D62: IB Sorting | E62: Lifestyle Staging | F62: IBSL | H62: 0 | P62: Put away - DG （C5) | R62: =第二轮数据!C4 -> 2.4 | S62: lines per trip
D63: Floor1 Staging | E63: Packing | F63: OBF1P | G63: 0.7 | H63: =H49-90 -> 20
D64: Floor2 Staging | E64: Packing | F64: OBF2P | G64: 0.3 | H64: =H63-30 -> -10 | P64: Put away - Others (e.g. locker) | R64: =(Volume!D48+Volume!I48)*Parameter!R28 -> 0 | S64: Other lines
C65: 10 | D65: Floor Staging | E65: Packing | F65: OBFP | H65: =H63*G63+H64*G64 -> 11 | I65: Y | R65: 4 | S65: lines per trip
D66: Racking1 Staging | E66: Packing | F66: OBR1P | G66: 0.6 | H66: =H52 -> 65 | I66: Y
D67: Racking2 Staging | E67: Packing | F67: OBR2P | G67: 0.4 | H67: =H53 -> 95 | I67: Y | O67: Outbound processing | P67: Pick from shelving | R67: =Volume!E77*Parameter!R30 -> 738.62063 | S67: line
D68: Racking3 Staging | E68: Packing | F68: OBR3P | G68: 0 | R68: 24 | S68: lines per trip
C69: 11 | D69: Racking Staging | E69: Packing | F69: OBRP | H69: =H66*G66+H67*G67+H68*G68 -> 77 | I69: Y | R69: 6.5 | S69: pieces per line
D70: VNA1_P&D | E70: Packing | F70: OBV1P | R70: =R52 -> 0 | S70: lines through elevator
D71: VNA2_P&D | E71: Packing | F71: OBV2P
D72: VNA3_P&D | E72: Packing | F72: OBV3P | P72: Pick from Floor | R72: =Volume!C77*Parameter!R30 -> 358.32178 | S72: line
C73: 12 | D73: VNA P&D | E73: Packing | F73: OBVP | R73: 1 | S73: line per trip
C74: 13 | D74: Mezzanine Staging | E74: Packing | F74: OBMP | H74: 55 | I74: Y
C75: 14 | D75: C5 Staging | E75: Packing | F75: OBCP | H75: 160 | I75: Y | P75: Pick from Racking | R75: =Volume!G77*Parameter!R30 -> 1223.0717 | S75: line
C76: 15 | D76: Others picking | E76: Workstation | F76: OBLP | H76: 30 | I76: Y | R76: 6 | S76: line per trip
C77: 16 | D77: XDO | E77: Handover | F77: OBXDOH | H77: 120 | I77: Y | R77: 0.3 | S77: from ground level
C78: 17 | D78: Packing(Type_B) | E78: Handover | F78: OBPH | H78: 60 | I78: Y | R78: =1-R77 -> 0.7 | S78: from upper level
C79: 18 | D79: Packing | E79: Handover | F79: OBPH | H79: 60 | I79: Y | R79: 6.5 | S79: pieces per line
C80: 19 | D80: Floor | E80: Line | F80: FL | H80: =60/R55 -> 60 | I80: Y
C81: 20 | D81: Floor | E81: Aisle | F81: FA | H81: 90 | I81: Y | P81: Replenishiment | Q81: Racking | R81: =Parameter!R75 -> 1223.0717 | S81: line
C82: 21 | D82: Racking | E82: Line | F82: RL | H82: =30/R58 -> 30 | I82: Y | R82: 0 | S82: line per trip
C83: 22 | D83: Racking | E83: Height | F83: RH | H83: 9 | I83: Y
C84: 23 | D84: Racking | E84: Aisle | F84: RA | H84: 80 | I84: Y | P84: Shelf life checking | R84: =第二轮数据!C58 -> 0.09 | S84: of total ob. Lines
C85: 28 | D85: Mezzanine | E85: Line | F85: ML | H85: =80/Parameter!R51 -> 10 | I85: Y
C86: 29 | D86: Mezzanine | E86: Aisle | F86: MA | H86: 20 | I86: Y
C87: 30 | D87: Mezzanine | E87: Elevator | F87: ME | H87: 0 | I87: Y | P87: Pick from DG-C5 | Q87: DC-C5 | R87: =Volume!B77*Parameter!R30 -> 47.776238 | S87: line
C88: 31 | D88: C5 | E88: Line | F88: CL | H88: 30 | I88: Y | R88: =R62 -> 2.4 | S88: line per trip
C89: 32 | D89: C5 | E89: Aisle | F89: CA | H89: 30 | I89: Y
C90: 33 | D90: Lifestyle | E90: Line | F90: LL | P90: Pick from Others | R90: =Volume!D77+Volume!I77 -> 0.0088 | S90: of total ob. Lines
C91: 34 | D91: Lifestyle | E91: Aisle | F91: LA
C92: 35 | D92: CS inspection | E92: Staging | F92: CS | H92: 90 | I92: Y | P92: Packing VOR | R92: =(Volume!G53*(1-Parameter!R101))*Parameter!R30 -> 243.65881 | S92: line
R93: 13 | S93: pieces per line
R94: 2 | S94: lines/ packing carton
R95: 4 | S95: hours_service level
P97: Packing Stock | R97: =Volume!G55*(1-Parameter!R101)*Parameter!R30 -> 1786.8313 | S97: RUSH/Stock line
R98: =Parameter!R93 -> 13 | S98: pcs/line
R99: 6 | S99: lines/ packing carton
P101: Packing Bulk | R101: =Volume!C77 -> 0.15 | S101: (assume same as floor picking)
R102: =R101*Parameter!R30 -> 358.32178 | S102: line
R103: 1 | S103: pieces per line
P105: Consolidate packing | R105: 6 | S105: small case /pallet
...

Sheet Process
A1: No. | B1: Rate-operation | C1: Area-2 | D1: Main-Process | E1: Sub-Process | F1: Daily Volume (2026) | G1: UOM (HU) | H1: Index | I1: Distance (m) | J1: MHE | K1: MHE speed | L1: Time (sec.) - movement | M1: Time (sec.) /handling | N1: Total Time (sec.) | O1: Role | P1: FTE | Q1: Packing Station | R1: HPJ with Scale | S1: Customize 1 | T1: Customize 2 | U1: Customize 3 | V1: Customize 4 | W1: Customize 5 | X1: FTE-Y2 | Y1: FTE-Y3 | Z1: FTE-Y4 | AA1: FTE-Y5 | AB1: FTE Cost - Y1 | AC1: FTE Cost - Y2 | AD1: FTE Cost - Y3 | AE1: FTE Cost - Y4 | AF1: FTE Cost - Y5
A2: =ROW()-1 -> 1 | B2: Inbound processing | C2: Make IB plan | D2: Make IB plan and paper work | E2: Check IB Plan | F2: 1 | G2: Daily | H2: HDL | I2: =IFERROR(VLOOKUP(H2,Parameter!$F$44:$H$92,3,0),"") -> 0 | J2: Manual | K2: =IFERROR(INDEX(Parameter!$D$122:$M$122,1,MATCH(Process!$J2,Parameter!$D$121:$M$121,0)),"") -> 1.2 | L2: =IFERROR(I2/K2,0) -> 0 | M2: =2*3600 -> 7200 | N2: =L2+M2 -> 7200 | O2: IB Planner | P2: =N2*F2/3600/Parameter!$P$6/Parameter!$P$7 -> 0.29411765 | X2: =P2*Parameter!W$8 -> 0.28529412 | Y2: =X2*Parameter!X$8 -> 0.26306457 | Z2: =Y2*Parameter!Y$8 -> 0.24984412 | AA2: =Z2*Parameter!Z$8 -> 0.24440671 | AB2: =VLOOKUP(O2,Parameter!$O$11:$P$22,2,0)*Process!P2 -> 37078.999 | AC2: =VLOOKUP($O2,Parameter!$O$11:$P$22,2,0)*VLOOKUP($O2,Parameter!$O$11:$T$22,6,0)*X2 -> 38484.293 | AD2: =VLOOKUP($O2,Parameter!$O$11:$P$22,2,0)*VLOOKUP($O2,Parameter!$O$11:$T$22,6,0)^2*Y2 -> 37969.671 | AE2: =VLOOKUP($O2,Parameter!$O$11:$P$22,2,0)*VLOOKUP($O2,Parameter!$O$11:$T$22,6,0)^3*Z2 -> 38585.789 | AF2: =VLOOKUP($O2,Parameter!$O$11:$P$22,2,0)*VLOOKUP($O2,Parameter!$O$11:$T$22,6,0)^4*AA2 -> 40388.261
A3: =ROW()-1 -> 2 | B3: Inbound processing | C3: Good Receiving | D3: Checking truck / container before unloading | E3: Adjust Dock | F3: =Volume!H23/Parameter!P4 -> 4.8054608 | G3: Truck/Ctnr. | H3: HDL | I3: =IFERROR(VLOOKUP(H3,Parameter!$F$44:$H$92,3,0),"") -> 0 | J3: Manual | K3: =IFERROR(INDEX(Parameter!$D$122:$M$122,1,MATCH(Process!$J3,Parameter!$D$121:$M$121,0)),"") -> 1.2 | L3: =IFERROR(I3/K3,0) -> 0 | M3: 120 | N3: =L3+M3 -> 120 | O3: Operator | P3: =N3*F3/3600/Parameter!$P$6/Parameter!$P$7 -> 0.02355618 | X3: =P3*Parameter!W$8 -> 0.022849495 | Y3: =X3*Parameter!X$8 -> 0.021069108 | Z3: =Y3*Parameter!Y$8 -> 0.020010268 | AA3: =Z3*Parameter!Z$8 -> 0.019574781 | AB3: =VLOOKUP(O3,Parameter!$O$11:$P$22,2,0)*Process!P3 -> 1979.7964 | AC3: =VLOOKUP($O3,Parameter!$O$11:$P$22,2,0)*VLOOKUP($O3,Parameter!$O$11:$T$22,6,0)*X3 -> 2054.8307 | AD3: =VLOOKUP($O3,Parameter!$O$11:$P$22,2,0)*VLOOKUP($O3,Parameter!$O$11:$T$22,6,0)^2*Y3 -> 2027.353 | AE3: =VLOOKUP($O3,Parameter!$O$11:$P$22,2,0)*VLOOKUP($O3,Parameter!$O$11:$T$22,6,0)^3*Z3 -> 2060.2499 | AF3: =VLOOKUP($O3,Parameter!$O$11:$P$22,2,0)*VLOOKUP($O3,Parameter!$O$11:$T$22,6,0)^4*AA3 -> 2156.4912
A4: =ROW()-1 -> 3 | B4: Inbound processing | C4: Good Receiving | D4: Checking truck / container before unloading | E4: Safety Confirm | F4: =F3 -> 4.8054608 | G4: Truck/Ctnr. | H4: HDL | I4: =IFERROR(VLOOKUP(H4,Parameter!$F$44:$H$92,3,0),"") -> 0 | J4: Manual | K4: =IFERROR(INDEX(Parameter!$D$122:$M$122,1,MATCH(Process!$J4,Parameter!$D$121:$M$121,0)),"") -> 1.2 | L4: =IFERROR(I4/K4,0) -> 0 | M4: 90 | N4: =L4+M4 -> 90 | O4: Operator | P4: =N4*F4/3600/Parameter!$P$6/Parameter!$P$7 -> 0.017667135 | X4: =P4*Parameter!W$8 -> 0.017137121 | Y4: =X4*Parameter!X$8 -> 0.015801831 | Z4: =Y4*Parameter!Y$8 -> 0.015007701 | AA4: =Z4*Parameter!Z$8 -> 0.014681086 | AB4: =VLOOKUP(O4,Parameter!$O$11:$P$22,2,0)*Process!P4 -> 1484.8473 | AC4: =VLOOKUP($O4,Parameter!$O$11:$P$22,2,0)*VLOOKUP($O4,Parameter!$O$11:$T$22,6,0)*X4 -> 1541.123 | AD4: =VLOOKUP($O4,Parameter!$O$11:$P$22,2,0)*VLOOKUP($O4,Parameter!$O$11:$T$22,6,0)^2*Y4 -> 1520.5147 | AE4: =VLOOKUP($O4,Parameter!$O$11:$P$22,2,0)*VLOOKUP($O4,Parameter!$O$11:$T$22,6,0)^3*Z4 -> 1545.1875 | AF4: =VLOOKUP($O4,Parameter!$O$11:$P$22,2,0)*VLOOKUP($O4,Parameter!$O$11:$T$22,6,0)^4*AA4 -> 1617.3684
A5: =ROW()-1 -> 4 | B5: Inbound processing | C5: Good Receiving | D5: Checking truck / container before unloading | E5: Check IB DN | F5: =F4 -> 4.8054608 | G5: Truck/Ctnr. | H5: HDL | I5: =IFERROR(VLOOKUP(H5,Parameter!$F$44:$H$92,3,0),"") -> 0 | J5: Manual | K5: =IFERROR(INDEX(Parameter!$D$122:$M$122,1,MATCH(Process!$J5,Parameter!$D$121:$M$121,0)),"") -> 1.2 | L5: =IFERROR(I5/K5,0) -> 0 | M5: 15 | N5: =L5+M5 -> 15 | O5: Operator | P5: =N5*F5/3600/Parameter!$P$6/Parameter!$P$7 -> 0.0029445225 | X5: =P5*Parameter!W$8 -> 0.0028561868 | Y5: =X5*Parameter!X$8 -> 0.0026336385 | Z5: =Y5*Parameter!Y$8 -> 0.0025012836 | AA5: =Z5*Parameter!Z$8 -> 0.0024468476 | AB5: =VLOOKUP(O5,Parameter!$O$11:$P$22,2,0)*Process!P5 -> 247.47455 | AC5: =VLOOKUP($O5,Parameter!$O$11:$P$22,2,0)*VLOOKUP($O5,Parameter!$O$11:$T$22,6,0)*X5 -> 256.85384 | AD5: =VLOOKUP($O5,Parameter!$O$11:$P$22,2,0)*VLOOKUP($O5,Parameter!$O$11:$T$22,6,0)^2*Y5 -> 253.41912 | AE5: =VLOOKUP($O5,Parameter!$O$11:$P$22,2,0)*VLOOKUP($O5,Parameter!$O$11:$T$22,6,0)^3*Z5 -> 257.53124 | AF5: =VLOOKUP($O5,Parameter!$O$11:$P$22,2,0)*VLOOKUP($O5,Parameter!$O$11:$T$22,6,0)^4*AA5 -> 269.56139
A6: =ROW()-1 -> 5 | B6: Inbound processing | C6: Good Receiving | D6: Checking truck / container before unloading | E6: Check Container | F6: =F5 -> 4.8054608 | G6: Truck/Ctnr. | H6: HDL | I6: =IFERROR(VLOOKUP(H6,Parameter!$F$44:$H$92,3,0),"") -> 0 | J6: Manual | K6: =IFERROR(INDEX(Parameter!$D$122:$M$122,1,MATCH(Process!$J6,Parameter!$D$121:$M$121,0)),"") -> 1.2 | L6: =IFERROR(I6/K6,0) -> 0 | M6: 75 | N6: =L6+M6 -> 75 | O6: Operator | P6: =N6*F6/3600/Parameter!$P$6/Parameter!$P$7 -> 0.014722613 | X6: =P6*Parameter!W$8 -> 0.014280934 | Y6: =X6*Parameter!X$8 -> 0.013168192 | Z6: =Y6*Parameter!Y$8 -> 0.012506418 | AA6: =Z6*Parameter!Z$8 -> 0.012234238 | AB6: =VLOOKUP(O6,Parameter!$O$11:$P$22,2,0)*Process!P6 -> 1237.3727 | AC6: =VLOOKUP($O6,Parameter!$O$11:$P$22,2,0)*VLOOKUP($O6,Parameter!$O$11:$T$22,6,0)*X6 -> 1284.2692 | AD6: =VLOOKUP($O6,Parameter!$O$11:$P$22,2,0)*VLOOKUP($O6,Parameter!$O$11:$T$22,6,0)^2*Y6 -> 1267.0956 | AE6: =VLOOKUP($O6,Parameter!$O$11:$P$22,2,0)*VLOOKUP($O6,Parameter!$O$11:$T$22,6,0)^3*Z6 -> 1287.6562 | AF6: =VLOOKUP($O6,Parameter!$O$11:$P$22,2,0)*VLOOKUP($O6,Parameter!$O$11:$T$22,6,0)^4*AA6 -> 1347.807
A7: =ROW()-1 -> 6 | B7: Inbound processing | C7: Good Receiving | D7: Checking truck / container before unloading | E7: Open Container | F7: =F6 -> 4.8054608 | G7: Truck/Ctnr. | H7: HDL | I7: =IFERROR(VLOOKUP(H7,Parameter!$F$44:$H$92,3,0),"") -> 0 | J7: Manual | K7: =IFERROR(INDEX(Parameter!$D$122:$M$122,1,MATCH(Process!$J7,Parameter!$D$121:$M$121,0)),"") -> 1.2 | L7: =IFERROR(I7/K7,0) -> 0 | M7: 75 | N7: =L7+M7 -> 75 | O7: Operator | P7: =N7*F7/3600/Parameter!$P$6/Parameter!$P$7 -> 0.014722613 | X7: =P7*Parameter!W$8 -> 0.014280934 | Y7: =X7*Parameter!X$8 -> 0.013168192 | Z7: =Y7*Parameter!Y$8 -> 0.012506418 | AA7: =Z7*Parameter!Z$8 -> 0.012234238 | AB7: =VLOOKUP(O7,Parameter!$O$11:$P$22,2,0)*Process!P7 -> 1237.3727 | AC7: =VLOOKUP($O7,Parameter!$O$11:$P$22,2,0)*VLOOKUP($O7,Parameter!$O$11:$T$22,6,0)*X7 -> 1284.2692 | AD7: =VLOOKUP($O7,Parameter!$O$11:$P$22,2,0)*VLOOKUP($O7,Parameter!$O$11:$T$22,6,0)^2*Y7 -> 1267.0956 | AE7: =VLOOKUP($O7,Parameter!$O$11:$P$22,2,0)*VLOOKUP($O7,Parameter!$O$11:$T$22,6,0)^3*Z7 -> 1287.6562 | AF7: =VLOOKUP($O7,Parameter!$O$11:$P$22,2,0)*VLOOKUP($O7,Parameter!$O$11:$T$22,6,0)^4*AA7 -> 1347.807
A8: =ROW()-1 -> 7 | B8: Inbound processing | C8: Good Receiving | D8: Checking truck / container before unloading | E8: Adjust Dock | F8: =F7 -> 4.8054608 | G8: Truck/Ctnr. | H8: HDL | I8: =IFERROR(VLOOKUP(H8,Parameter!$F$44:$H$92,3,0),"") -> 0 | J8: Manual | K8: =IFERROR(INDEX(Parameter!$D$122:$M$122,1,MATCH(Process!$J8,Parameter!$D$121:$M$121,0)),"") -> 1.2 | L8: =IFERROR(I8/K8,0) -> 0 | M8: 45 | N8: =L8+M8 -> 45 | O8: Operator | P8: =N8*F8/3600/Parameter!$P$6/Parameter!$P$7 -> 0.0088335676 | X8: =P8*Parameter!W$8 -> 0.0085685605 | Y8: =X8*Parameter!X$8 -> 0.0079009154 | Z8: =Y8*Parameter!Y$8 -> 0.0075038507 | AA8: =Z8*Parameter!Z$8 -> 0.0073405428 | AB8: =VLOOKUP(O8,Parameter!$O$11:$P$22,2,0)*Process!P8 -> 742.42365 | AC8: =VLOOKUP($O8,Parameter!$O$11:$P$22,2,0)*VLOOKUP($O8,Parameter!$O$11:$T$22,6,0)*X8 -> 770.56151 | AD8: =VLOOKUP($O8,Parameter!$O$11:$P$22,2,0)*VLOOKUP($O8,Parameter!$O$11:$T$22,6,0)^2*Y8 -> 760.25736 | AE8: =VLOOKUP($O8,Parameter!$O$11:$P$22,2,0)*VLOOKUP($O8,Parameter!$O$11:$T$22,6,0)^3*Z8 -> 772.59373 | AF8: =VLOOKUP($O8,Parameter!$O$11:$P$22,2,0)*VLOOKUP($O8,Parameter!$O$11:$T$22,6,0)^4*AA8 -> 808.68418
A9: =ROW()-1 -> 8 | B9: Inbound processing | C9: Good Receiving | D9: Unloading the truck / container | E9: Unloading Cargos | F9: =F3*Parameter!R35 -> 137.12979 | G9: HU | H9: HDL | I9: =IFERROR(VLOOKUP(H9,Parameter!$F$44:$H$92,3,0),"") -> 0 | J9: CB | K9: =IFERROR(INDEX(Parameter!$D$122:$M$122,1,MATCH(Process!$J9,Parameter!$D$121:$M$121,0)),"") -> 2.7777778 | L9: =IFERROR(I9/K9,0) -> 0 | M9: 30 | N9: =L9+M9 -> 30 | O9: MHE Driver | P9: =N9*F9/3600/Parameter!$P$6/Parameter!$P$7 -> 0.16805121 | X9: =P9*Parameter!W$8 -> 0.16300967 | Y9: =X9*Parameter!X$8 -> 0.15030829 | Z9: =Y9*Parameter!Y$8 -> 0.14275446 | AA9: =Z9*Parameter!Z$8 -> 0.13964767 | AB9: =VLOOKUP(O9,Parameter!$O$11:$P$22,2,0)*Process!P9 -> 16948.784 | AC9: =VLOOKUP($O9,Parameter!$O$11:$P$22,2,0)*VLOOKUP($O9,Parameter!$O$11:$T$22,6,0)*X9 -> 17591.143 | AD9: =VLOOKUP($O9,Parameter!$O$11:$P$22,2,0)*VLOOKUP($O9,Parameter!$O$11:$T$22,6,0)^2*Y9 -> 17355.91 | AE9: =VLOOKUP($O9,Parameter!$O$11:$P$22,2,0)*VLOOKUP($O9,Parameter!$O$11:$T$22,6,0)^3*Z9 -> 17637.537 | AF9: =VLOOKUP($O9,Parameter!$O$11:$P$22,2,0)*VLOOKUP($O9,Parameter!$O$11:$T$22,6,0)^4*AA9 -> 18461.446
A10: =ROW()-1 -> 9 | B10: Inbound processing | C10: Good Receiving | D10: Unloading the truck / container | E10: Move to IB staging | F10: =F9/Parameter!R36 -> 137.12979 | G10: Trip | H10: IBU | I10: =IFERROR(VLOOKUP(H10,Parameter!$F$44:$H$92,3,0),"") -> 110 | J10: CB | K10: =IFERROR(INDEX(Parameter!$D$122:$M$122,1,MATCH(Process!$J10,Parameter!$D$121:$M$121,0)),"") -> 2.7777778 | L10: =IFERROR(I10/K10,0) -> 39.6 | M10: 0 | N10: =L10+M10 -> 39.6 | O10: MHE Driver | P10: =N10*F10/3600/Parameter!$P$6/Parameter!$P$7 -> 0.2218276 | X10: =P10*Parameter!W$8 -> 0.21517277 | Y10: =X10*Parameter!X$8 -> 0.19840694 | Z10: =Y10*Parameter!Y$8 -> 0.18843589 | AA10: =Z10*Parameter!Z$8 -> 0.18433492 | AB10: =VLOOKUP(O10,Parameter!$O$11:$P$22,2,0)*Process!P10 -> 22372.395 | AC10: =VLOOKUP($O10,Parameter!$O$11:$P$22,2,0)*VLOOKUP($O10,Parameter!$O$11:$T$22,6,0)*X10 -> 23220.309 | AD10: =VLOOKUP($O10,Parameter!$O$11:$P$22,2,0)*VLOOKUP($O10,Parameter!$O$11:$T$22,6,0)^2*Y10 -> 22909.801 | AE10: =VLOOKUP($O10,Parameter!$O$11:$P$22,2,0)*VLOOKUP($O10,Parameter!$O$11:$T$22,6,0)^3*Z10 -> 23281.549 | AF10: =VLOOKUP($O10,Parameter!$O$11:$P$22,2,0)*VLOOKUP($O10,Parameter!$O$11:$T$22,6,0)^4*AA10 -> 24369.108
A11: =ROW()-1 -> 10 | B11: Inbound processing | C11: Good Receiving | D11: Unloading the truck / container | E11: Check Cargos' Performance | F11: =F9 -> 137.12979 | G11: HU | H11: HDL | I11: =IFERROR(VLOOKUP(H11,Parameter!$F$44:$H$92,3,0),"") -> 0 | J11: Manual | K11: =IFERROR(INDEX(Parameter!$D$122:$M$122,1,MATCH(Process!$J11,Parameter!$D$121:$M$121,0)),"") -> 1.2 | L11: =IFERROR(I11/K11,0) -> 0 | M11: 25 | N11: =L11+M11 -> 25 | O11: Operator | P11: =N11*F11/3600/Parameter!$P$6/Parameter!$P$7 -> 0.14004268 | X11: =P11*Parameter!W$8 -> 0.1358414 | Y11: =X11*Parameter!X$8 -> 0.12525691 | Z11: =Y11*Parameter!Y$8 -> 0.11896205 | AA11: =Z11*Parameter!Z$8 -> 0.11637306 | AB11: =VLOOKUP(O11,Parameter!$O$11:$P$22,2,0)*Process!P11 -> 11769.989 | AC11: =VLOOKUP($O11,Parameter!$O$11:$P$22,2,0)*VLOOKUP($O11,Parameter!$O$11:$T$22,6,0)*X11 -> 12216.072 | AD11: =VLOOKUP($O11,Parameter!$O$11:$P$22,2,0)*VLOOKUP($O11,Parameter!$O$11:$T$22,6,0)^2*Y11 -> 12052.715 | AE11: =VLOOKUP($O11,Parameter!$O$11:$P$22,2,0)*VLOOKUP($O11,Parameter!$O$11:$T$22,6,0)^3*Z11 -> 12248.289 | AF11: =VLOOKUP($O11,Parameter!$O$11:$P$22,2,0)*VLOOKUP($O11,Parameter!$O$11:$T$22,6,0)^4*AA11 -> 12820.448
A12: =ROW()-1 -> 11 | B12: Inbound processing | C12: Cross dock | D12: Move cross dock to inbound staging | E12: =D12 -> Move cross dock to inbound staging | F12: =Parameter!R44*Parameter!R45 -> 37.03928 | G12: trip | H12: IBXDO | I12: =IFERROR(VLOOKUP(H12,Parameter!$F$44:$H$92,3,0),"") -> 30 | J12: CB | K12: =IFERROR(INDEX(Parameter!$D$122:$M$122,1,MATCH(Process!$J12,Parameter!$D$121:$M$121,0)),"") -> 2.7777778 | L12: =IFERROR(I12/K12,0) -> 10.8 | N12: =L12+M12 -> 10.8 | O12: MHE Driver | P12: =N12*F12/3600/Parameter!$P$6/Parameter!$P$7 -> 0.016340859 | X12: =P12*Parameter!W$8 -> 0.015850633 | Y12: =X12*Parameter!X$8 -> 0.014615584 | Z12: =Y12*Parameter!Y$8 -> 0.01388107 | AA12: =Z12*Parameter!Z$8 -> 0.013578973 | AB12: =VLOOKUP(O12,Parameter!$O$11:$P$22,2,0)*Process!P12 -> 1648.0553 | AC12: =VLOOKUP($O12,Parameter!$O$11:$P$22,2,0)*VLOOKUP($O12,Parameter!$O$11:$T$22,6,0)*X12 -> 1710.5166 | AD12: =VLOOKUP($O12,Parameter!$O$11:$P$22,2,0)*VLOOKUP($O12,Parameter!$O$11:$T$22,6,0)^2*Y12 -> 1687.6432 | AE12: =VLOOKUP($O12,Parameter!$O$11:$P$22,2,0)*VLOOKUP($O12,Parameter!$O$11:$T$22,6,0)^3*Z12 -> 1715.0278 | AF12: =VLOOKUP($O12,Parameter!$O$11:$P$22,2,0)*VLOOKUP($O12,Parameter!$O$11:$T$22,6,0)^4*AA12 -> 1795.1426
A13: =ROW()-1 -> 12 | B13: Inbound processing | C13: Cross dock | D13: Move confirmation | E13: Scan zone code | F13: =F12*2 -> 74.078561 | G13: =G12 -> trip | H13: HDL | I13: =IFERROR(VLOOKUP(H13,Parameter!$F$44:$H$92,3,0),"") -> 0 | J13: CB | K13: =IFERROR(INDEX(Parameter!$D$122:$M$122,1,MATCH(Process!$J13,Parameter!$D$121:$M$121,0)),"") -> 2.7777778 | L13: =IFERROR(I13/K13,0) -> 0 | M13: 15 | N13: =L13+M13 -> 15 | O13: MHE Driver | P13: =N13*F13/3600/Parameter!$P$6/Parameter!$P$7 -> 0.045391275 | X13: =P13*Parameter!W$8 -> 0.044029537 | Y13: =X13*Parameter!X$8 -> 0.040598843 | Z13: =Y13*Parameter!Y$8 -> 0.038558526 | AA13: =Z13*Parameter!Z$8 -> 0.037719369 | AB13: =VLOOKUP(O13,Parameter!$O$11:$P$22,2,0)*Process!P13 -> 4577.9315 | AC13: =VLOOKUP($O13,Parameter!$O$11:$P$22,2,0)*VLOOKUP($O13,Parameter!$O$11:$T$22,6,0)*X13 -> 4751.4351 | AD13: =VLOOKUP($O13,Parameter!$O$11:$P$22,2,0)*VLOOKUP($O13,Parameter!$O$11:$T$22,6,0)^2*Y13 -> 4687.8977 | AE13: =VLOOKUP($O13,Parameter!$O$11:$P$22,2,0)*VLOOKUP($O13,Parameter!$O$11:$T$22,6,0)^3*Z13 -> 4763.9662 | AF13: =VLOOKUP($O13,Parameter!$O$11:$P$22,2,0)*VLOOKUP($O13,Parameter!$O$11:$T$22,6,0)^4*AA13 -> 4986.5071
A14: =ROW()-1 -> 13 | B14: Inbound processing | C14: Cross dock | D14: Move cross dock to outbound staging | E14: =D14 -> Move cross dock to outbound staging | F14: =F12 -> 37.03928 | G14: trip | H14: OBXDOH | I14: =IFERROR(VLOOKUP(H14,Parameter!$F$44:$H$92,3,0),"") -> 120 | J14: CB | K14: =IFERROR(INDEX(Parameter!$D$122:$M$122,1,MATCH(Process!$J14,Parameter!$D$121:$M$121,0)),"") -> 2.7777778 | L14: =IFERROR(I14/K14,0) -> 43.2 | N14: =L14+M14 -> 43.2 | O14: MHE Driver | P14: =N14*F14/3600/Parameter!$P$6/Parameter!$P$7 -> 0.065363436 | X14: =P14*Parameter!W$8 -> 0.063402533 | Y14: =X14*Parameter!X$8 -> 0.058462334 | Z14: =Y14*Parameter!Y$8 -> 0.055524278 | AA14: =Z14*Parameter!Z$8 -> 0.054315892 | AB14: =VLOOKUP(O14,Parameter!$O$11:$P$22,2,0)*Process!P14 -> 6592.2214 | AC14: =VLOOKUP($O14,Parameter!$O$11:$P$22,2,0)*VLOOKUP($O14,Parameter!$O$11:$T$22,6,0)*X14 -> 6842.0666 | AD14: =VLOOKUP($O14,Parameter!$O$11:$P$22,2,0)*VLOOKUP($O14,Parameter!$O$11:$T$22,6,0)^2*Y14 -> 6750.5727 | AE14: =VLOOKUP($O14,Parameter!$O$11:$P$22,2,0)*VLOOKUP($O14,Parameter!$O$11:$T$22,6,0)^3*Z14 -> 6860.1113 | AF14: =VLOOKUP($O14,Parameter!$O$11:$P$22,2,0)*VLOOKUP($O14,Parameter!$O$11:$T$22,6,0)^4*AA14 -> 7180.5702
A15: =ROW()-1 -> 14 | B15: Chinese labelling | C15: Checking and labelling | D15: Cargo checking and stick label | E15: Scan Pallet | F15: =F9-F12 -> 100.09051 | G15: HU | H15: HDL | I15: =IFERROR(VLOOKUP(H15,Parameter!$F$44:$H$92,3,0),"") -> 0 | J15: CB | K15: =IFERROR(INDEX(Parameter!$D$122:$M$122,1,MATCH(Process!$J15,Parameter!$D$121:$M$121,0)),"") -> 2.7777778 | L15: =IFERROR(I15/K15,0) -> 0 | M15: 5 | N15: =L15+M15 -> 5 | O15: MHE Driver | P15: =N15*F15/3600/Parameter!$P$6/Parameter!$P$7 -> 0.020443323 | X15: =P15*Parameter!W$8 -> 0.019830023 | Y15: =X15*Parameter!X$8 -> 0.018284907 | Z15: =Y15*Parameter!Y$8 -> 0.017365989 | AA15: =Z15*Parameter!Z$8 -> 0.01698805 | AB15: =VLOOKUP(O15,Parameter!$O$11:$P$22,2,0)*Process!P15 -> 2061.8088 | AC15: =VLOOKUP($O15,Parameter!$O$11:$P$22,2,0)*VLOOKUP($O15,Parameter!$O$11:$T$22,6,0)*X15 -> 2139.9514 | AD15: =VLOOKUP($O15,Parameter!$O$11:$P$22,2,0)*VLOOKUP($O15,Parameter!$O$11:$T$22,6,0)^2*Y15 -> 2111.3354 | AE15: =VLOOKUP($O15,Parameter!$O$11:$P$22,2,0)*VLOOKUP($O15,Parameter!$O$11:$T$22,6,0)^3*Z15 -> 2145.5951 | AF15: =VLOOKUP($O15,Parameter!$O$11:$P$22,2,0)*VLOOKUP($O15,Parameter!$O$11:$T$22,6,0)^4*AA15 -> 2245.8231
A16: =ROW()-1 -> 15 | B16: Chinese labelling | C16: Checking and labelling | D16: Cargo checking and stick label | E16: Move HU to Sorting Area | F16: =F15 -> 100.09051 | G16: HU | H16: IBS | I16: =IFERROR(VLOOKUP(H16,Parameter!$F$44:$H$92,3,0),"") -> 40 | J16: CB | K16: =IFERROR(INDEX(Parameter!$D$122:$M$122,1,MATCH(Process!$J16,Parameter!$D$121:$M$121,0)),"") -> 2.7777778 | L16: =IFERROR(I16/K16,0) -> 14.4 | N16: =L16+M16 -> 14.4 | O16: MHE Driver | P16: =N16*F16/3600/Parameter!$P$6/Parameter!$P$7 -> 0.058876769 | X16: =P16*Parameter!W$8 -> 0.057110466 | Y16: =X16*Parameter!X$8 -> 0.052660533 | Z16: =Y16*Parameter!Y$8 -> 0.050014049 | AA16: =Z16*Parameter!Z$8 -> 0.048925583 | AB16: =VLOOKUP(O16,Parameter!$O$11:$P$22,2,0)*Process!P16 -> 5938.0094 | AC16: =VLOOKUP($O16,Parameter!$O$11:$P$22,2,0)*VLOOKUP($O16,Parameter!$O$11:$T$22,6,0)*X16 -> 6163.0599 | AD16: =VLOOKUP($O16,Parameter!$O$11:$P$22,2,0)*VLOOKUP($O16,Parameter!$O$11:$T$22,6,0)^2*Y16 -> 6080.6459 | AE16: =VLOOKUP($O16,Parameter!$O$11:$P$22,2,0)*VLOOKUP($O16,Parameter!$O$11:$T$22,6,0)^3*Z16 -> 6179.3139 | AF16: =VLOOKUP($O16,Parameter!$O$11:$P$22,2,0)*VLOOKUP($O16,Parameter!$O$11:$T$22,6,0)^4*AA16 -> 6467.9705
A17: =ROW()-1 -> 16 | B17: Chinese labelling | C17: Checking and labelling | D17: Cargo checking and stick label | E17: Open Multi-collie | F17: =Parameter!T38 -> 68.564894 | G17: HU | H17: HDL | I17: =IFERROR(VLOOKUP(H17,Parameter!$F$44:$H$92,3,0),"") -> 0 | J17: Manual | K17: =IFERROR(INDEX(Parameter!$D$122:$M$122,1,MATCH(Process!$J17,Parameter!$D$121:$M$121,0)),"") -> 1.2 | L17: =IFERROR(I17/K17,0) -> 0 | M17: 60 | N17: =L17+M17 -> 60 | O17: Operator | P17: =N17*F17/3600/Parameter!$P$6/Parameter!$P$7 -> 0.16805121 | X17: =P17*Parameter!W$8 -> 0.16300967 | Y17: =X17*Parameter!X$8 -> 0.15030829 | Z17: =Y17*Parameter!Y$8 -> 0.14275446 | AA17: =Z17*Parameter!Z$8 -> 0.13964767 | AB17: =VLOOKUP(O17,Parameter!$O$11:$P$22,2,0)*Process!P17 -> 14123.987 | AC17: =VLOOKUP($O17,Parameter!$O$11:$P$22,2,0)*VLOOKUP($O17,Parameter!$O$11:$T$22,6,0)*X17 -> 14659.286 | AD17: =VLOOKUP($O17,Parameter!$O$11:$P$22,2,0)*VLOOKUP($O17,Parameter!$O$11:$T$22,6,0)^2*Y17 -> 14463.258 | AE17: =VLOOKUP($O17,Parameter!$O$11:$P$22,2,0)*VLOOKUP($O17,Parameter!$O$11:$T$22,6,0)^3*Z17 -> 14697.947 | AF17: =VLOOKUP($O17,Parameter!$O$11:$P$22,2,0)*VLOOKUP($O17,Parameter!$O$11:$T$22,6,0)^4*AA17 -> 15384.538
A18: =ROW()-1 -> 17 | B18: Chinese labelling | C18: Checking and labelling | D18: Cargo checking and stick label | E18: Count Parts in multi-collie | F18: =F17*Parameter!R40*Parameter!R39 -> 10211.033 | G18: Piece | H18: HDL | I18: =IFERROR(VLOOKUP(H18,Parameter!$F$44:$H$92,3,0),"") -> 0 | J18: Manual | K18: =IFERROR(INDEX(Parameter!$D$122:$M$122,1,MATCH(Process!$J18,Parameter!$D$121:$M$121,0)),"") -> 1.2 | L18: =IFERROR(I18/K18,0) -> 0 | M18: 2 | N18: =L18+M18 -> 2 | O18: Operator | P18: =N18*F18/3600/Parameter!$P$6/Parameter!$P$7 -> 0.83423469 | X18: =P18*Parameter!W$8 -> 0.80920765 | Y18: =X18*Parameter!X$8 -> 0.74615581 | Z18: =Y18*Parameter!Y$8 -> 0.70865735 | AA18: =Z18*Parameter!Z$8 -> 0.69323469 | AB18: =VLOOKUP(O18,Parameter!$O$11:$P$22,2,0)*Process!P18 -> 70113.865 | AC18: =VLOOKUP($O18,Parameter!$O$11:$P$22,2,0)*VLOOKUP($O18,Parameter!$O$11:$T$22,6,0)*X18 -> 72771.181 | AD18: =VLOOKUP($O18,Parameter!$O$11:$P$22,2,0)*VLOOKUP($O18,Parameter!$O$11:$T$22,6,0)^2*Y18 -> 71798.066 | AE18: =VLOOKUP($O18,Parameter!$O$11:$P$22,2,0)*VLOOKUP($O18,Parameter!$O$11:$T$22,6,0)^3*Z18 -> 72963.102 | AF18: =VLOOKUP($O18,Parameter!$O$11:$P$22,2,0)*VLOOKUP($O18,Parameter!$O$11:$T$22,6,0)^4*AA18 -> 76371.454
A19: =ROW()-1 -> 18 | B19: Chinese labelling | C19: Checking and labelling | D19: Cargo checking and stick label | E19: Check Performance | F19: =F17*Parameter!R40+(F15-F17)*1 -> 703.74633 | G19: HU | H19: HDL | I19: =IFERROR(VLOOKUP(H19,Parameter!$F$44:$H$92,3,0),"") -> 0 | J19: Manual | K19: =IFERROR(INDEX(Parameter!$D$122:$M$122,1,MATCH(Process!$J19,Parameter!$D$121:$M$121,0)),"") -> 1.2 | L19: =IFERROR(I19/K19,0) -> 0 | M19: 5 | N19: =L19+M19 -> 5 | O19: Operator | P19: =N19*F19/3600/Parameter!$P$6/Parameter!$P$7 -> 0.14373904 | X19: =P19*Parameter!W$8 -> 0.13942687 | Y19: =X19*Parameter!X$8 -> 0.128563 | Z19: =Y19*Parameter!Y$8 -> 0.122102 | AA19: =Z19*Parameter!Z$8 -> 0.11944467 | AB19: =VLOOKUP(O19,Parameter!$O$11:$P$22,2,0)*Process!P19 -> 12080.653 | AC19: =VLOOKUP($O19,Parameter!$O$11:$P$22,2,0)*VLOOKUP($O19,Parameter!$O$11:$T$22,6,0)*X19 -> 12538.509 | AD19: =VLOOKUP($O19,Parameter!$O$11:$P$22,2,0)*VLOOKUP($O19,Parameter!$O$11:$T$22,6,0)^2*Y19 -> 12370.841 | AE19: =VLOOKUP($O19,Parameter!$O$11:$P$22,2,0)*VLOOKUP($O19,Parameter!$O$11:$T$22,6,0)^3*Z19 -> 12571.577 | AF19: =VLOOKUP($O19,Parameter!$O$11:$P$22,2,0)*VLOOKUP($O19,Parameter!$O$11:$T$22,6,0)^4*AA19 -> 13158.838
A20: =ROW()-1 -> 19 | B20: Chinese labelling | C20: Checking and labelling | D20: Update New Parts Info. | E20: Update New Parts Info. | F20: =Parameter!R28*Parameter!R41 -> 0 | G20: Line | H20: HDL | I20: =IFERROR(VLOOKUP(H20,Parameter!$F$44:$H$92,3,0),"") -> 0 | J20: Manual | K20: =IFERROR(INDEX(Parameter!$D$122:$M$122,1,MATCH(Process!$J20,Parameter!$D$121:$M$121,0)),"") -> 1.2 | L20: =IFERROR(I20/K20,0) -> 0 | M20: 10 | N20: =L20+M20 -> 10 | O20: Operator | P20: =N20*F20/3600/Parameter!$P$6/Parameter!$P$7 -> 0 | X20: =P20*Parameter!W$8 -> 0 | Y20: =X20*Parameter!X$8 -> 0 | Z20: =Y20*Parameter!Y$8 -> 0 | AA20: =Z20*Parameter!Z$8 -> 0 | AB20: =VLOOKUP(O20,Parameter!$O$11:$P$22,2,0)*Process!P20 -> 0 | AC20: =VLOOKUP($O20,Parameter!$O$11:$P$22,2,0)*VLOOKUP($O20,Parameter!$O$11:$T$22,6,0)*X20 -> 0 | AD20: =VLOOKUP($O20,Parameter!$O$11:$P$22,2,0)*VLOOKUP($O20,Parameter!$O$11:$T$22,6,0)^2*Y20 -> 0 | AE20: =VLOOKUP($O20,Parameter!$O$11:$P$22,2,0)*VLOOKUP($O20,Parameter!$O$11:$T$22,6,0)^3*Z20 -> 0 | AF20: =VLOOKUP($O20,Parameter!$O$11:$P$22,2,0)*VLOOKUP($O20,Parameter!$O$11:$T$22,6,0)^4*AA20 -> 0
A21: =ROW()-1 -> 20 | B21: Chinese labelling | C21: Checking and labelling | D21: Cargo checking and stick label | E21: Scan HU, label printed in office | F21: =F15 -> 100.09051 | G21: HU | H21: HDL | I21: =IFERROR(VLOOKUP(H21,Parameter!$F$44:$H$92,3,0),"") -> 0 | J21: Manual | K21: =IFERROR(INDEX(Parameter!$D$122:$M$122,1,MATCH(Process!$J21,Parameter!$D$121:$M$121,0)),"") -> 1.2 | L21: =IFERROR(I21/K21,0) -> 0 | M21: 5 | N21: =L21+M21 -> 5 | O21: Operator | P21: =N21*F21/3600/Parameter!$P$6/Parameter!$P$7 -> 0.020443323 | X21: =P21*Parameter!W$8 -> 0.019830023 | Y21: =X21*Parameter!X$8 -> 0.018284907 | Z21: =Y21*Parameter!Y$8 -> 0.017365989 | AA21: =Z21*Parameter!Z$8 -> 0.01698805 | AB21: =VLOOKUP(O21,Parameter!$O$11:$P$22,2,0)*Process!P21 -> 1718.174 | AC21: =VLOOKUP($O21,Parameter!$O$11:$P$22,2,0)*VLOOKUP($O21,Parameter!$O$11:$T$22,6,0)*X21 -> 1783.2928 | AD21: =VLOOKUP($O21,Parameter!$O$11:$P$22,2,0)*VLOOKUP($O21,Parameter!$O$11:$T$22,6,0)^2*Y21 -> 1759.4461 | AE21: =VLOOKUP($O21,Parameter!$O$11:$P$22,2,0)*VLOOKUP($O21,Parameter!$O$11:$T$22,6,0)^3*Z21 -> 1787.9959 | AF21: =VLOOKUP($O21,Parameter!$O$11:$P$22,2,0)*VLOOKUP($O21,Parameter!$O$11:$T$22,6,0)^4*AA21 -> 1871.5192
A22: =ROW()-1 -> 21 | B22: Chinese labelling | C22: Checking and labelling | D22: Cargo checking and stick label | E22: Label sorting | F22: =F15 -> 100.09051 | G22: HU | H22: HDL | I22: =IFERROR(VLOOKUP(H22,Parameter!$F$44:$H$92,3,0),"") -> 0 | J22: Manual | K22: =IFERROR(INDEX(Parameter!$D$122:$M$122,1,MATCH(Process!$J22,Parameter!$D$121:$M$121,0)),"") -> 1.2 | L22: =IFERROR(I22/K22,0) -> 0 | M22: 60 | N22: =L22+M22 -> 60 | O22: IB Planner | P22: =N22*F22/3600/Parameter!$P$6/Parameter!$P$7 -> 0.24531987 | X22: =P22*Parameter!W$8 -> 0.23796027 | Y22: =X22*Parameter!X$8 -> 0.21941889 | Z22: =Y22*Parameter!Y$8 -> 0.20839187 | AA22: =Z22*Parameter!Z$8 -> 0.2038566 | AB22: =VLOOKUP(O22,Parameter!$O$11:$P$22,2,0)*Process!P22 -> 30927.132 | AC22: =VLOOKUP($O22,Parameter!$O$11:$P$22,2,0)*VLOOKUP($O22,Parameter!$O$11:$T$22,6,0)*X22 -> 32099.27 | AD22: =VLOOKUP($O22,Parameter!$O$11:$P$22,2,0)*VLOOKUP($O22,Parameter!$O$11:$T$22,6,0)^2*Y22 -> 31670.031 | AE22: =VLOOKUP($O22,Parameter!$O$11:$P$22,2,0)*VLOOKUP($O22,Parameter!$O$11:$T$22,6,0)^3*Z22 -> 32183.927 | AF22: =VLOOKUP($O22,Parameter!$O$11:$P$22,2,0)*VLOOKUP($O22,Parameter!$O$11:$T$22,6,0)^4*AA22 -> 33687.346
A23: =ROW()-1 -> 22 | B23: Chinese labelling | C23: Checking and labelling | D23: Cargo checking and stick label | E23: Stick Label | F23: =Volume!B85/Parameter!P4 -> 6746.2526 | G23: Piece | H23: HDL | I23: =IFERROR(VLOOKUP(H23,Parameter!$F$44:$H$92,3,0),"") -> 0 | J23: Manual | K23: =IFERROR(INDEX(Parameter!$D$122:$M$122,1,MATCH(Process!$J23,Parameter!$D$121:$M$121,0)),"") -> 1.2 | L23: =IFERROR(I23/K23,0) -> 0 | M23: 3 | N23: =L23+M23 -> 3 | O23: Operator | P23: =N23*F23/3600/Parameter!$P$6/Parameter!$P$7 -> 0.82674664 | X23: =P23*Parameter!W$8 -> 0.80194424 | Y23: =X23*Parameter!X$8 -> 0.73945835 | Z23: =Y23*Parameter!Y$8 -> 0.70229647 | AA23: =Z23*Parameter!Z$8 -> 0.68701225 | AB23: =VLOOKUP(O23,Parameter!$O$11:$P$22,2,0)*Process!P23 -> 69484.526 | AC23: =VLOOKUP($O23,Parameter!$O$11:$P$22,2,0)*VLOOKUP($O23,Parameter!$O$11:$T$22,6,0)*X23 -> 72117.99 | AD23: =VLOOKUP($O23,Parameter!$O$11:$P$22,2,0)*VLOOKUP($O23,Parameter!$O$11:$T$22,6,0)^2*Y23 -> 71153.609 | AE23: =VLOOKUP($O23,Parameter!$O$11:$P$22,2,0)*VLOOKUP($O23,Parameter!$O$11:$T$22,6,0)^3*Z23 -> 72308.188 | AF23: =VLOOKUP($O23,Parameter!$O$11:$P$22,2,0)*VLOOKUP($O23,Parameter!$O$11:$T$22,6,0)^4*AA23 -> 75685.947
A24: =ROW()-1 -> 23 | B24: Warranty & Return | C24: Return check | D24: Return handling | E24: Check return and sort by Class | F24: =Volume!B10/Parameter!P4*Parameter!R42*(1-Volume!J26) -> 83.047235 | G24: Piece | H24: HDL | I24: =IFERROR(VLOOKUP(H24,Parameter!$F$44:$H$92,3,0),"") -> 0 | J24: Manual | K24: =IFERROR(INDEX(Parameter!$D$122:$M$122,1,MATCH(Process!$J24,Parameter!$D$121:$M$121,0)),"") -> 1.2 | L24: =IFERROR(I24/K24,0) -> 0 | M24: 180 | N24: =L24+M24 -> 180 | O24: IB Planner | P24: =N24*F24/3600/Parameter!$P$6/Parameter!$P$7 -> 0.61064144 | X24: =P24*Parameter!W$8 -> 0.59232219 | Y24: =X24*Parameter!X$8 -> 0.54616963 | Z24: =Y24*Parameter!Y$8 -> 0.51872158 | AA24: =Z24*Parameter!Z$8 -> 0.50743254 | AB24: =VLOOKUP(O24,Parameter!$O$11:$P$22,2,0)*Process!P24 -> 76982.71 | AC24: =VLOOKUP($O24,Parameter!$O$11:$P$22,2,0)*VLOOKUP($O24,Parameter!$O$11:$T$22,6,0)*X24 -> 79900.354 | AD24: =VLOOKUP($O24,Parameter!$O$11:$P$22,2,0)*VLOOKUP($O24,Parameter!$O$11:$T$22,6,0)^2*Y24 -> 78831.906 | AE24: =VLOOKUP($O24,Parameter!$O$11:$P$22,2,0)*VLOOKUP($O24,Parameter!$O$11:$T$22,6,0)^3*Z24 -> 80111.078 | AF24: =VLOOKUP($O24,Parameter!$O$11:$P$22,2,0)*VLOOKUP($O24,Parameter!$O$11:$T$22,6,0)^4*AA24 -> 83853.336
A25: =ROW()-1 -> 24 | B25: Warranty & Return | C25: Return check | D25: Return handling | E25: Put away to return shelving | F25: =F24 -> 83.047235 | G25: =G24 -> Piece | H25: HDL | I25: =IFERROR(VLOOKUP(H25,Parameter!$F$44:$H$92,3,0),"") -> 0 | J25: Manual | K25: =IFERROR(INDEX(Parameter!$D$122:$M$122,1,MATCH(Process!$J25,Parameter!$D$121:$M$121,0)),"") -> 1.2 | L25: =IFERROR(I25/K25,0) -> 0 | M25: =3600/40 -> 90 | N25: =L25+M25 -> 90 | O25: IB Planner | P25: =N25*F25/3600/Parameter!$P$6/Parameter!$P$7 -> 0.30532072 | X25: =P25*Parameter!W$8 -> 0.2961611 | Y25: =X25*Parameter!X$8 -> 0.27308482 | Z25: =Y25*Parameter!Y$8 -> 0.25936079 | AA25: =Z25*Parameter!Z$8 -> 0.25371627 | AB25: =VLOOKUP(O25,Parameter!$O$11:$P$22,2,0)*Process!P25 -> 38491.355 | AC25: =VLOOKUP($O25,Parameter!$O$11:$P$22,2,0)*VLOOKUP($O25,Parameter!$O$11:$T$22,6,0)*X25 -> 39950.177 | AD25: =VLOOKUP($O25,Parameter!$O$11:$P$22,2,0)*VLOOKUP($O25,Parameter!$O$11:$T$22,6,0)^2*Y25 -> 39415.953 | AE25: =VLOOKUP($O25,Parameter!$O$11:$P$22,2,0)*VLOOKUP($O25,Parameter!$O$11:$T$22,6,0)^3*Z25 -> 40055.539 | AF25: =VLOOKUP($O25,Parameter!$O$11:$P$22,2,0)*VLOOKUP($O25,Parameter!$O$11:$T$22,6,0)^4*AA25 -> 41926.668
A26: =ROW()-1 -> 25 | B26: Warranty & Return | C26: Return check | D26: Return handling | E26: System registration | F26: =Volume!B10/Parameter!P4*(1-Volume!J26) -> 41.523618 | G26: Line | H26: HDL | I26: =IFERROR(VLOOKUP(H26,Parameter!$F$44:$H$92,3,0),"") -> 0 | J26: Manual | K26: =IFERROR(INDEX(Parameter!$D$122:$M$122,1,MATCH(Process!$J26,Parameter!$D$121:$M$121,0)),"") -> 1.2 | L26: =IFERROR(I26/K26,0) -> 0 | M26: 300 | N26: =L26+M26 -> 300 | O26: IB Planner | P26: =N26*F26/3600/Parameter!$P$6/Parameter!$P$7 -> 0.50886786 | X26: =P26*Parameter!W$8 -> 0.49360183 | Y26: =X26*Parameter!X$8 -> 0.45514136 | Z26: =Y26*Parameter!Y$8 -> 0.43226799 | AA26: =Z26*Parameter!Z$8 -> 0.42286045 | AB26: =VLOOKUP(O26,Parameter!$O$11:$P$22,2,0)*Process!P26 -> 64152.258 | AC26: =VLOOKUP($O26,Parameter!$O$11:$P$22,2,0)*VLOOKUP($O26,Parameter!$O$11:$T$22,6,0)*X26 -> 66583.629 | AD26: =VLOOKUP($O26,Parameter!$O$11:$P$22,2,0)*VLOOKUP($O26,Parameter!$O$11:$T$22,6,0)^2*Y26 -> 65693.255 | AE26: =VLOOKUP($O26,Parameter!$O$11:$P$22,2,0)*VLOOKUP($O26,Parameter!$O$11:$T$22,6,0)^3*Z26 -> 66759.231 | AF26: =VLOOKUP($O26,Parameter!$O$11:$P$22,2,0)*VLOOKUP($O26,Parameter!$O$11:$T$22,6,0)^4*AA26 -> 69877.78
A27: =ROW()-1 -> 26 | B27: Inbound processing | C27: Sorting to putaway | D27: Scan single collie | E27: RF show where the collie going | F27: =F15-F17 -> 31.525613 | G27: HU | H27: HDL | I27: =IFERROR(VLOOKUP(H27,Parameter!$F$44:$H$92,3,0),"") -> 0 | J27: Manual | K27: =IFERROR(INDEX(Parameter!$D$122:$M$122,1,MATCH(Process!$J27,Parameter!$D$121:$M$121,0)),"") -> 1.2 | L27: =IFERROR(I27/K27,0) -> 0 | M27: 3 | N27: =L27+M27 -> 3 | O27: Operator | P27: =N27*F27/3600/Parameter!$P$6/Parameter!$P$7 -> 0.003863433 | X27: =P27*Parameter!W$8 -> 0.00374753 | Y27: =X27*Parameter!X$8 -> 0.00345553 | Z27: =Y27*Parameter!Y$8 -> 0.0032818705 | AA27: =Z27*Parameter!Z$8 -> 0.0032104464 | AB27: =VLOOKUP(O27,Parameter!$O$11:$P$22,2,0)*Process!P27 -> 324.70506 | AC27: =VLOOKUP($O27,Parameter!$O$11:$P$22,2,0)*VLOOKUP($O27,Parameter!$O$11:$T$22,6,0)*X27 -> 337.01138 | AD27: =VLOOKUP($O27,Parameter!$O$11:$P$22,2,0)*VLOOKUP($O27,Parameter!$O$11:$T$22,6,0)^2*Y27 -> 332.50477 | AE27: =VLOOKUP($O27,Parameter!$O$11:$P$22,2,0)*VLOOKUP($O27,Parameter!$O$11:$T$22,6,0)^3*Z27 -> 337.90019 | AF27: =VLOOKUP($O27,Parameter!$O$11:$P$22,2,0)*VLOOKUP($O27,Parameter!$O$11:$T$22,6,0)^4*AA27 -> 353.68464
A28: =ROW()-1 -> 27 | B28: Inbound processing | C28: Sorting to putaway | D28: Sorting to M trolley | E28: Sorting Parts to Trolley | F28: =Parameter!R50*Parameter!R39 -> 1575.3547 | G28: Piece | H28: HDL | I28: =IFERROR(VLOOKUP(H28,Parameter!$F$44:$H$92,3,0),"") -> 0 | J28: Trolley | K28: =IFERROR(INDEX(Parameter!$D$122:$M$122,1,MATCH(Process!$J28,Parameter!$D$121:$M$121,0)),"") -> 0.42 | L28: =IFERROR(I28/K28,0) -> 0 | M28: 3 | N28: =L28+M28 -> 3 | O28: Operator | P28: =N28*F28/3600/Parameter!$P$6/Parameter!$P$7 -> 0.19305817 | X28: =P28*Parameter!W$8 -> 0.18726643 | Y28: =X28*Parameter!X$8 -> 0.172675 | Z28: =Y28*Parameter!Y$8 -> 0.16399712 | AA28: =Z28*Parameter!Z$8 -> 0.16042802 | AB28: =VLOOKUP(O28,Parameter!$O$11:$P$22,2,0)*Process!P28 -> 16225.715 | AC28: =VLOOKUP($O28,Parameter!$O$11:$P$22,2,0)*VLOOKUP($O28,Parameter!$O$11:$T$22,6,0)*X28 -> 16840.67 | AD28: =VLOOKUP($O28,Parameter!$O$11:$P$22,2,0)*VLOOKUP($O28,Parameter!$O$11:$T$22,6,0)^2*Y28 -> 16615.472 | AE28: =VLOOKUP($O28,Parameter!$O$11:$P$22,2,0)*VLOOKUP($O28,Parameter!$O$11:$T$22,6,0)^3*Z28 -> 16885.084 | AF28: =VLOOKUP($O28,Parameter!$O$11:$P$22,2,0)*VLOOKUP($O28,Parameter!$O$11:$T$22,6,0)^4*AA28 -> 17673.843
A29: =ROW()-1 -> 28 | B29: Inbound processing | C29: Full inspection | D29: Full inspection | E29: Open check, take photo and system registration | F29: =Parameter!R28*Parameter!U41 -> 44.447136 | G29: Line | H29: HDL | J29: Manual | K29: =IFERROR(INDEX(Parameter!$D$122:$M$122,1,MATCH(Process!$J29,Parameter!$D$121:$M$121,0)),"") -> 1.2 | L29: =IFERROR(I29/K29,0) -> 0 | M29: 300 | N29: =L29+M29 -> 300 | O29: Operator | P29: =N29*F29/3600/Parameter!$P$6/Parameter!$P$7 -> 0.5446953 | X29: =P29*Parameter!W$8 -> 0.52835444 | Y29: =X29*Parameter!X$8 -> 0.48718612 | Z29: =Y29*Parameter!Y$8 -> 0.46270232 | AA29: =Z29*Parameter!Z$8 -> 0.45263243 | AB29: =VLOOKUP(O29,Parameter!$O$11:$P$22,2,0)*Process!P29 -> 45779.315 | AC29: =VLOOKUP($O29,Parameter!$O$11:$P$22,2,0)*VLOOKUP($O29,Parameter!$O$11:$T$22,6,0)*X29 -> 47514.351 | AD29: =VLOOKUP($O29,Parameter!$O$11:$P$22,2,0)*VLOOKUP($O29,Parameter!$O$11:$T$22,6,0)^2*Y29 -> 46878.977 | AE29: =VLOOKUP($O29,Parameter!$O$11:$P$22,2,0)*VLOOKUP($O29,Parameter!$O$11:$T$22,6,0)^3*Z29 -> 47639.662 | AF29: =VLOOKUP($O29,Parameter!$O$11:$P$22,2,0)*VLOOKUP($O29,Parameter!$O$11:$T$22,6,0)^4*AA29 -> 49865.071
A30: =ROW()-1 -> 29 | B30: Inbound processing | C30: M Put away | D30: Mezzanine_Put away | E30: Move trolley to M staging | F30: =Parameter!R50/Parameter!R51 -> 12.963748 | G30: Trip | H30: IBSM | I30: =IFERROR(VLOOKUP(H30,Parameter!$F$44:$H$92,3,0),"") -> 150 | J30: Trolley | K30: =IFERROR(INDEX(Parameter!$D$122:$M$122,1,MATCH(Process!$J30,Parameter!$D$121:$M$121,0)),"") -> 0.42 | L30: =IFERROR(I30/K30,0) -> 357.14286 | N30: =L30+M30 -> 357.14286 | O30: Operator | P30: =N30*F30/3600/Parameter!$P$6/Parameter!$P$7 -> 0.18913031 | X30: =P30*Parameter!W$8 -> 0.1834564 | Y30: =X30*Parameter!X$8 -> 0.16916185 | Z30: =Y30*Parameter!Y$8 -> 0.16066053 | AA30: =Z30*Parameter!Z$8 -> 0.15716404 | AB30: =VLOOKUP(O30,Parameter!$O$11:$P$22,2,0)*Process!P30 -> 15895.595 | AC30: =VLOOKUP($O30,Parameter!$O$11:$P$22,2,0)*VLOOKUP($O30,Parameter!$O$11:$T$22,6,0)*X30 -> 16498.039 | AD30: =VLOOKUP($O30,Parameter!$O$11:$P$22,2,0)*VLOOKUP($O30,Parameter!$O$11:$T$22,6,0)^2*Y30 -> 16277.422 | AE30: =VLOOKUP($O30,Parameter!$O$11:$P$22,2,0)*VLOOKUP($O30,Parameter!$O$11:$T$22,6,0)^3*Z30 -> 16541.549 | AF30: =VLOOKUP($O30,Parameter!$O$11:$P$22,2,0)*VLOOKUP($O30,Parameter!$O$11:$T$22,6,0)^4*AA30 -> 17314.261
A31: =ROW()-1 -> 30 | B31: Inbound processing | C31: M Put away | D31: Mezzanine_Put away | E31: Aisle Distance | F31: =F30 -> 12.963748 | G31: Trip | H31: MA | I31: =IFERROR(VLOOKUP(H31,Parameter!$F$44:$H$92,3,0),"") -> 20 | J31: Trolley | K31: =IFERROR(INDEX(Parameter!$D$122:$M$122,1,MATCH(Process!$J31,Parameter!$D$121:$M$121,0)),"") -> 0.42 | L31: =IFERROR(I31/K31,0) -> 47.619048 | N31: =L31+M31 -> 47.619048 | O31: Operator | P31: =N31*F31/3600/Parameter!$P$6/Parameter!$P$7 -> 0.025217375 | X31: =P31*Parameter!W$8 -> 0.024460854 | Y31: =X31*Parameter!X$8 -> 0.022554913 | Z31: =Y31*Parameter!Y$8 -> 0.021421404 | AA31: =Z31*Parameter!Z$8 -> 0.020955205 | AB31: =VLOOKUP(O31,Parameter!$O$11:$P$22,2,0)*Process!P31 -> 2119.4127 | AC31: =VLOOKUP($O31,Parameter!$O$11:$P$22,2,0)*VLOOKUP($O31,Parameter!$O$11:$T$22,6,0)*X31 -> 2199.7385 | AD31: =VLOOKUP($O31,Parameter!$O$11:$P$22,2,0)*VLOOKUP($O31,Parameter!$O$11:$T$22,6,0)^2*Y31 -> 2170.323 | AE31: =VLOOKUP($O31,Parameter!$O$11:$P$22,2,0)*VLOOKUP($O31,Parameter!$O$11:$T$22,6,0)^3*Z31 -> 2205.5399 | AF31: =VLOOKUP($O31,Parameter!$O$11:$P$22,2,0)*VLOOKUP($O31,Parameter!$O$11:$T$22,6,0)^4*AA31 -> 2308.5681
A32: =ROW()-1 -> 31 | B32: Inbound processing | C32: M Put away | D32: Mezzanine_Elevator operation | E32: Move to Elevator and Back to Elevator | F32: =F30*Parameter!R52 -> 0 | G32: Trip | H32: ME | I32: =IFERROR(VLOOKUP(H32,Parameter!$F$44:$H$92,3,0),"") -> 0 | J32: Trolley | K32: =IFERROR(INDEX(Parameter!$D$122:$M$122,1,MATCH(Process!$J32,Parameter!$D$121:$M$121,0)),"") -> 0.42 | L32: =IFERROR(I32/K32,0) -> 0 | N32: =L32+M32 -> 0 | O32: Operator | P32: =N32*F32/3600/Parameter!$P$6/Parameter!$P$7 -> 0 | X32: =P32*Parameter!W$8 -> 0 | Y32: =X32*Parameter!X$8 -> 0 | Z32: =Y32*Parameter!Y$8 -> 0 | AA32: =Z32*Parameter!Z$8 -> 0 | AB32: =VLOOKUP(O32,Parameter!$O$11:$P$22,2,0)*Process!P32 -> 0 | AC32: =VLOOKUP($O32,Parameter!$O$11:$P$22,2,0)*VLOOKUP($O32,Parameter!$O$11:$T$22,6,0)*X32 -> 0 | AD32: =VLOOKUP($O32,Parameter!$O$11:$P$22,2,0)*VLOOKUP($O32,Parameter!$O$11:$T$22,6,0)^2*Y32 -> 0 | AE32: =VLOOKUP($O32,Parameter!$O$11:$P$22,2,0)*VLOOKUP($O32,Parameter!$O$11:$T$22,6,0)^3*Z32 -> 0 | AF32: =VLOOKUP($O32,Parameter!$O$11:$P$22,2,0)*VLOOKUP($O32,Parameter!$O$11:$T$22,6,0)^4*AA32 -> 0
A33: =ROW()-1 -> 32 | B33: Inbound processing | C33: M Put away | D33: Mezzanine_Elevator operation | E33: Elevator Operation | F33: =F32 -> 0 | G33: Trip | H33: HDL | I33: =IFERROR(VLOOKUP(H33,Parameter!$F$44:$H$92,3,0),"") -> 0 | J33: Trolley | K33: =IFERROR(INDEX(Parameter!$D$122:$M$122,1,MATCH(Process!$J33,Parameter!$D$121:$M$121,0)),"") -> 0.42 | L33: =IFERROR(I33/K33,0) -> 0 | M33: 180 | N33: =L33+M33 -> 180 | O33: Operator | P33: =N33*F33/3600/Parameter!$P$6/Parameter!$P$7 -> 0 | X33: =P33*Parameter!W$8 -> 0 | Y33: =X33*Parameter!X$8 -> 0 | Z33: =Y33*Parameter!Y$8 -> 0 | AA33: =Z33*Parameter!Z$8 -> 0 | AB33: =VLOOKUP(O33,Parameter!$O$11:$P$22,2,0)*Process!P33 -> 0 | AC33: =VLOOKUP($O33,Parameter!$O$11:$P$22,2,0)*VLOOKUP($O33,Parameter!$O$11:$T$22,6,0)*X33 -> 0 | AD33: =VLOOKUP($O33,Parameter!$O$11:$P$22,2,0)*VLOOKUP($O33,Parameter!$O$11:$T$22,6,0)^2*Y33 -> 0 | AE33: =VLOOKUP($O33,Parameter!$O$11:$P$22,2,0)*VLOOKUP($O33,Parameter!$O$11:$T$22,6,0)^3*Z33 -> 0 | AF33: =VLOOKUP($O33,Parameter!$O$11:$P$22,2,0)*VLOOKUP($O33,Parameter!$O$11:$T$22,6,0)^4*AA33 -> 0
A34: =ROW()-1 -> 33 | B34: Inbound processing | C34: M Put away | D34: Mezzanine_Put away | E34: Find Bin Location | F34: =Parameter!R50 -> 103.70999 | G34: Line | H34: ML | I34: =IFERROR(VLOOKUP(H34,Parameter!$F$44:$H$92,3,0),"") -> 10 | J34: Trolley | K34: =IFERROR(INDEX(Parameter!$D$122:$M$122,1,MATCH(Process!$J34,Parameter!$D$121:$M$121,0)),"") -> 0.42 | L34: =IFERROR(I34/K34,0) -> 23.809524 | N34: =L34+M34 -> 23.809524 | O34: Operator | P34: =N34*F34/3600/Parameter!$P$6/Parameter!$P$7 -> 0.1008695 | X34: =P34*Parameter!W$8 -> 0.097843415 | Y34: =X34*Parameter!X$8 -> 0.090219652 | Z34: =Y34*Parameter!Y$8 -> 0.085685614 | AA34: =Z34*Parameter!Z$8 -> 0.083820821 | AB34: =VLOOKUP(O34,Parameter!$O$11:$P$22,2,0)*Process!P34 -> 8477.6509 | AC34: =VLOOKUP($O34,Parameter!$O$11:$P$22,2,0)*VLOOKUP($O34,Parameter!$O$11:$T$22,6,0)*X34 -> 8798.9539 | AD34: =VLOOKUP($O34,Parameter!$O$11:$P$22,2,0)*VLOOKUP($O34,Parameter!$O$11:$T$22,6,0)^2*Y34 -> 8681.292 | AE34: =VLOOKUP($O34,Parameter!$O$11:$P$22,2,0)*VLOOKUP($O34,Parameter!$O$11:$T$22,6,0)^3*Z34 -> 8822.1596 | AF34: =VLOOKUP($O34,Parameter!$O$11:$P$22,2,0)*VLOOKUP($O34,Parameter!$O$11:$T$22,6,0)^4*AA34 -> 9234.2724
A35: =ROW()-1 -> 34 | B35: Inbound processing | C35: M Put away | D35: Mezzanine_Put away | E35: Put away Parts | F35: =F34 -> 103.70999 | G35: Line | H35: HDL | I35: =IFERROR(VLOOKUP(H35,Parameter!$F$44:$H$92,3,0),"") -> 0 | J35: Trolley | K35: =IFERROR(INDEX(Parameter!$D$122:$M$122,1,MATCH(Process!$J35,Parameter!$D$121:$M$121,0)),"") -> 0.42 | L35: =IFERROR(I35/K35,0) -> 0 | M35: 20 | N35: =L35+M35 -> 20 | O35: Operator | P35: =N35*F35/3600/Parameter!$P$6/Parameter!$P$7 -> 0.08473038 | X35: =P35*Parameter!W$8 -> 0.082188469 | Y35: =X35*Parameter!X$8 -> 0.075784507 | Z35: =Y35*Parameter!Y$8 -> 0.071975916 | AA35: =Z35*Parameter!Z$8 -> 0.070409489 | AB35: =VLOOKUP(O35,Parameter!$O$11:$P$22,2,0)*Process!P35 -> 7121.2268 | AC35: =VLOOKUP($O35,Parameter!$O$11:$P$22,2,0)*VLOOKUP($O35,Parameter!$O$11:$T$22,6,0)*X35 -> 7391.1213 | AD35: =VLOOKUP($O35,Parameter!$O$11:$P$22,2,0)*VLOOKUP($O35,Parameter!$O$11:$T$22,6,0)^2*Y35 -> 7292.2853 | AE35: =VLOOKUP($O35,Parameter!$O$11:$P$22,2,0)*VLOOKUP($O35,Parameter!$O$11:$T$22,6,0)^3*Z35 -> 7410.6141 | AF35: =VLOOKUP($O35,Parameter!$O$11:$P$22,2,0)*VLOOKUP($O35,Parameter!$O$11:$T$22,6,0)^4*AA35 -> 7756.7888
A36: =ROW()-1 -> 35 | B36: Inbound processing | C36: M Put away | D36: Mezzanine_Put away | E36: Scan Bin Location | F36: =F34 -> 103.70999 | G36: Line | H36: HDL | I36: =IFERROR(VLOOKUP(H36,Parameter!$F$44:$H$92,3,0),"") -> 0 | J36: Trolley | K36: =IFERROR(INDEX(Parameter!$D$122:$M$122,1,MATCH(Process!$J36,Parameter!$D$121:$M$121,0)),"") -> 0.42 | L36: =IFERROR(I36/K36,0) -> 0 | M36: 3 | N36: =L36+M36 -> 3 | O36: Operator | P36: =N36*F36/3600/Parameter!$P$6/Parameter!$P$7 -> 0.012709557 | X36: =P36*Parameter!W$8 -> 0.01232827 | Y36: =X36*Parameter!X$8 -> 0.011367676 | Z36: =Y36*Parameter!Y$8 -> 0.010796387 | AA36: =Z36*Parameter!Z$8 -> 0.010561423 | AB36: =VLOOKUP(O36,Parameter!$O$11:$P$22,2,0)*Process!P36 -> 1068.184 | AC36: =VLOOKUP($O36,Parameter!$O$11:$P$22,2,0)*VLOOKUP($O36,Parameter!$O$11:$T$22,6,0)*X36 -> 1108.6682 | AD36: =VLOOKUP($O36,Parameter!$O$11:$P$22,2,0)*VLOOKUP($O36,Parameter!$O$11:$T$22,6,0)^2*Y36 -> 1093.8428 | AE36: =VLOOKUP($O36,Parameter!$O$11:$P$22,2,0)*VLOOKUP($O36,Parameter!$O$11:$T$22,6,0)^3*Z36 -> 1111.5921 | AF36: =VLOOKUP($O36,Parameter!$O$11:$P$22,2,0)*VLOOKUP($O36,Parameter!$O$11:$T$22,6,0)^4*AA36 -> 1163.5183
A37: =ROW()-1 -> 36 | B37: Inbound processing | C37: M Put away | D37: Mezzanine_Put away | E37: Back to IB Sorting from M Staging | F37: =F30 -> 12.963748 | G37: Trip | H37: IBSM | I37: =IFERROR(VLOOKUP(H37,Parameter!$F$44:$H$92,3,0),"") -> 150 | J37: Trolley | K37: =IFERROR(INDEX(Parameter!$D$122:$M$122,1,MATCH(Process!$J37,Parameter!$D$121:$M$121,0)),"") -> 0.42 | L37: =IFERROR(I37/K37,0) -> 357.14286 | N37: =L37+M37 -> 357.14286 | O37: Operator | P37: =N37*F37/3600/Parameter!$P$6/Parameter!$P$7 -> 0.18913031 | X37: =P37*Parameter!W$8 -> 0.1834564 | Y37: =X37*Parameter!X$8 -> 0.16916185 | Z37: =Y37*Parameter!Y$8 -> 0.16066053 | AA37: =Z37*Parameter!Z$8 -> 0.15716404 | AB37: =VLOOKUP(O37,Parameter!$O$11:$P$22,2,0)*Process!P37 -> 15895.595 | AC37: =VLOOKUP($O37,Parameter!$O$11:$P$22,2,0)*VLOOKUP($O37,Parameter!$O$11:$T$22,6,0)*X37 -> 16498.039 | AD37: =VLOOKUP($O37,Parameter!$O$11:$P$22,2,0)*VLOOKUP($O37,Parameter!$O$11:$T$22,6,0)^2*Y37 -> 16277.422 | AE37: =VLOOKUP($O37,Parameter!$O$11:$P$22,2,0)*VLOOKUP($O37,Parameter!$O$11:$T$22,6,0)^3*Z37 -> 16541.549 | AF37: =VLOOKUP($O37,Parameter!$O$11:$P$22,2,0)*VLOOKUP($O37,Parameter!$O$11:$T$22,6,0)^4*AA37 -> 17314.261
A38: =ROW()-1 -> 37 | B38: Inbound processing | C38: F Put away | D38: Floor_Put away | E38: Check TO Label | F38: =Parameter!R54/Parameter!R55 -> 222.23568 | G38: Trip | H38: HDL | I38: =IFERROR(VLOOKUP(H38,Parameter!$F$44:$H$92,3,0),"") -> 0 | J38: CB | K38: =IFERROR(INDEX(Parameter!$D$122:$M$122,1,MATCH(Process!$J38,Parameter!$D$121:$M$121,0)),"") -> 2.7777778 | L38: =IFERROR(I38/K38,0) -> 0 | M38: 5 | N38: =L38+M38 -> 5 | O38: MHE Driver | P38: =N38*F38/3600/Parameter!$P$6/Parameter!$P$7 -> 0.045391275 | X38: =P38*Parameter!W$8 -> 0.044029537 | Y38: =X38*Parameter!X$8 -> 0.040598843 | Z38: =Y38*Parameter!Y$8 -> 0.038558526 | AA38: =Z38*Parameter!Z$8 -> 0.037719369 | AB38: =VLOOKUP(O38,Parameter!$O$11:$P$22,2,0)*Process!P38 -> 4577.9315 | AC38: =VLOOKUP($O38,Parameter!$O$11:$P$22,2,0)*VLOOKUP($O38,Parameter!$O$11:$T$22,6,0)*X38 -> 4751.4351 | AD38: =VLOOKUP($O38,Parameter!$O$11:$P$22,2,0)*VLOOKUP($O38,Parameter!$O$11:$T$22,6,0)^2*Y38 -> 4687.8977 | AE38: =VLOOKUP($O38,Parameter!$O$11:$P$22,2,0)*VLOOKUP($O38,Parameter!$O$11:$T$22,6,0)^3*Z38 -> 4763.9662 | AF38: =VLOOKUP($O38,Parameter!$O$11:$P$22,2,0)*VLOOKUP($O38,Parameter!$O$11:$T$22,6,0)^4*AA38 -> 4986.5071
A39: =ROW()-1 -> 38 | B39: Inbound processing | C39: F Put away | D39: Floor_Put away | E39: Move to F Staging | F39: =Parameter!R54*Parameter!R55 -> 222.23568 | G39: Trip | H39: IBSF | I39: =IFERROR(VLOOKUP(H39,Parameter!$F$44:$H$92,3,0),"") -> 110 | J39: CB | K39: =IFERROR(INDEX(Parameter!$D$122:$M$122,1,MATCH(Process!$J39,Parameter!$D$121:$M$121,0)),"") -> 2.7777778 | L39: =IFERROR(I39/K39,0) -> 39.6 | N39: =L39+M39 -> 39.6 | O39: MHE Driver | P39: =N39*F39/3600/Parameter!$P$6/Parameter!$P$7 -> 0.3594989 | X39: =P39*Parameter!W$8 -> 0.34871393 | Y39: =X39*Parameter!X$8 -> 0.32154284 | Z39: =Y39*Parameter!Y$8 -> 0.30538353 | AA39: =Z39*Parameter!Z$8 -> 0.29873741 | AB39: =VLOOKUP(O39,Parameter!$O$11:$P$22,2,0)*Process!P39 -> 36257.217 | AC39: =VLOOKUP($O39,Parameter!$O$11:$P$22,2,0)*VLOOKUP($O39,Parameter!$O$11:$T$22,6,0)*X39 -> 37631.366 | AD39: =VLOOKUP($O39,Parameter!$O$11:$P$22,2,0)*VLOOKUP($O39,Parameter!$O$11:$T$22,6,0)^2*Y39 -> 37128.15 | AE39: =VLOOKUP($O39,Parameter!$O$11:$P$22,2,0)*VLOOKUP($O39,Parameter!$O$11:$T$22,6,0)^3*Z39 -> 37730.612 | AF39: =VLOOKUP($O39,Parameter!$O$11:$P$22,2,0)*VLOOKUP($O39,Parameter!$O$11:$T$22,6,0)^4*AA39 -> 39493.136
A40: =ROW()-1 -> 39 | B40: Inbound processing | C40: F Put away | D40: Floor_Put away | E40: Aisle Distance | F40: =F39 -> 222.23568 | G40: Trip | H40: FA | I40: =IFERROR(VLOOKUP(H40,Parameter!$F$44:$H$92,3,0),"") -> 90 | J40: CB | K40: =IFERROR(INDEX(Parameter!$D$122:$M$122,1,MATCH(Process!$J40,Parameter!$D$121:$M$121,0)),"") -> 2.7777778 | L40: =IFERROR(I40/K40,0) -> 32.4 | N40: =L40+M40 -> 32.4 | O40: MHE Driver | P40: =N40*F40/3600/Parameter!$P$6/Parameter!$P$7 -> 0.29413546 | X40: =P40*Parameter!W$8 -> 0.2853114 | Y40: =X40*Parameter!X$8 -> 0.2630805 | Z40: =Y40*Parameter!Y$8 -> 0.24985925 | AA40: =Z40*Parameter!Z$8 -> 0.24442151 | AB40: =VLOOKUP(O40,Parameter!$O$11:$P$22,2,0)*Process!P40 -> 29664.996 | AC40: =VLOOKUP($O40,Parameter!$O$11:$P$22,2,0)*VLOOKUP($O40,Parameter!$O$11:$T$22,6,0)*X40 -> 30789.299 | AD40: =VLOOKUP($O40,Parameter!$O$11:$P$22,2,0)*VLOOKUP($O40,Parameter!$O$11:$T$22,6,0)^2*Y40 -> 30377.577 | AE40: =VLOOKUP($O40,Parameter!$O$11:$P$22,2,0)*VLOOKUP($O40,Parameter!$O$11:$T$22,6,0)^3*Z40 -> 30870.501 | AF40: =VLOOKUP($O40,Parameter!$O$11:$P$22,2,0)*VLOOKUP($O40,Parameter!$O$11:$T$22,6,0)^4*AA40 -> 32312.566
A41: =ROW()-1 -> 40 | B41: Inbound processing | C41: F Put away | D41: Floor_Put away | E41: Find Bin Location | F41: =Parameter!R54 -> 222.23568 | G41: Line | H41: FL | I41: =IFERROR(VLOOKUP(H41,Parameter!$F$44:$H$92,3,0),"") -> 60 | J41: CB | K41: =IFERROR(INDEX(Parameter!$D$122:$M$122,1,MATCH(Process!$J41,Parameter!$D$121:$M$121,0)),"") -> 2.7777778 | L41: =IFERROR(I41/K41,0) -> 21.6 | N41: =L41+M41 -> 21.6 | O41: MHE Driver | P41: =N41*F41/3600/Parameter!$P$6/Parameter!$P$7 -> 0.19609031 | X41: =P41*Parameter!W$8 -> 0.1902076 | Y41: =X41*Parameter!X$8 -> 0.175387 | Z41: =Y41*Parameter!Y$8 -> 0.16657283 | AA41: =Z41*Parameter!Z$8 -> 0.16294768 | AB41: =VLOOKUP(O41,Parameter!$O$11:$P$22,2,0)*Process!P41 -> 19776.664 | AC41: =VLOOKUP($O41,Parameter!$O$11:$P$22,2,0)*VLOOKUP($O41,Parameter!$O$11:$T$22,6,0)*X41 -> 20526.2 | AD41: =VLOOKUP($O41,Parameter!$O$11:$P$22,2,0)*VLOOKUP($O41,Parameter!$O$11:$T$22,6,0)^2*Y41 -> 20251.718 | AE41: =VLOOKUP($O41,Parameter!$O$11:$P$22,2,0)*VLOOKUP($O41,Parameter!$O$11:$T$22,6,0)^3*Z41 -> 20580.334 | AF41: =VLOOKUP($O41,Parameter!$O$11:$P$22,2,0)*VLOOKUP($O41,Parameter!$O$11:$T$22,6,0)^4*AA41 -> 21541.711
A42: =ROW()-1 -> 41 | B42: Inbound processing | C42: F Put away | D42: Floor_Put away | E42: Put away Pallet | F42: =F41 -> 222.23568 | G42: Line | H42: HDL | I42: =IFERROR(VLOOKUP(H42,Parameter!$F$44:$H$92,3,0),"") -> 0 | J42: CB | K42: =IFERROR(INDEX(Parameter!$D$122:$M$122,1,MATCH(Process!$J42,Parameter!$D$121:$M$121,0)),"") -> 2.7777778 | L42: =IFERROR(I42/K42,0) -> 0 | M42: 15 | N42: =L42+M42 -> 15 | O42: MHE Driver | P42: =N42*F42/3600/Parameter!$P$6/Parameter!$P$7 -> 0.13617382 | X42: =P42*Parameter!W$8 -> 0.13208861 | Y42: =X42*Parameter!X$8 -> 0.12179653 | Z42: =Y42*Parameter!Y$8 -> 0.11567558 | AA42: =Z42*Parameter!Z$8 -> 0.11315811 | AB42: =VLOOKUP(O42,Parameter!$O$11:$P$22,2,0)*Process!P42 -> 13733.795 | AC42: =VLOOKUP($O42,Parameter!$O$11:$P$22,2,0)*VLOOKUP($O42,Parameter!$O$11:$T$22,6,0)*X42 -> 14254.305 | AD42: =VLOOKUP($O42,Parameter!$O$11:$P$22,2,0)*VLOOKUP($O42,Parameter!$O$11:$T$22,6,0)^2*Y42 -> 14063.693 | AE42: =VLOOKUP($O42,Parameter!$O$11:$P$22,2,0)*VLOOKUP($O42,Parameter!$O$11:$T$22,6,0)^3*Z42 -> 14291.899 | AF42: =VLOOKUP($O42,Parameter!$O$11:$P$22,2,0)*VLOOKUP($O42,Parameter!$O$11:$T$22,6,0)^4*AA42 -> 14959.521
A43: =ROW()-1 -> 42 | B43: Inbound processing | C43: F Put away | D43: Floor_Put away | E43: Scan Bin Location | F43: =F41 -> 222.23568 | G43: Line | H43: HDL | I43: =IFERROR(VLOOKUP(H43,Parameter!$F$44:$H$92,3,0),"") -> 0 | J43: CB | K43: =IFERROR(INDEX(Parameter!$D$122:$M$122,1,MATCH(Process!$J43,Parameter!$D$121:$M$121,0)),"") -> 2.7777778 | L43: =IFERROR(I43/K43,0) -> 0 | M43: 5 | N43: =L43+M43 -> 5 | O43: MHE Driver | P43: =N43*F43/3600/Parameter!$P$6/Parameter!$P$7 -> 0.045391275 | X43: =P43*Parameter!W$8 -> 0.044029537 | Y43: =X43*Parameter!X$8 -> 0.040598843 | Z43: =Y43*Parameter!Y$8 -> 0.038558526 | AA43: =Z43*Parameter!Z$8 -> 0.037719369 | AB43: =VLOOKUP(O43,Parameter!$O$11:$P$22,2,0)*Process!P43 -> 4577.9315 | AC43: =VLOOKUP($O43,Parameter!$O$11:$P$22,2,0)*VLOOKUP($O43,Parameter!$O$11:$T$22,6,0)*X43 -> 4751.4351 | AD43: =VLOOKUP($O43,Parameter!$O$11:$P$22,2,0)*VLOOKUP($O43,Parameter!$O$11:$T$22,6,0)^2*Y43 -> 4687.8977 | AE43: =VLOOKUP($O43,Parameter!$O$11:$P$22,2,0)*VLOOKUP($O43,Parameter!$O$11:$T$22,6,0)^3*Z43 -> 4763.9662 | AF43: =VLOOKUP($O43,Parameter!$O$11:$P$22,2,0)*VLOOKUP($O43,Parameter!$O$11:$T$22,6,0)^4*AA43 -> 4986.5071
A44: =ROW()-1 -> 43 | B44: Inbound processing | C44: F Put away | D44: Floor_Put away | E44: Back to IB Sorting from F | F44: =F38 -> 222.23568 | G44: Trip | H44: IBSF | I44: =IFERROR(VLOOKUP(H44,Parameter!$F$44:$H$92,3,0),"") -> 110 | J44: CB | K44: =IFERROR(INDEX(Parameter!$D$122:$M$122,1,MATCH(Process!$J44,Parameter!$D$121:$M$121,0)),"") -> 2.7777778 | L44: =IFERROR(I44/K44,0) -> 39.6 | N44: =L44+M44 -> 39.6 | O44: MHE Driver | P44: =N44*F44/3600/Parameter!$P$6/Parameter!$P$7 -> 0.3594989 | X44: =P44*Parameter!W$8 -> 0.34871393 | Y44: =X44*Parameter!X$8 -> 0.32154284 | Z44: =Y44*Parameter!Y$8 -> 0.30538353 | AA44: =Z44*Parameter!Z$8 -> 0.29873741 | AB44: =VLOOKUP(O44,Parameter!$O$11:$P$22,2,0)*Process!P44 -> 36257.217 | AC44: =VLOOKUP($O44,Parameter!$O$11:$P$22,2,0)*VLOOKUP($O44,Parameter!$O$11:$T$22,6,0)*X44 -> 37631.366 | AD44: =VLOOKUP($O44,Parameter!$O$11:$P$22,2,0)*VLOOKUP($O44,Parameter!$O$11:$T$22,6,0)^2*Y44 -> 37128.15 | AE44: =VLOOKUP($O44,Parameter!$O$11:$P$22,2,0)*VLOOKUP($O44,Parameter!$O$11:$T$22,6,0)^3*Z44 -> 37730.612 | AF44: =VLOOKUP($O44,Parameter!$O$11:$P$22,2,0)*VLOOKUP($O44,Parameter!$O$11:$T$22,6,0)^4*AA44 -> 39493.136
A45: =ROW()-1 -> 44 | B45: Inbound processing | C45: R Put away | D45: Racking_Put away | E45: Check TO Label | F45: =Parameter!R57/Parameter!R58 -> 355.57709 | G45: Trip | H45: HDL | I45: =IFERROR(VLOOKUP(H45,Parameter!$F$44:$H$92,3,0),"") -> 0 | J45: R-Truck | K45: =IFERROR(INDEX(Parameter!$D$122:$M$122,1,MATCH(Process!$J45,Parameter!$D$121:$M$121,0)),"") -> 2.7777778 | L45: =IFERROR(I45/K45,0) -> 0 | M45: 5 | N45: =L45+M45 -> 5 | O45: MHE Driver | P45: =N45*F45/3600/Parameter!$P$6/Parameter!$P$7 -> 0.07262604 | X45: =P45*Parameter!W$8 -> 0.070447259 | Y45: =X45*Parameter!X$8 -> 0.064958149 | Z45: =Y45*Parameter!Y$8 -> 0.061693642 | AA45: =Z45*Parameter!Z$8 -> 0.060350991 | AB45: =VLOOKUP(O45,Parameter!$O$11:$P$22,2,0)*Process!P45 -> 7324.6904 | AC45: =VLOOKUP($O45,Parameter!$O$11:$P$22,2,0)*VLOOKUP($O45,Parameter!$O$11:$T$22,6,0)*X45 -> 7602.2962 | AD45: =VLOOKUP($O45,Parameter!$O$11:$P$22,2,0)*VLOOKUP($O45,Parameter!$O$11:$T$22,6,0)^2*Y45 -> 7500.6363 | AE45: =VLOOKUP($O45,Parameter!$O$11:$P$22,2,0)*VLOOKUP($O45,Parameter!$O$11:$T$22,6,0)^3*Z45 -> 7622.3459 | AF45: =VLOOKUP($O45,Parameter!$O$11:$P$22,2,0)*VLOOKUP($O45,Parameter!$O$11:$T$22,6,0)^4*AA45 -> 7978.4114
A46: =ROW()-1 -> 45 | B46: Inbound processing | C46: R Put away | D46: Racking_Put away | E46: Move to R Staging | F46: =F45 -> 355.57709 | G46: Trip | H46: IBSR | I46: =IFERROR(VLOOKUP(H46,Parameter!$F$44:$H$92,3,0),"") -> 77 | J46: R-Truck | K46: =IFERROR(INDEX(Parameter!$D$122:$M$122,1,MATCH(Process!$J46,Parameter!$D$121:$M$121,0)),"") -> 2.7777778 | L46: =IFERROR(I46/K46,0) -> 27.72 | N46: =L46+M46 -> 27.72 | O46: MHE Driver | P46: =N46*F46/3600/Parameter!$P$6/Parameter!$P$7 -> 0.40263877 | X46: =P46*Parameter!W$8 -> 0.3905596 | Y46: =X46*Parameter!X$8 -> 0.36012798 | Z46: =Y46*Parameter!Y$8 -> 0.34202955 | AA46: =Z46*Parameter!Z$8 -> 0.33458589 | AB46: =VLOOKUP(O46,Parameter!$O$11:$P$22,2,0)*Process!P46 -> 40608.084 | AC46: =VLOOKUP($O46,Parameter!$O$11:$P$22,2,0)*VLOOKUP($O46,Parameter!$O$11:$T$22,6,0)*X46 -> 42147.13 | AD46: =VLOOKUP($O46,Parameter!$O$11:$P$22,2,0)*VLOOKUP($O46,Parameter!$O$11:$T$22,6,0)^2*Y46 -> 41583.528 | AE46: =VLOOKUP($O46,Parameter!$O$11:$P$22,2,0)*VLOOKUP($O46,Parameter!$O$11:$T$22,6,0)^3*Z46 -> 42258.286 | AF46: =VLOOKUP($O46,Parameter!$O$11:$P$22,2,0)*VLOOKUP($O46,Parameter!$O$11:$T$22,6,0)^4*AA46 -> 44232.313
A47: =ROW()-1 -> 46 | B47: Inbound processing | C47: R Put away | D47: Racking_Put away | E47: Aisle Distance | F47: =F46 -> 355.57709 | G47: Trip | H47: RA | I47: =IFERROR(VLOOKUP(H47,Parameter!$F$44:$H$92,3,0),"") -> 80 | J47: R-Truck | K47: =IFERROR(INDEX(Parameter!$D$122:$M$122,1,MATCH(Process!$J47,Parameter!$D$121:$M$121,0)),"") -> 2.7777778 | L47: =IFERROR(I47/K47,0) -> 28.8 | N47: =L47+M47 -> 28.8 | O47: MHE Driver | P47: =N47*F47/3600/Parameter!$P$6/Parameter!$P$7 -> 0.41832599 | X47: =P47*Parameter!W$8 -> 0.40577621 | Y47: =X47*Parameter!X$8 -> 0.37415894 | Z47: =Y47*Parameter!Y$8 -> 0.35535538 | AA47: =Z47*Parameter!Z$8 -> 0.34762171 | AB47: =VLOOKUP(O47,Parameter!$O$11:$P$22,2,0)*Process!P47 -> 42190.217 | AC47: =VLOOKUP($O47,Parameter!$O$11:$P$22,2,0)*VLOOKUP($O47,Parameter!$O$11:$T$22,6,0)*X47 -> 43789.226 | AD47: =VLOOKUP($O47,Parameter!$O$11:$P$22,2,0)*VLOOKUP($O47,Parameter!$O$11:$T$22,6,0)^2*Y47 -> 43203.665 | AE47: =VLOOKUP($O47,Parameter!$O$11:$P$22,2,0)*VLOOKUP($O47,Parameter!$O$11:$T$22,6,0)^3*Z47 -> 43904.712 | AF47: =VLOOKUP($O47,Parameter!$O$11:$P$22,2,0)*VLOOKUP($O47,Parameter!$O$11:$T$22,6,0)^4*AA47 -> 45955.649
A48: =ROW()-1 -> 47 | B48: Inbound processing | C48: R Put away | D48: Racking_Put away | E48: Find Bin Location | F48: =Parameter!R57 -> 355.57709 | G48: Line | H48: RL | I48: =IFERROR(VLOOKUP(H48,Parameter!$F$44:$H$92,3,0),"") -> 30 | J48: R-Truck | K48: =IFERROR(INDEX(Parameter!$D$122:$M$122,1,MATCH(Process!$J48,Parameter!$D$121:$M$121,0)),"") -> 2.7777778 | L48: =IFERROR(I48/K48,0) -> 10.8 | N48: =L48+M48 -> 10.8 | O48: MHE Driver | P48: =N48*F48/3600/Parameter!$P$6/Parameter!$P$7 -> 0.15687225 | X48: =P48*Parameter!W$8 -> 0.15216608 | Y48: =X48*Parameter!X$8 -> 0.1403096 | Z48: =Y48*Parameter!Y$8 -> 0.13325827 | AA48: =Z48*Parameter!Z$8 -> 0.13035814 | AB48: =VLOOKUP(O48,Parameter!$O$11:$P$22,2,0)*Process!P48 -> 15821.331 | AC48: =VLOOKUP($O48,Parameter!$O$11:$P$22,2,0)*VLOOKUP($O48,Parameter!$O$11:$T$22,6,0)*X48 -> 16420.96 | AD48: =VLOOKUP($O48,Parameter!$O$11:$P$22,2,0)*VLOOKUP($O48,Parameter!$O$11:$T$22,6,0)^2*Y48 -> 16201.374 | AE48: =VLOOKUP($O48,Parameter!$O$11:$P$22,2,0)*VLOOKUP($O48,Parameter!$O$11:$T$22,6,0)^3*Z48 -> 16464.267 | AF48: =VLOOKUP($O48,Parameter!$O$11:$P$22,2,0)*VLOOKUP($O48,Parameter!$O$11:$T$22,6,0)^4*AA48 -> 17233.369
A49: =ROW()-1 -> 48 | B49: Inbound processing | C49: R Put away | D49: Racking_Put away | E49: Put away Pallet | F49: =F46*(1-Parameter!R59) -> 284.46167 | G49: Line | H49: HDL | I49: =IFERROR(VLOOKUP(H49,Parameter!$F$44:$H$92,3,0),"") -> 0 | J49: R-Truck | K49: =IFERROR(INDEX(Parameter!$D$122:$M$122,1,MATCH(Process!$J49,Parameter!$D$121:$M$121,0)),"") -> 2.7777778 | L49: =IFERROR(I49/K49,0) -> 0 | M49: 60 | N49: =L49+M49 -> 60 | O49: MHE Driver | P49: =N49*F49/3600/Parameter!$P$6/Parameter!$P$7 -> 0.69720998 | X49: =P49*Parameter!W$8 -> 0.67629368 | Y49: =X49*Parameter!X$8 -> 0.62359823 | Z49: =Y49*Parameter!Y$8 -> 0.59225897 | AA49: =Z49*Parameter!Z$8 -> 0.57936951 | AB49: =VLOOKUP(O49,Parameter!$O$11:$P$22,2,0)*Process!P49 -> 70317.028 | AC49: =VLOOKUP($O49,Parameter!$O$11:$P$22,2,0)*VLOOKUP($O49,Parameter!$O$11:$T$22,6,0)*X49 -> 72982.043 | AD49: =VLOOKUP($O49,Parameter!$O$11:$P$22,2,0)*VLOOKUP($O49,Parameter!$O$11:$T$22,6,0)^2*Y49 -> 72006.108 | AE49: =VLOOKUP($O49,Parameter!$O$11:$P$22,2,0)*VLOOKUP($O49,Parameter!$O$11:$T$22,6,0)^3*Z49 -> 73174.521 | AF49: =VLOOKUP($O49,Parameter!$O$11:$P$22,2,0)*VLOOKUP($O49,Parameter!$O$11:$T$22,6,0)^4*AA49 -> 76592.749
A50: =ROW()-1 -> 49 | B50: Inbound processing | C50: R Put away | D50: Racking_Put away | E50: Scan Bin Location | F50: =F49 -> 284.46167 | G50: Line | H50: HDL | I50: =IFERROR(VLOOKUP(H50,Parameter!$F$44:$H$92,3,0),"") -> 0 | J50: R-Truck | K50: =IFERROR(INDEX(Parameter!$D$122:$M$122,1,MATCH(Process!$J50,Parameter!$D$121:$M$121,0)),"") -> 2.7777778 | L50: =IFERROR(I50/K50,0) -> 0 | M50: 5 | N50: =L50+M50 -> 5 | O50: MHE Driver | P50: =N50*F50/3600/Parameter!$P$6/Parameter!$P$7 -> 0.058100832 | X50: =P50*Parameter!W$8 -> 0.056357807 | Y50: =X50*Parameter!X$8 -> 0.051966519 | Z50: =Y50*Parameter!Y$8 -> 0.049354914 | AA50: =Z50*Parameter!Z$8 -> 0.048280793 | AB50: =VLOOKUP(O50,Parameter!$O$11:$P$22,2,0)*Process!P50 -> 5859.7523 | AC50: =VLOOKUP($O50,Parameter!$O$11:$P$22,2,0)*VLOOKUP($O50,Parameter!$O$11:$T$22,6,0)*X50 -> 6081.8369 | AD50: =VLOOKUP($O50,Parameter!$O$11:$P$22,2,0)*VLOOKUP($O50,Parameter!$O$11:$T$22,6,0)^2*Y50 -> 6000.509 | AE50: =VLOOKUP($O50,Parameter!$O$11:$P$22,2,0)*VLOOKUP($O50,Parameter!$O$11:$T$22,6,0)^3*Z50 -> 6097.8767 | AF50: =VLOOKUP($O50,Parameter!$O$11:$P$22,2,0)*VLOOKUP($O50,Parameter!$O$11:$T$22,6,0)^4*AA50 -> 6382.7291
A51: =ROW()-1 -> 50 | B51: Inbound processing | C51: R Put away | D51: Racking_Put away | E51: Back to IB Sorting from R | F51: =F46 -> 355.57709 | G51: Trip | H51: IBSR | I51: =IFERROR(VLOOKUP(H51,Parameter!$F$44:$H$92,3,0),"") -> 77 | J51: R-Truck | K51: =IFERROR(INDEX(Parameter!$D$122:$M$122,1,MATCH(Process!$J51,Parameter!$D$121:$M$121,0)),"") -> 2.7777778 | L51: =IFERROR(I51/K51,0) -> 27.72 | N51: =L51+M51 -> 27.72 | O51: MHE Driver | P51: =N51*F51/3600/Parameter!$P$6/Parameter!$P$7 -> 0.40263877 | X51: =P51*Parameter!W$8 -> 0.3905596 | Y51: =X51*Parameter!X$8 -> 0.36012798 | Z51: =Y51*Parameter!Y$8 -> 0.34202955 | AA51: =Z51*Parameter!Z$8 -> 0.33458589 | AB51: =VLOOKUP(O51,Parameter!$O$11:$P$22,2,0)*Process!P51 -> 40608.084 | AC51: =VLOOKUP($O51,Parameter!$O$11:$P$22,2,0)*VLOOKUP($O51,Parameter!$O$11:$T$22,6,0)*X51 -> 42147.13 | AD51: =VLOOKUP($O51,Parameter!$O$11:$P$22,2,0)*VLOOKUP($O51,Parameter!$O$11:$T$22,6,0)^2*Y51 -> 41583.528 | AE51: =VLOOKUP($O51,Parameter!$O$11:$P$22,2,0)*VLOOKUP($O51,Parameter!$O$11:$T$22,6,0)^3*Z51 -> 42258.286 | AF51: =VLOOKUP($O51,Parameter!$O$11:$P$22,2,0)*VLOOKUP($O51,Parameter!$O$11:$T$22,6,0)^4*AA51 -> 44232.313
A52: =ROW()-1 -> 51 | B52: Inbound processing | C52: R Put away | D52: Racking_Put away | E52: Case putaway | F52: =F48-F49 -> 71.115418 | G52: Line | H52: HDL | I52: =IFERROR(VLOOKUP(H52,Parameter!$F$44:$H$92,3,0),"") -> 0 | J52: OP-raise/down | K52: =IFERROR(INDEX(Parameter!$D$122:$M$122,1,MATCH(Process!$J52,Parameter!$D$121:$M$121,0)),"") -> 0.5 | L52: =IFERROR(I52/K52,0) -> 0 | M52: 240 | N52: =L52+M52 -> 240 | O52: MHE Driver | P52: =N52*F52/3600/Parameter!$P$6/Parameter!$P$7 -> 0.69720998 | X52: =P52*Parameter!W$8 -> 0.67629368 | Y52: =X52*Parameter!X$8 -> 0.62359823 | Z52: =Y52*Parameter!Y$8 -> 0.59225897 | AA52: =Z52*Parameter!Z$8 -> 0.57936951 | AB52: =VLOOKUP(O52,Parameter!$O$11:$P$22,2,0)*Process!P52 -> 70317.028 | AC52: =VLOOKUP($O52,Parameter!$O$11:$P$22,2,0)*VLOOKUP($O52,Parameter!$O$11:$T$22,6,0)*X52 -> 72982.043 | AD52: =VLOOKUP($O52,Parameter!$O$11:$P$22,2,0)*VLOOKUP($O52,Parameter!$O$11:$T$22,6,0)^2*Y52 -> 72006.108 | AE52: =VLOOKUP($O52,Parameter!$O$11:$P$22,2,0)*VLOOKUP($O52,Parameter!$O$11:$T$22,6,0)^3*Z52 -> 73174.521 | AF52: =VLOOKUP($O52,Parameter!$O$11:$P$22,2,0)*VLOOKUP($O52,Parameter!$O$11:$T$22,6,0)^4*AA52 -> 76592.749
A53: =ROW()-1 -> 52 | B53: Inbound processing | C53: C5 Put away | D53: Non-critical DG parts put away | E53: Check TO Label | F53: =Parameter!R47/Parameter!R62 -> 18.763567 | G53: Trip | H53: HDL | I53: =IFERROR(VLOOKUP(H53,Parameter!$F$44:$H$92,3,0),"") -> 0 | J53: CB - DG | K53: =IFERROR(INDEX(Parameter!$D$122:$M$122,1,MATCH(Process!$J53,Parameter!$D$121:$M$121,0)),"") -> 0.5 | L53: =IFERROR(I53/K53,0) -> 0 | M53: 5 | N53: =L53+M53 -> 5 | O53: DG operator | P53: =N53*F53/3600/Parameter!$P$6/Parameter!$P$7 -> 0.0038324278 | X53: =P53*Parameter!W$8 -> 0.003717455 | Y53: =X53*Parameter!X$8 -> 0.0034277983 | Z53: =Y53*Parameter!Y$8 -> 0.0032555325 | AA53: =Z53*Parameter!Z$8 -> 0.0031846816 | AB53: =VLOOKUP(O53,Parameter!$O$11:$P$22,2,0)*Process!P53 -> 386.51904 | AC53: =VLOOKUP($O53,Parameter!$O$11:$P$22,2,0)*VLOOKUP($O53,Parameter!$O$11:$T$22,6,0)*X53 -> 401.16811 | AD53: =VLOOKUP($O53,Parameter!$O$11:$P$22,2,0)*VLOOKUP($O53,Parameter!$O$11:$T$22,6,0)^2*Y53 -> 395.80359 | AE53: =VLOOKUP($O53,Parameter!$O$11:$P$22,2,0)*VLOOKUP($O53,Parameter!$O$11:$T$22,6,0)^3*Z53 -> 402.22612 | AF53: =VLOOKUP($O53,Parameter!$O$11:$P$22,2,0)*VLOOKUP($O53,Parameter!$O$11:$T$22,6,0)^4*AA53 -> 421.01546
A54: =ROW()-1 -> 53 | B54: Inbound processing | C54: C5 Put away | D54: Non-critical DG parts put away | E54: Move to C5 Staging | F54: =F53 -> 18.763567 | G54: Trip | H54: IBSC | I54: =IFERROR(VLOOKUP(H54,Parameter!$F$44:$H$92,3,0),"") -> 320 | J54: CB - DG | K54: =IFERROR(INDEX(Parameter!$D$122:$M$122,1,MATCH(Process!$J54,Parameter!$D$121:$M$121,0)),"") -> 0.5 | L54: =IFERROR(I54/K54,0) -> 640 | N54: =L54+M54 -> 640 | O54: DG operator | P54: =N54*F54/3600/Parameter!$P$6/Parameter!$P$7 -> 0.49055076 | X54: =P54*Parameter!W$8 -> 0.47583424 | Y54: =X54*Parameter!X$8 -> 0.43875818 | Z54: =Y54*Parameter!Y$8 -> 0.41670816 | AA54: =Z54*Parameter!Z$8 -> 0.40763925 | AB54: =VLOOKUP(O54,Parameter!$O$11:$P$22,2,0)*Process!P54 -> 49474.437 | AC54: =VLOOKUP($O54,Parameter!$O$11:$P$22,2,0)*VLOOKUP($O54,Parameter!$O$11:$T$22,6,0)*X54 -> 51349.518 | AD54: =VLOOKUP($O54,Parameter!$O$11:$P$22,2,0)*VLOOKUP($O54,Parameter!$O$11:$T$22,6,0)^2*Y54 -> 50662.859 | AE54: =VLOOKUP($O54,Parameter!$O$11:$P$22,2,0)*VLOOKUP($O54,Parameter!$O$11:$T$22,6,0)^3*Z54 -> 51484.944 | AF54: =VLOOKUP($O54,Parameter!$O$11:$P$22,2,0)*VLOOKUP($O54,Parameter!$O$11:$T$22,6,0)^4*AA54 -> 53889.979
A55: =ROW()-1 -> 54 | B55: Inbound processing | C55: C5 Put away | D55: Non-critical DG parts put away | E55: Aisle Distance | F55: =F54 -> 18.763567 | G55: Trip | H55: CA | I55: =IFERROR(VLOOKUP(H55,Parameter!$F$44:$H$92,3,0),"") -> 30 | J55: CB - DG | K55: =IFERROR(INDEX(Parameter!$D$122:$M$122,1,MATCH(Process!$J55,Parameter!$D$121:$M$121,0)),"") -> 0.5 | L55: =IFERROR(I55/K55,0) -> 60 | N55: =L55+M55 -> 60 | O55: DG operator | P55: =N55*F55/3600/Parameter!$P$6/Parameter!$P$7 -> 0.045989134 | X55: =P55*Parameter!W$8 -> 0.04460946 | Y55: =X55*Parameter!X$8 -> 0.04113358 | Z55: =Y55*Parameter!Y$8 -> 0.03906639 | AA55: =Z55*Parameter!Z$8 -> 0.03821618 | AB55: =VLOOKUP(O55,Parameter!$O$11:$P$22,2,0)*Process!P55 -> 4638.2285 | AC55: =VLOOKUP($O55,Parameter!$O$11:$P$22,2,0)*VLOOKUP($O55,Parameter!$O$11:$T$22,6,0)*X55 -> 4814.0173 | AD55: =VLOOKUP($O55,Parameter!$O$11:$P$22,2,0)*VLOOKUP($O55,Parameter!$O$11:$T$22,6,0)^2*Y55 -> 4749.643 | AE55: =VLOOKUP($O55,Parameter!$O$11:$P$22,2,0)*VLOOKUP($O55,Parameter!$O$11:$T$22,6,0)^3*Z55 -> 4826.7135 | AF55: =VLOOKUP($O55,Parameter!$O$11:$P$22,2,0)*VLOOKUP($O55,Parameter!$O$11:$T$22,6,0)^4*AA55 -> 5052.1855
A56: =ROW()-1 -> 55 | B56: Inbound processing | C56: C5 Put away | D56: Non-critical DG parts put away | E56: Find Bin Location | F56: =Parameter!R47 -> 45.03256 | G56: Line | H56: CL | I56: =IFERROR(VLOOKUP(H56,Parameter!$F$44:$H$92,3,0),"") -> 30 | J56: CB - DG | K56: =IFERROR(INDEX(Parameter!$D$122:$M$122,1,MATCH(Process!$J56,Parameter!$D$121:$M$121,0)),"") -> 0.5 | L56: =IFERROR(I56/K56,0) -> 60 | N56: =L56+M56 -> 60 | O56: DG operator | P56: =N56*F56/3600/Parameter!$P$6/Parameter!$P$7 -> 0.11037392 | X56: =P56*Parameter!W$8 -> 0.1070627 | Y56: =X56*Parameter!X$8 -> 0.098720592 | Z56: =Y56*Parameter!Y$8 -> 0.093759335 | AA56: =Z56*Parameter!Z$8 -> 0.091718831 | AB56: =VLOOKUP(O56,Parameter!$O$11:$P$22,2,0)*Process!P56 -> 11131.748 | AC56: =VLOOKUP($O56,Parameter!$O$11:$P$22,2,0)*VLOOKUP($O56,Parameter!$O$11:$T$22,6,0)*X56 -> 11553.642 | AD56: =VLOOKUP($O56,Parameter!$O$11:$P$22,2,0)*VLOOKUP($O56,Parameter!$O$11:$T$22,6,0)^2*Y56 -> 11399.143 | AE56: =VLOOKUP($O56,Parameter!$O$11:$P$22,2,0)*VLOOKUP($O56,Parameter!$O$11:$T$22,6,0)^3*Z56 -> 11584.112 | AF56: =VLOOKUP($O56,Parameter!$O$11:$P$22,2,0)*VLOOKUP($O56,Parameter!$O$11:$T$22,6,0)^4*AA56 -> 12125.245
A57: =ROW()-1 -> 56 | B57: Inbound processing | C57: C5 Put away | D57: Non-critical DG parts put away | E57: Put away Pallet | F57: =F56 -> 45.03256 | G57: Line | H57: HDL | I57: =IFERROR(VLOOKUP(H57,Parameter!$F$44:$H$92,3,0),"") -> 0 | J57: CB - DG | K57: =IFERROR(INDEX(Parameter!$D$122:$M$122,1,MATCH(Process!$J57,Parameter!$D$121:$M$121,0)),"") -> 0.5 | L57: =IFERROR(I57/K57,0) -> 0 | M57: 15 | N57: =L57+M57 -> 15 | O57: DG operator | P57: =N57*F57/3600/Parameter!$P$6/Parameter!$P$7 -> 0.02759348 | X57: =P57*Parameter!W$8 -> 0.026765676 | Y57: =X57*Parameter!X$8 -> 0.024680148 | Z57: =Y57*Parameter!Y$8 -> 0.023439834 | AA57: =Z57*Parameter!Z$8 -> 0.022929708 | AB57: =VLOOKUP(O57,Parameter!$O$11:$P$22,2,0)*Process!P57 -> 2782.9371 | AC57: =VLOOKUP($O57,Parameter!$O$11:$P$22,2,0)*VLOOKUP($O57,Parameter!$O$11:$T$22,6,0)*X57 -> 2888.4104 | AD57: =VLOOKUP($O57,Parameter!$O$11:$P$22,2,0)*VLOOKUP($O57,Parameter!$O$11:$T$22,6,0)^2*Y57 -> 2849.7858 | AE57: =VLOOKUP($O57,Parameter!$O$11:$P$22,2,0)*VLOOKUP($O57,Parameter!$O$11:$T$22,6,0)^3*Z57 -> 2896.0281 | AF57: =VLOOKUP($O57,Parameter!$O$11:$P$22,2,0)*VLOOKUP($O57,Parameter!$O$11:$T$22,6,0)^4*AA57 -> 3031.3113
A58: =ROW()-1 -> 57 | B58: Inbound processing | C58: C5 Put away | D58: Non-critical DG parts put away | E58: Scan Bin Location | F58: =F56 -> 45.03256 | G58: Line | H58: HDL | I58: =IFERROR(VLOOKUP(H58,Parameter!$F$44:$H$92,3,0),"") -> 0 | J58: CB - DG | K58: =IFERROR(INDEX(Parameter!$D$122:$M$122,1,MATCH(Process!$J58,Parameter!$D$121:$M$121,0)),"") -> 0.5 | L58: =IFERROR(I58/K58,0) -> 0 | M58: 5 | N58: =L58+M58 -> 5 | O58: DG operator | P58: =N58*F58/3600/Parameter!$P$6/Parameter!$P$7 -> 0.0091978267 | X58: =P58*Parameter!W$8 -> 0.0089218919 | Y58: =X58*Parameter!X$8 -> 0.008226716 | Z58: =Y58*Parameter!Y$8 -> 0.0078132779 | AA58: =Z58*Parameter!Z$8 -> 0.0076432359 | AB58: =VLOOKUP(O58,Parameter!$O$11:$P$22,2,0)*Process!P58 -> 927.64569 | AC58: =VLOOKUP($O58,Parameter!$O$11:$P$22,2,0)*VLOOKUP($O58,Parameter!$O$11:$T$22,6,0)*X58 -> 962.80347 | AD58: =VLOOKUP($O58,Parameter!$O$11:$P$22,2,0)*VLOOKUP($O58,Parameter!$O$11:$T$22,6,0)^2*Y58 -> 949.92861 | AE58: =VLOOKUP($O58,Parameter!$O$11:$P$22,2,0)*VLOOKUP($O58,Parameter!$O$11:$T$22,6,0)^3*Z58 -> 965.34269 | AF58: =VLOOKUP($O58,Parameter!$O$11:$P$22,2,0)*VLOOKUP($O58,Parameter!$O$11:$T$22,6,0)^4*AA58 -> 1010.4371
A59: =ROW()-1 -> 58 | B59: Inbound processing | C59: C5 Put away | D59: Non-critical DG parts put away | E59: Back to Dock | F59: =F53 -> 18.763567 | G59: Trip | H59: IBSC | I59: =IFERROR(VLOOKUP(H59,Parameter!$F$44:$H$92,3,0),"") -> 320 | J59: CB - DG | K59: =IFERROR(INDEX(Parameter!$D$122:$M$122,1,MATCH(Process!$J59,Parameter!$D$121:$M$121,0)),"") -> 0.5 | L59: =IFERROR(I59/K59,0) -> 640 | N59: =L59+M59 -> 640 | O59: DG operator | P59: =N59*F59/3600/Parameter!$P$6/Parameter!$P$7 -> 0.49055076 | X59: =P59*Parameter!W$8 -> 0.47583424 | Y59: =X59*Parameter!X$8 -> 0.43875818 | Z59: =Y59*Parameter!Y$8 -> 0.41670816 | AA59: =Z59*Parameter!Z$8 -> 0.40763925 | AB59: =VLOOKUP(O59,Parameter!$O$11:$P$22,2,0)*Process!P59 -> 49474.437 | AC59: =VLOOKUP($O59,Parameter!$O$11:$P$22,2,0)*VLOOKUP($O59,Parameter!$O$11:$T$22,6,0)*X59 -> 51349.518 | AD59: =VLOOKUP($O59,Parameter!$O$11:$P$22,2,0)*VLOOKUP($O59,Parameter!$O$11:$T$22,6,0)^2*Y59 -> 50662.859 | AE59: =VLOOKUP($O59,Parameter!$O$11:$P$22,2,0)*VLOOKUP($O59,Parameter!$O$11:$T$22,6,0)^3*Z59 -> 51484.944 | AF59: =VLOOKUP($O59,Parameter!$O$11:$P$22,2,0)*VLOOKUP($O59,Parameter!$O$11:$T$22,6,0)^4*AA59 -> 53889.979
A60: =ROW()-1 -> 59 | B60: Inbound DG processing | C60: (don't remove the line) | J60: Manual
A61: =ROW()-1 -> 60 | B61: Warranty & Return DG | C61: Return check | D61: Return handling | E61: Check return | F61: =Volume!B10/Parameter!P4*Parameter!R42*Volume!J26 -> 5.3008874 | G61: Piece | H61: HDL | I61: =IFERROR(VLOOKUP(H61,Parameter!$F$44:$H$92,3,0),"") -> 0 | J61: Manual | K61: =IFERROR(INDEX(Parameter!$D$122:$M$122,1,MATCH(Process!$J61,Parameter!$D$121:$M$121,0)),"") -> 1.2 | L61: =IFERROR(I61/K61,0) -> 0 | M61: 180 | N61: =L61+M61 -> 180 | O61: DG operator | P61: =N61*F61/3600/Parameter!$P$6/Parameter!$P$7 -> 0.038977113 | X61: =P61*Parameter!W$8 -> 0.0378078 | Y61: =X61*Parameter!X$8 -> 0.034861892 | Z61: =Y61*Parameter!Y$8 -> 0.033109888 | AA61: =Z61*Parameter!Z$8 -> 0.032389311 | AB61: =VLOOKUP(O61,Parameter!$O$11:$P$22,2,0)*Process!P61 -> 3931.032 | AC61: =VLOOKUP($O61,Parameter!$O$11:$P$22,2,0)*VLOOKUP($O61,Parameter!$O$11:$T$22,6,0)*X61 -> 4080.0181 | AD61: =VLOOKUP($O61,Parameter!$O$11:$P$22,2,0)*VLOOKUP($O61,Parameter!$O$11:$T$22,6,0)^2*Y61 -> 4025.459 | AE61: =VLOOKUP($O61,Parameter!$O$11:$P$22,2,0)*VLOOKUP($O61,Parameter!$O$11:$T$22,6,0)^3*Z61 -> 4090.7784 | AF61: =VLOOKUP($O61,Parameter!$O$11:$P$22,2,0)*VLOOKUP($O61,Parameter!$O$11:$T$22,6,0)^4*AA61 -> 4281.8725
A62: =ROW()-1 -> 61 | B62: Warranty & Return DG | C62: Return check | D62: Return handling | E62: Sort by Class and put away to return shelving | F62: =F61 -> 5.3008874 | G62: =G61 -> Piece | H62: HDL | I62: =IFERROR(VLOOKUP(H62,Parameter!$F$44:$H$92,3,0),"") -> 0 | J62: Manual | K62: =IFERROR(INDEX(Parameter!$D$122:$M$122,1,MATCH(Process!$J62,Parameter!$D$121:$M$121,0)),"") -> 1.2 | L62: =IFERROR(I62/K62,0) -> 0 | M62: =3600/30 -> 120 | N62: =L62+M62 -> 120 | O62: DG operator | P62: =N62*F62/3600/Parameter!$P$6/Parameter!$P$7 -> 0.025984742 | X62: =P62*Parameter!W$8 -> 0.0252052 | Y62: =X62*Parameter!X$8 -> 0.023241261 | Z62: =Y62*Parameter!Y$8 -> 0.022073259 | AA62: =Z62*Parameter!Z$8 -> 0.021592874 | AB62: =VLOOKUP(O62,Parameter!$O$11:$P$22,2,0)*Process!P62 -> 2620.688 | AC62: =VLOOKUP($O62,Parameter!$O$11:$P$22,2,0)*VLOOKUP($O62,Parameter!$O$11:$T$22,6,0)*X62 -> 2720.0121 | AD62: =VLOOKUP($O62,Parameter!$O$11:$P$22,2,0)*VLOOKUP($O62,Parameter!$O$11:$T$22,6,0)^2*Y62 -> 2683.6394 | AE62: =VLOOKUP($O62,Parameter!$O$11:$P$22,2,0)*VLOOKUP($O62,Parameter!$O$11:$T$22,6,0)^3*Z62 -> 2727.1856 | AF62: =VLOOKUP($O62,Parameter!$O$11:$P$22,2,0)*VLOOKUP($O62,Parameter!$O$11:$T$22,6,0)^4*AA62 -> 2854.5817
A63: =ROW()-1 -> 62 | B63: Warranty & Return DG | C63: Return check | D63: Return handling | E63: =E26 -> System registration | F63: =Volume!B10/Parameter!P4*Volume!J26 -> 2.6504437 | G63: Line | H63: HDL | I63: =IFERROR(VLOOKUP(H63,Parameter!$F$44:$H$92,3,0),"") -> 0 | J63: Manual | K63: =IFERROR(INDEX(Parameter!$D$122:$M$122,1,MATCH(Process!$J63,Parameter!$D$121:$M$121,0)),"") -> 1.2 | L63: =IFERROR(I63/K63,0) -> 0 | M63: 300 | N63: =L63+M63 -> 300 | O63: DG operator | P63: =N63*F63/3600/Parameter!$P$6/Parameter!$P$7 -> 0.032480928 | X63: =P63*Parameter!W$8 -> 0.0315065 | Y63: =X63*Parameter!X$8 -> 0.029051576 | Z63: =Y63*Parameter!Y$8 -> 0.027591574 | AA63: =Z63*Parameter!Z$8 -> 0.026991092 | AB63: =VLOOKUP(O63,Parameter!$O$11:$P$22,2,0)*Process!P63 -> 3275.86 | AC63: =VLOOKUP($O63,Parameter!$O$11:$P$22,2,0)*VLOOKUP($O63,Parameter!$O$11:$T$22,6,0)*X63 -> 3400.0151 | AD63: =VLOOKUP($O63,Parameter!$O$11:$P$22,2,0)*VLOOKUP($O63,Parameter!$O$11:$T$22,6,0)^2*Y63 -> 3354.5492 | AE63: =VLOOKUP($O63,Parameter!$O$11:$P$22,2,0)*VLOOKUP($O63,Parameter!$O$11:$T$22,6,0)^3*Z63 -> 3408.982 | AF63: =VLOOKUP($O63,Parameter!$O$11:$P$22,2,0)*VLOOKUP($O63,Parameter!$O$11:$T$22,6,0)^4*AA63 -> 3568.2271
A64: =ROW()-1 -> 63 | B64: Inbound processing | C64: Other Put away | D64: Others | E64: Check TO Label | F64: =Parameter!R64/Parameter!R65 -> 0 | G64: Trip | H64: HDL | I64: =IFERROR(VLOOKUP(H64,Parameter!$F$44:$H$92,3,0),"") -> 0 | J64: Trolley | K64: =IFERROR(INDEX(Parameter!$D$122:$M$122,1,MATCH(Process!$J64,Parameter!$D$121:$M$121,0)),"") -> 0.42 | L64: =IFERROR(I64/K64,0) -> 0 | M64: 5 | N64: =L64+M64 -> 5 | O64: Operator | P64: =N64*F64/3600/Parameter!$P$6/Parameter!$P$7 -> 0 | X64: =P64*Parameter!W$8 -> 0 | Y64: =X64*Parameter!X$8 -> 0 | Z64: =Y64*Parameter!Y$8 -> 0 | AA64: =Z64*Parameter!Z$8 -> 0 | AB64: =VLOOKUP(O64,Parameter!$O$11:$P$22,2,0)*Process!P64 -> 0 | AC64: =VLOOKUP($O64,Parameter!$O$11:$P$22,2,0)*VLOOKUP($O64,Parameter!$O$11:$T$22,6,0)*X64 -> 0 | AD64: =VLOOKUP($O64,Parameter!$O$11:$P$22,2,0)*VLOOKUP($O64,Parameter!$O$11:$T$22,6,0)^2*Y64 -> 0 | AE64: =VLOOKUP($O64,Parameter!$O$11:$P$22,2,0)*VLOOKUP($O64,Parameter!$O$11:$T$22,6,0)^3*Z64 -> 0 | AF64: =VLOOKUP($O64,Parameter!$O$11:$P$22,2,0)*VLOOKUP($O64,Parameter!$O$11:$T$22,6,0)^4*AA64 -> 0
A65: =ROW()-1 -> 64 | B65: Inbound processing | C65: Other Put away | D65: Others | E65: Move Trolley to Other Storage Area | F65: =F64 -> 0 | G65: Trip | H65: IBSL | I65: =IFERROR(VLOOKUP(H65,Parameter!$F$44:$H$92,3,0),"") -> 0 | J65: Trolley | K65: =IFERROR(INDEX(Parameter!$D$122:$M$122,1,MATCH(Process!$J65,Parameter!$D$121:$M$121,0)),"") -> 0.42 | L65: =IFERROR(I65/K65,0) -> 0 | N65: =L65+M65 -> 0 | O65: Operator | P65: =N65*F65/3600/Parameter!$P$6/Parameter!$P$7 -> 0 | X65: =P65*Parameter!W$8 -> 0 | Y65: =X65*Parameter!X$8 -> 0 | Z65: =Y65*Parameter!Y$8 -> 0 | AA65: =Z65*Parameter!Z$8 -> 0 | AB65: =VLOOKUP(O65,Parameter!$O$11:$P$22,2,0)*Process!P65 -> 0 | AC65: =VLOOKUP($O65,Parameter!$O$11:$P$22,2,0)*VLOOKUP($O65,Parameter!$O$11:$T$22,6,0)*X65 -> 0 | AD65: =VLOOKUP($O65,Parameter!$O$11:$P$22,2,0)*VLOOKUP($O65,Parameter!$O$11:$T$22,6,0)^2*Y65 -> 0 | AE65: =VLOOKUP($O65,Parameter!$O$11:$P$22,2,0)*VLOOKUP($O65,Parameter!$O$11:$T$22,6,0)^3*Z65 -> 0 | AF65: =VLOOKUP($O65,Parameter!$O$11:$P$22,2,0)*VLOOKUP($O65,Parameter!$O$11:$T$22,6,0)^4*AA65 -> 0
A66: =ROW()-1 -> 65 | B66: Inbound processing | C66: Other Put away | D66: Others | E66: Aisle Distance | F66: =F65 -> 0 | G66: Trip | H66: LA | I66: =IFERROR(VLOOKUP(H66,Parameter!$F$44:$H$92,3,0),"") -> 0 | J66: Trolley | K66: =IFERROR(INDEX(Parameter!$D$122:$M$122,1,MATCH(Process!$J66,Parameter!$D$121:$M$121,0)),"") -> 0.42 | L66: =IFERROR(I66/K66,0) -> 0 | N66: =L66+M66 -> 0 | O66: Operator | P66: =N66*F66/3600/Parameter!$P$6/Parameter!$P$7 -> 0 | X66: =P66*Parameter!W$8 -> 0 | Y66: =X66*Parameter!X$8 -> 0 | Z66: =Y66*Parameter!Y$8 -> 0 | AA66: =Z66*Parameter!Z$8 -> 0 | AB66: =VLOOKUP(O66,Parameter!$O$11:$P$22,2,0)*Process!P66 -> 0 | AC66: =VLOOKUP($O66,Parameter!$O$11:$P$22,2,0)*VLOOKUP($O66,Parameter!$O$11:$T$22,6,0)*X66 -> 0 | AD66: =VLOOKUP($O66,Parameter!$O$11:$P$22,2,0)*VLOOKUP($O66,Parameter!$O$11:$T$22,6,0)^2*Y66 -> 0 | AE66: =VLOOKUP($O66,Parameter!$O$11:$P$22,2,0)*VLOOKUP($O66,Parameter!$O$11:$T$22,6,0)^3*Z66 -> 0 | AF66: =VLOOKUP($O66,Parameter!$O$11:$P$22,2,0)*VLOOKUP($O66,Parameter!$O$11:$T$22,6,0)^4*AA66 -> 0
A67: =ROW()-1 -> 66 | B67: Inbound processing | C67: Other Put away | D67: Others | E67: Find Bin Location | F67: =Parameter!R64 -> 0 | G67: Line | H67: LL | I67: =IFERROR(VLOOKUP(H67,Parameter!$F$44:$H$92,3,0),"") -> 0 | J67: Trolley | K67: =IFERROR(INDEX(Parameter!$D$122:$M$122,1,MATCH(Process!$J67,Parameter!$D$121:$M$121,0)),"") -> 0.42 | L67: =IFERROR(I67/K67,0) -> 0 | N67: =L67+M67 -> 0 | O67: Operator | P67: =N67*F67/3600/Parameter!$P$6/Parameter!$P$7 -> 0 | X67: =P67*Parameter!W$8 -> 0 | Y67: =X67*Parameter!X$8 -> 0 | Z67: =Y67*Parameter!Y$8 -> 0 | AA67: =Z67*Parameter!Z$8 -> 0 | AB67: =VLOOKUP(O67,Parameter!$O$11:$P$22,2,0)*Process!P67 -> 0 | AC67: =VLOOKUP($O67,Parameter!$O$11:$P$22,2,0)*VLOOKUP($O67,Parameter!$O$11:$T$22,6,0)*X67 -> 0 | AD67: =VLOOKUP($O67,Parameter!$O$11:$P$22,2,0)*VLOOKUP($O67,Parameter!$O$11:$T$22,6,0)^2*Y67 -> 0 | AE67: =VLOOKUP($O67,Parameter!$O$11:$P$22,2,0)*VLOOKUP($O67,Parameter!$O$11:$T$22,6,0)^3*Z67 -> 0 | AF67: =VLOOKUP($O67,Parameter!$O$11:$P$22,2,0)*VLOOKUP($O67,Parameter!$O$11:$T$22,6,0)^4*AA67 -> 0
A68: =ROW()-1 -> 67 | B68: Inbound processing | C68: Other Put away | D68: Others | E68: Put away parts | F68: =F67 -> 0 | G68: Line | H68: HDL | I68: =IFERROR(VLOOKUP(H68,Parameter!$F$44:$H$92,3,0),"") -> 0 | J68: Trolley | K68: =IFERROR(INDEX(Parameter!$D$122:$M$122,1,MATCH(Process!$J68,Parameter!$D$121:$M$121,0)),"") -> 0.42 | L68: =IFERROR(I68/K68,0) -> 0 | M68: =3600/40 -> 90 | N68: =L68+M68 -> 90 | O68: Operator | P68: =N68*F68/3600/Parameter!$P$6/Parameter!$P$7 -> 0 | X68: =P68*Parameter!W$8 -> 0 | Y68: =X68*Parameter!X$8 -> 0 | Z68: =Y68*Parameter!Y$8 -> 0 | AA68: =Z68*Parameter!Z$8 -> 0 | AB68: =VLOOKUP(O68,Parameter!$O$11:$P$22,2,0)*Process!P68 -> 0 | AC68: =VLOOKUP($O68,Parameter!$O$11:$P$22,2,0)*VLOOKUP($O68,Parameter!$O$11:$T$22,6,0)*X68 -> 0 | AD68: =VLOOKUP($O68,Parameter!$O$11:$P$22,2,0)*VLOOKUP($O68,Parameter!$O$11:$T$22,6,0)^2*Y68 -> 0 | AE68: =VLOOKUP($O68,Parameter!$O$11:$P$22,2,0)*VLOOKUP($O68,Parameter!$O$11:$T$22,6,0)^3*Z68 -> 0 | AF68: =VLOOKUP($O68,Parameter!$O$11:$P$22,2,0)*VLOOKUP($O68,Parameter!$O$11:$T$22,6,0)^4*AA68 -> 0
A69: =ROW()-1 -> 68 | B69: Inbound processing | C69: Other Put away | D69: Others | E69: Back to Dock | F69: =F64 -> 0 | G69: Trip | H69: IBSL | I69: =IFERROR(VLOOKUP(H69,Parameter!$F$44:$H$92,3,0),"") -> 0 | J69: Trolley | K69: =IFERROR(INDEX(Parameter!$D$122:$M$122,1,MATCH(Process!$J69,Parameter!$D$121:$M$121,0)),"") -> 0.42 | L69: =IFERROR(I69/K69,0) -> 0 | N69: =L69+M69 -> 0 | O69: Operator | P69: =N69*F69/3600/Parameter!$P$6/Parameter!$P$7 -> 0 | X69: =P69*Parameter!W$8 -> 0 | Y69: =X69*Parameter!X$8 -> 0 | Z69: =Y69*Parameter!Y$8 -> 0 | AA69: =Z69*Parameter!Z$8 -> 0 | AB69: =VLOOKUP(O69,Parameter!$O$11:$P$22,2,0)*Process!P69 -> 0 | AC69: =VLOOKUP($O69,Parameter!$O$11:$P$22,2,0)*VLOOKUP($O69,Parameter!$O$11:$T$22,6,0)*X69 -> 0 | AD69: =VLOOKUP($O69,Parameter!$O$11:$P$22,2,0)*VLOOKUP($O69,Parameter!$O$11:$T$22,6,0)^2*Y69 -> 0 | AE69: =VLOOKUP($O69,Parameter!$O$11:$P$22,2,0)*VLOOKUP($O69,Parameter!$O$11:$T$22,6,0)^3*Z69 -> 0 | AF69: =VLOOKUP($O69,Parameter!$O$11:$P$22,2,0)*VLOOKUP($O69,Parameter!$O$11:$T$22,6,0)^4*AA69 -> 0
A70: =ROW()-1 -> 69 | B70: Customs inspection | C70: Customs inspection | D70: System handling | E70: System handling | F70: =Volume!B86/Parameter!P4 -> 6.1433447 | G70: Line | H70: HDL | I70: =IFERROR(VLOOKUP(H70,Parameter!$F$44:$H$92,3,0),"") -> 0 | J70: Manual | K70: =IFERROR(INDEX(Parameter!$D$122:$M$122,1,MATCH(Process!$J70,Parameter!$D$121:$M$121,0)),"") -> 1.2 | L70: =IFERROR(I70/K70,0) -> 0 | M70: 300 | N70: =L70+M70 -> 300 | O70: IB Planner | P70: =N70*F70/3600/Parameter!$P$6/Parameter!$P$7 -> 0.075286087 | X70: =P70*Parameter!W$8 -> 0.073027505 | Y70: =X70*Parameter!X$8 -> 0.067337347 | Z70: =Y70*Parameter!Y$8 -> 0.063953273 | AA70: =Z70*Parameter!Z$8 -> 0.062561444 | AB70: =VLOOKUP(O70,Parameter!$O$11:$P$22,2,0)*Process!P70 -> 9491.2114 | AC70: =VLOOKUP($O70,Parameter!$O$11:$P$22,2,0)*VLOOKUP($O70,Parameter!$O$11:$T$22,6,0)*X70 -> 9850.9283 | AD70: =VLOOKUP($O70,Parameter!$O$11:$P$22,2,0)*VLOOKUP($O70,Parameter!$O$11:$T$22,6,0)^2*Y70 -> 9719.1992 | AE70: =VLOOKUP($O70,Parameter!$O$11:$P$22,2,0)*VLOOKUP($O70,Parameter!$O$11:$T$22,6,0)^3*Z70 -> 9876.9084 | AF70: =VLOOKUP($O70,Parameter!$O$11:$P$22,2,0)*VLOOKUP($O70,Parameter!$O$11:$T$22,6,0)^4*AA70 -> 10338.292
A71: =ROW()-1 -> 70 | B71: Customs inspection | C71: Customs inspection | D71: Move to staging area | E71: Move to staging area | F71: =F70/Parameter!R37 -> 6.1433447 | G71: Trip | H71: CS | I71: =IFERROR(VLOOKUP(H71,Parameter!$F$44:$H$92,3,0),"") -> 90 | J71: CB | K71: =IFERROR(INDEX(Parameter!$D$122:$M$122,1,MATCH(Process!$J71,Parameter!$D$121:$M$121,0)),"") -> 2.7777778 | L71: =IFERROR(I71/K71,0) -> 32.4 | O71: MHE Driver | P71: =N71*F71/3600/Parameter!$P$6/Parameter!$P$7 -> 0 | X71: =P71*Parameter!W$8 -> 0 | Y71: =X71*Parameter!X$8 -> 0 | Z71: =Y71*Parameter!Y$8 -> 0 | AA71: =Z71*Parameter!Z$8 -> 0 | AB71: =VLOOKUP(O71,Parameter!$O$11:$P$22,2,0)*Process!P71 -> 0 | AC71: =VLOOKUP($O71,Parameter!$O$11:$P$22,2,0)*VLOOKUP($O71,Parameter!$O$11:$T$22,6,0)*X71 -> 0 | AD71: =VLOOKUP($O71,Parameter!$O$11:$P$22,2,0)*VLOOKUP($O71,Parameter!$O$11:$T$22,6,0)^2*Y71 -> 0 | AE71: =VLOOKUP($O71,Parameter!$O$11:$P$22,2,0)*VLOOKUP($O71,Parameter!$O$11:$T$22,6,0)^3*Z71 -> 0 | AF71: =VLOOKUP($O71,Parameter!$O$11:$P$22,2,0)*VLOOKUP($O71,Parameter!$O$11:$T$22,6,0)^4*AA71 -> 0
A72: =ROW()-1 -> 71 | B72: Inbound processing | C72: Transit between chamber | D72: Transit between chamber | E72: Move to and back C1/2/5 | G72: Trip | J72: CB | K72: =IFERROR(INDEX(Parameter!$D$122:$M$122,1,MATCH(Process!$J72,Parameter!$D$121:$M$121,0)),"") -> 2.7777778 | L72: =IFERROR(I72/K72,0) -> 0 | O72: MHE Driver | P72: =N72*F72/3600/Parameter!$P$6/Parameter!$P$7 -> 0 | X72: =P72*Parameter!W$8 -> 0 | Y72: =X72*Parameter!X$8 -> 0 | Z72: =Y72*Parameter!Y$8 -> 0 | AA72: =Z72*Parameter!Z$8 -> 0 | AB72: =VLOOKUP(O72,Parameter!$O$11:$P$22,2,0)*Process!P72 -> 0 | AC72: =VLOOKUP($O72,Parameter!$O$11:$P$22,2,0)*VLOOKUP($O72,Parameter!$O$11:$T$22,6,0)*X72 -> 0 | AD72: =VLOOKUP($O72,Parameter!$O$11:$P$22,2,0)*VLOOKUP($O72,Parameter!$O$11:$T$22,6,0)^2*Y72 -> 0 | AE72: =VLOOKUP($O72,Parameter!$O$11:$P$22,2,0)*VLOOKUP($O72,Parameter!$O$11:$T$22,6,0)^3*Z72 -> 0 | AF72: =VLOOKUP($O72,Parameter!$O$11:$P$22,2,0)*VLOOKUP($O72,Parameter!$O$11:$T$22,6,0)^4*AA72 -> 0
A73: =ROW()-1 -> 72 | B73: Outbound processing | C73: Make OB Plan | D73: Make OB plan and paper work | E73: Cut off OB Plan | F73: 1 | G73: Daily | H73: HDL | I73: =IFERROR(VLOOKUP(H73,Parameter!$F$44:$H$92,3,0),"") -> 0 | J73: Manual | K73: =IFERROR(INDEX(Parameter!$D$122:$M$122,1,MATCH(Process!$J73,Parameter!$D$121:$M$121,0)),"") -> 1.2 | L73: =IFERROR(I73/K73,0) -> 0 | M73: =3600*2 -> 7200 | N73: =L73+M73 -> 7200 | O73: Documentation | P73: =N73*F73/3600/Parameter!$P$6/Parameter!$P$7 -> 0.29411765 | X73: =P73*Parameter!W$8 -> 0.28529412 | Y73: =X73*Parameter!X$8 -> 0.26306457 | Z73: =Y73*Parameter!Y$8 -> 0.24984412 | AA73: =Z73*Parameter!Z$8 -> 0.24440671 | AB73: =VLOOKUP(O73,Parameter!$O$11:$P$22,2,0)*Process!P73 -> 37179.878 | AC73: =VLOOKUP($O73,Parameter!$O$11:$P$22,2,0)*VLOOKUP($O73,Parameter!$O$11:$T$22,6,0)*X73 -> 38588.995 | AD73: =VLOOKUP($O73,Parameter!$O$11:$P$22,2,0)*VLOOKUP($O73,Parameter!$O$11:$T$22,6,0)^2*Y73 -> 38072.973 | AE73: =VLOOKUP($O73,Parameter!$O$11:$P$22,2,0)*VLOOKUP($O73,Parameter!$O$11:$T$22,6,0)^3*Z73 -> 38690.767 | AF73: =VLOOKUP($O73,Parameter!$O$11:$P$22,2,0)*VLOOKUP($O73,Parameter!$O$11:$T$22,6,0)^4*AA73 -> 40498.143
A74: =ROW()-1 -> 73 | B74: Outbound processing | C74: M Picking | D74: Mezzaning_Move to storage area and back | E74: Check TO List | F74: =F75 -> 30.77586 | G74: Trip | H74: HDL | I74: =IFERROR(VLOOKUP(H74,Parameter!$F$44:$H$92,3,0),"") -> 0 | J74: Trolley | K74: =IFERROR(INDEX(Parameter!$D$122:$M$122,1,MATCH(Process!$J74,Parameter!$D$121:$M$121,0)),"") -> 0.42 | L74: =IFERROR(I74/K74,0) -> 0 | M74: 5 | N74: =L74+M74 -> 5 | O74: Operator | P74: =N74*F74/3600/Parameter!$P$6/Parameter!$P$7 -> 0.0062859191 | X74: =P74*Parameter!W$8 -> 0.0060973415 | Y74: =X74*Parameter!X$8 -> 0.0056222488 | Z74: =Y74*Parameter!Y$8 -> 0.0053396997 | AA74: =Z74*Parameter!Z$8 -> 0.0052234907 | AB74: =VLOOKUP(O74,Parameter!$O$11:$P$22,2,0)*Process!P74 -> 528.30467 | AC74: =VLOOKUP($O74,Parameter!$O$11:$P$22,2,0)*VLOOKUP($O74,Parameter!$O$11:$T$22,6,0)*X74 -> 548.32741 | AD74: =VLOOKUP($O74,Parameter!$O$11:$P$22,2,0)*VLOOKUP($O74,Parameter!$O$11:$T$22,6,0)^2*Y74 -> 540.99504 | AE74: =VLOOKUP($O74,Parameter!$O$11:$P$22,2,0)*VLOOKUP($O74,Parameter!$O$11:$T$22,6,0)^3*Z74 -> 549.77353 | AF74: =VLOOKUP($O74,Parameter!$O$11:$P$22,2,0)*VLOOKUP($O74,Parameter!$O$11:$T$22,6,0)^4*AA74 -> 575.45531
A75: =ROW()-1 -> 74 | B75: Outbound processing | C75: M Picking | D75: Mezzaning_Move to storage area and back | E75: Move to M Staging | F75: =Parameter!R67/Parameter!R68 -> 30.77586 | G75: Trip | H75: OBMP | I75: =IFERROR(VLOOKUP(H75,Parameter!$F$44:$H$92,3,0),"") -> 55 | J75: Trolley | K75: =IFERROR(INDEX(Parameter!$D$122:$M$122,1,MATCH(Process!$J75,Parameter!$D$121:$M$121,0)),"") -> 0.42 | L75: =IFERROR(I75/K75,0) -> 130.95238 | N75: =L75+M75 -> 130.95238 | O75: Operator | P75: =N75*F75/3600/Parameter!$P$6/Parameter!$P$7 -> 0.16463121 | X75: =P75*Parameter!W$8 -> 0.15969228 | Y75: =X75*Parameter!X$8 -> 0.14724937 | Z75: =Y75*Parameter!Y$8 -> 0.13984928 | AA75: =Z75*Parameter!Z$8 -> 0.13680571 | AB75: =VLOOKUP(O75,Parameter!$O$11:$P$22,2,0)*Process!P75 -> 13836.551 | AC75: =VLOOKUP($O75,Parameter!$O$11:$P$22,2,0)*VLOOKUP($O75,Parameter!$O$11:$T$22,6,0)*X75 -> 14360.956 | AD75: =VLOOKUP($O75,Parameter!$O$11:$P$22,2,0)*VLOOKUP($O75,Parameter!$O$11:$T$22,6,0)^2*Y75 -> 14168.918 | AE75: =VLOOKUP($O75,Parameter!$O$11:$P$22,2,0)*VLOOKUP($O75,Parameter!$O$11:$T$22,6,0)^3*Z75 -> 14398.831 | AF75: =VLOOKUP($O75,Parameter!$O$11:$P$22,2,0)*VLOOKUP($O75,Parameter!$O$11:$T$22,6,0)^4*AA75 -> 15071.448
A76: =ROW()-1 -> 75 | B76: Outbound processing | C76: M Picking | D76: Mezzaning_Move to storage area and back | E76: Move Full Trolley to Packing Area | F76: =F75 -> 30.77586 | G76: Trip | H76: OBMP | I76: =IFERROR(VLOOKUP(H76,Parameter!$F$44:$H$92,3,0),"") -> 55 | J76: Trolley | K76: =IFERROR(INDEX(Parameter!$D$122:$M$122,1,MATCH(Process!$J76,Parameter!$D$121:$M$121,0)),"") -> 0.42 | L76: =IFERROR(I76/K76,0) -> 130.95238 | N76: =L76+M76 -> 130.95238 | O76: Operator | P76: =N76*F76/3600/Parameter!$P$6/Parameter!$P$7 -> 0.16463121 | X76: =P76*Parameter!W$8 -> 0.15969228 | Y76: =X76*Parameter!X$8 -> 0.14724937 | Z76: =Y76*Parameter!Y$8 -> 0.13984928 | AA76: =Z76*Parameter!Z$8 -> 0.13680571 | AB76: =VLOOKUP(O76,Parameter!$O$11:$P$22,2,0)*Process!P76 -> 13836.551 | AC76: =VLOOKUP($O76,Parameter!$O$11:$P$22,2,0)*VLOOKUP($O76,Parameter!$O$11:$T$22,6,0)*X76 -> 14360.956 | AD76: =VLOOKUP($O76,Parameter!$O$11:$P$22,2,0)*VLOOKUP($O76,Parameter!$O$11:$T$22,6,0)^2*Y76 -> 14168.918 | AE76: =VLOOKUP($O76,Parameter!$O$11:$P$22,2,0)*VLOOKUP($O76,Parameter!$O$11:$T$22,6,0)^3*Z76 -> 14398.831 | AF76: =VLOOKUP($O76,Parameter!$O$11:$P$22,2,0)*VLOOKUP($O76,Parameter!$O$11:$T$22,6,0)^4*AA76 -> 15071.448
A77: =ROW()-1 -> 76 | B77: Outbound processing | C77: M Picking | D77: Mezzanine_Picking | E77: Aisle Distance | F77: =F74 -> 30.77586 | G77: Trip | H77: MA | I77: =IFERROR(VLOOKUP(H77,Parameter!$F$44:$H$92,3,0),"") -> 20 | J77: Trolley | K77: =IFERROR(INDEX(Parameter!$D$122:$M$122,1,MATCH(Process!$J77,Parameter!$D$121:$M$121,0)),"") -> 0.42 | L77: =IFERROR(I77/K77,0) -> 47.619048 | N77: =L77+M77 -> 47.619048 | O77: Operator | P77: =N77*F77/3600/Parameter!$P$6/Parameter!$P$7 -> 0.059865896 | X77: =P77*Parameter!W$8 -> 0.058069919 | Y77: =X77*Parameter!X$8 -> 0.053545227 | Z77: =Y77*Parameter!Y$8 -> 0.050854283 | AA77: =Z77*Parameter!Z$8 -> 0.04974753 | AB77: =VLOOKUP(O77,Parameter!$O$11:$P$22,2,0)*Process!P77 -> 5031.473 | AC77: =VLOOKUP($O77,Parameter!$O$11:$P$22,2,0)*VLOOKUP($O77,Parameter!$O$11:$T$22,6,0)*X77 -> 5222.1658 | AD77: =VLOOKUP($O77,Parameter!$O$11:$P$22,2,0)*VLOOKUP($O77,Parameter!$O$11:$T$22,6,0)^2*Y77 -> 5152.3337 | AE77: =VLOOKUP($O77,Parameter!$O$11:$P$22,2,0)*VLOOKUP($O77,Parameter!$O$11:$T$22,6,0)^3*Z77 -> 5235.9384 | AF77: =VLOOKUP($O77,Parameter!$O$11:$P$22,2,0)*VLOOKUP($O77,Parameter!$O$11:$T$22,6,0)^4*AA77 -> 5480.5267
A78: =ROW()-1 -> 77 | B78: Outbound processing | C78: M Picking | D78: Mezzanine_Picking | E78: Find Bin Location | F78: =Parameter!R67 -> 738.62063 | G78: Line | H78: ML | I78: =IFERROR(VLOOKUP(H78,Parameter!$F$44:$H$92,3,0),"") -> 10 | J78: Trolley | K78: =IFERROR(INDEX(Parameter!$D$122:$M$122,1,MATCH(Process!$J78,Parameter!$D$121:$M$121,0)),"") -> 0.42 | L78: =IFERROR(I78/K78,0) -> 23.809524 | N78: =L78+M78 -> 23.809524 | O78: Operator | P78: =N78*F78/3600/Parameter!$P$6/Parameter!$P$7 -> 0.71839075 | X78: =P78*Parameter!W$8 -> 0.69683903 | Y78: =X78*Parameter!X$8 -> 0.64254272 | Z78: =Y78*Parameter!Y$8 -> 0.61025139 | AA78: =Z78*Parameter!Z$8 -> 0.59697036 | AB78: =VLOOKUP(O78,Parameter!$O$11:$P$22,2,0)*Process!P78 -> 60377.676 | AC78: =VLOOKUP($O78,Parameter!$O$11:$P$22,2,0)*VLOOKUP($O78,Parameter!$O$11:$T$22,6,0)*X78 -> 62665.99 | AD78: =VLOOKUP($O78,Parameter!$O$11:$P$22,2,0)*VLOOKUP($O78,Parameter!$O$11:$T$22,6,0)^2*Y78 -> 61828.004 | AE78: =VLOOKUP($O78,Parameter!$O$11:$P$22,2,0)*VLOOKUP($O78,Parameter!$O$11:$T$22,6,0)^3*Z78 -> 62831.261 | AF78: =VLOOKUP($O78,Parameter!$O$11:$P$22,2,0)*VLOOKUP($O78,Parameter!$O$11:$T$22,6,0)^4*AA78 -> 65766.321
A79: =ROW()-1 -> 78 | B79: Outbound processing | C79: M Picking | D79: Mezzanine_Picking | E79: Picking Parts according to List | F79: =Parameter!R67*Parameter!R69 -> 4801.0341 | G79: Piece | H79: HDL | I79: =IFERROR(VLOOKUP(H79,Parameter!$F$44:$H$92,3,0),"") -> 0 | J79: Trolley | K79: =IFERROR(INDEX(Parameter!$D$122:$M$122,1,MATCH(Process!$J79,Parameter!$D$121:$M$121,0)),"") -> 0.42 | L79: =IFERROR(I79/K79,0) -> 0 | M79: 8 | N79: =L79+M79 -> 8 | O79: Operator | P79: =N79*F79/3600/Parameter!$P$6/Parameter!$P$7 -> 1.5689654 | X79: =P79*Parameter!W$8 -> 1.5218964 | Y79: =X79*Parameter!X$8 -> 1.4033133 | Z79: =Y79*Parameter!Y$8 -> 1.332789 | AA79: =Z79*Parameter!Z$8 -> 1.3037833 | AB79: =VLOOKUP(O79,Parameter!$O$11:$P$22,2,0)*Process!P79 -> 131864.84 | AC79: =VLOOKUP($O79,Parameter!$O$11:$P$22,2,0)*VLOOKUP($O79,Parameter!$O$11:$T$22,6,0)*X79 -> 136862.52 | AD79: =VLOOKUP($O79,Parameter!$O$11:$P$22,2,0)*VLOOKUP($O79,Parameter!$O$11:$T$22,6,0)^2*Y79 -> 135032.36 | AE79: =VLOOKUP($O79,Parameter!$O$11:$P$22,2,0)*VLOOKUP($O79,Parameter!$O$11:$T$22,6,0)^3*Z79 -> 137223.47 | AF79: =VLOOKUP($O79,Parameter!$O$11:$P$22,2,0)*VLOOKUP($O79,Parameter!$O$11:$T$22,6,0)^4*AA79 -> 143633.64
A80: =ROW()-1 -> 79 | B80: Outbound processing | C80: M Picking | D80: Mezzanine_Picking | E80: Check Performance and Shelf Life | F80: =F79*Parameter!R84 -> 432.09307 | G80: Piece | H80: HDL | I80: =IFERROR(VLOOKUP(H80,Parameter!$F$44:$H$92,3,0),"") -> 0 | J80: Trolley | K80: =IFERROR(INDEX(Parameter!$D$122:$M$122,1,MATCH(Process!$J80,Parameter!$D$121:$M$121,0)),"") -> 0.42 | L80: =IFERROR(I80/K80,0) -> 0 | M80: 5 | N80: =L80+M80 -> 5 | O80: Operator | P80: =N80*F80/3600/Parameter!$P$6/Parameter!$P$7 -> 0.088254304 | X80: =P80*Parameter!W$8 -> 0.085606674 | Y80: =X80*Parameter!X$8 -> 0.078936374 | Z80: =Y80*Parameter!Y$8 -> 0.074969383 | AA80: =Z80*Parameter!Z$8 -> 0.073337809 | AB80: =VLOOKUP(O80,Parameter!$O$11:$P$22,2,0)*Process!P80 -> 7417.3975 | AC80: =VLOOKUP($O80,Parameter!$O$11:$P$22,2,0)*VLOOKUP($O80,Parameter!$O$11:$T$22,6,0)*X80 -> 7698.5169 | AD80: =VLOOKUP($O80,Parameter!$O$11:$P$22,2,0)*VLOOKUP($O80,Parameter!$O$11:$T$22,6,0)^2*Y80 -> 7595.5703 | AE80: =VLOOKUP($O80,Parameter!$O$11:$P$22,2,0)*VLOOKUP($O80,Parameter!$O$11:$T$22,6,0)^3*Z80 -> 7718.8204 | AF80: =VLOOKUP($O80,Parameter!$O$11:$P$22,2,0)*VLOOKUP($O80,Parameter!$O$11:$T$22,6,0)^4*AA80 -> 8079.3925
A81: =ROW()-1 -> 80 | B81: Outbound processing | C81: M Picking | D81: Mezzanine_Picking | E81: Scan Bin Location | F81: =Parameter!R67 -> 738.62063 | G81: Line | H81: HDL | I81: =IFERROR(VLOOKUP(H81,Parameter!$F$44:$H$92,3,0),"") -> 0 | J81: Trolley | K81: =IFERROR(INDEX(Parameter!$D$122:$M$122,1,MATCH(Process!$J81,Parameter!$D$121:$M$121,0)),"") -> 0.42 | L81: =IFERROR(I81/K81,0) -> 0 | M81: 5 | N81: =L81+M81 -> 5 | O81: Operator | P81: =N81*F81/3600/Parameter!$P$6/Parameter!$P$7 -> 0.15086206 | X81: =P81*Parameter!W$8 -> 0.1463362 | Y81: =X81*Parameter!X$8 -> 0.13493397 | Z81: =Y81*Parameter!Y$8 -> 0.12815279 | AA81: =Z81*Parameter!Z$8 -> 0.12536378 | AB81: =VLOOKUP(O81,Parameter!$O$11:$P$22,2,0)*Process!P81 -> 12679.312 | AC81: =VLOOKUP($O81,Parameter!$O$11:$P$22,2,0)*VLOOKUP($O81,Parameter!$O$11:$T$22,6,0)*X81 -> 13159.858 | AD81: =VLOOKUP($O81,Parameter!$O$11:$P$22,2,0)*VLOOKUP($O81,Parameter!$O$11:$T$22,6,0)^2*Y81 -> 12983.881 | AE81: =VLOOKUP($O81,Parameter!$O$11:$P$22,2,0)*VLOOKUP($O81,Parameter!$O$11:$T$22,6,0)^3*Z81 -> 13194.565 | AF81: =VLOOKUP($O81,Parameter!$O$11:$P$22,2,0)*VLOOKUP($O81,Parameter!$O$11:$T$22,6,0)^4*AA81 -> 13810.927
A82: =ROW()-1 -> 81 | B82: Outbound processing | C82: M Picking | D82: Mezzanine_Picking | E82: Move to Elevator and Back to Elevator | F82: =F74*Parameter!R70 -> 0 | G82: Trip | H82: ME | I82: =IFERROR(VLOOKUP(H82,Parameter!$F$44:$H$92,3,0),"") -> 0 | J82: Trolley | K82: =IFERROR(INDEX(Parameter!$D$122:$M$122,1,MATCH(Process!$J82,Parameter!$D$121:$M$121,0)),"") -> 0.42 | L82: =IFERROR(I82/K82,0) -> 0 | N82: =L82+M82 -> 0 | O82: Operator | P82: =N82*F82/3600/Parameter!$P$6/Parameter!$P$7 -> 0 | X82: =P82*Parameter!W$8 -> 0 | Y82: =X82*Parameter!X$8 -> 0 | Z82: =Y82*Parameter!Y$8 -> 0 | AA82: =Z82*Parameter!Z$8 -> 0 | AB82: =VLOOKUP(O82,Parameter!$O$11:$P$22,2,0)*Process!P82 -> 0 | AC82: =VLOOKUP($O82,Parameter!$O$11:$P$22,2,0)*VLOOKUP($O82,Parameter!$O$11:$T$22,6,0)*X82 -> 0 | AD82: =VLOOKUP($O82,Parameter!$O$11:$P$22,2,0)*VLOOKUP($O82,Parameter!$O$11:$T$22,6,0)^2*Y82 -> 0 | AE82: =VLOOKUP($O82,Parameter!$O$11:$P$22,2,0)*VLOOKUP($O82,Parameter!$O$11:$T$22,6,0)^3*Z82 -> 0 | AF82: =VLOOKUP($O82,Parameter!$O$11:$P$22,2,0)*VLOOKUP($O82,Parameter!$O$11:$T$22,6,0)^4*AA82 -> 0
A83: =ROW()-1 -> 82 | B83: Outbound processing | C83: M Picking | D83: Mezzanine_Elevator operation | E83: Elevator Operation | F83: =F82 -> 0 | G83: Trip | H83: HDL | I83: =IFERROR(VLOOKUP(H83,Parameter!$F$44:$H$92,3,0),"") -> 0 | J83: Trolley | K83: =IFERROR(INDEX(Parameter!$D$122:$M$122,1,MATCH(Process!$J83,Parameter!$D$121:$M$121,0)),"") -> 0.42 | L83: =IFERROR(I83/K83,0) -> 0 | M83: 180 | N83: =L83+M83 -> 180 | O83: Operator | P83: =N83*F83/3600/Parameter!$P$6/Parameter!$P$7 -> 0 | X83: =P83*Parameter!W$8 -> 0 | Y83: =X83*Parameter!X$8 -> 0 | Z83: =Y83*Parameter!Y$8 -> 0 | AA83: =Z83*Parameter!Z$8 -> 0 | AB83: =VLOOKUP(O83,Parameter!$O$11:$P$22,2,0)*Process!P83 -> 0 | AC83: =VLOOKUP($O83,Parameter!$O$11:$P$22,2,0)*VLOOKUP($O83,Parameter!$O$11:$T$22,6,0)*X83 -> 0 | AD83: =VLOOKUP($O83,Parameter!$O$11:$P$22,2,0)*VLOOKUP($O83,Parameter!$O$11:$T$22,6,0)^2*Y83 -> 0 | AE83: =VLOOKUP($O83,Parameter!$O$11:$P$22,2,0)*VLOOKUP($O83,Parameter!$O$11:$T$22,6,0)^3*Z83 -> 0 | AF83: =VLOOKUP($O83,Parameter!$O$11:$P$22,2,0)*VLOOKUP($O83,Parameter!$O$11:$T$22,6,0)^4*AA83 -> 0
A84: =ROW()-1 -> 83 | B84: Outbound processing | C84: F Picking | D84: Floor_Picking | E84: Check TO List | F84: =Parameter!R72/Parameter!R73 -> 358.32178 | G84: Trip | H84: HDL | I84: =IFERROR(VLOOKUP(H84,Parameter!$F$44:$H$92,3,0),"") -> 0 | J84: CB | K84: =IFERROR(INDEX(Parameter!$D$122:$M$122,1,MATCH(Process!$J84,Parameter!$D$121:$M$121,0)),"") -> 2.7777778 | L84: =IFERROR(I84/K84,0) -> 0 | M84: 5 | N84: =L84+M84 -> 5 | O84: MHE Driver | P84: =N84*F84/3600/Parameter!$P$6/Parameter!$P$7 -> 0.073186638 | X84: =P84*Parameter!W$8 -> 0.070991039 | Y84: =X84*Parameter!X$8 -> 0.065459559 | Z84: =Y84*Parameter!Y$8 -> 0.062169854 | AA84: =Z84*Parameter!Z$8 -> 0.060816839 | AB84: =VLOOKUP(O84,Parameter!$O$11:$P$22,2,0)*Process!P84 -> 7381.2295 | AC84: =VLOOKUP($O84,Parameter!$O$11:$P$22,2,0)*VLOOKUP($O84,Parameter!$O$11:$T$22,6,0)*X84 -> 7660.9781 | AD84: =VLOOKUP($O84,Parameter!$O$11:$P$22,2,0)*VLOOKUP($O84,Parameter!$O$11:$T$22,6,0)^2*Y84 -> 7558.5335 | AE84: =VLOOKUP($O84,Parameter!$O$11:$P$22,2,0)*VLOOKUP($O84,Parameter!$O$11:$T$22,6,0)^3*Z84 -> 7681.1826 | AF84: =VLOOKUP($O84,Parameter!$O$11:$P$22,2,0)*VLOOKUP($O84,Parameter!$O$11:$T$22,6,0)^4*AA84 -> 8039.9965
A85: =ROW()-1 -> 84 | B85: Outbound processing | C85: F Picking | D85: Floor_Picking | E85: Move to F Staging | F85: =F84 -> 358.32178 | G85: Trip | H85: OBFP | I85: =IFERROR(VLOOKUP(H85,Parameter!$F$44:$H$92,3,0),"") -> 11 | J85: CB | K85: =IFERROR(INDEX(Parameter!$D$122:$M$122,1,MATCH(Process!$J85,Parameter!$D$121:$M$121,0)),"") -> 2.7777778 | L85: =IFERROR(I85/K85,0) -> 3.96 | N85: =L85+M85 -> 3.96 | O85: MHE Driver | P85: =N85*F85/3600/Parameter!$P$6/Parameter!$P$7 -> 0.057963818 | X85: =P85*Parameter!W$8 -> 0.056224903 | Y85: =X85*Parameter!X$8 -> 0.051843971 | Z85: =Y85*Parameter!Y$8 -> 0.049238524 | AA85: =Z85*Parameter!Z$8 -> 0.048166936 | AB85: =VLOOKUP(O85,Parameter!$O$11:$P$22,2,0)*Process!P85 -> 5845.9338 | AC85: =VLOOKUP($O85,Parameter!$O$11:$P$22,2,0)*VLOOKUP($O85,Parameter!$O$11:$T$22,6,0)*X85 -> 6067.4946 | AD85: =VLOOKUP($O85,Parameter!$O$11:$P$22,2,0)*VLOOKUP($O85,Parameter!$O$11:$T$22,6,0)^2*Y85 -> 5986.3585 | AE85: =VLOOKUP($O85,Parameter!$O$11:$P$22,2,0)*VLOOKUP($O85,Parameter!$O$11:$T$22,6,0)^3*Z85 -> 6083.4966 | AF85: =VLOOKUP($O85,Parameter!$O$11:$P$22,2,0)*VLOOKUP($O85,Parameter!$O$11:$T$22,6,0)^4*AA85 -> 6367.6772
A86: =ROW()-1 -> 85 | B86: Outbound processing | C86: F Picking | D86: Floor_Picking | E86: Aisle Distance | F86: =F84 -> 358.32178 | G86: Trip | H86: FA | I86: =IFERROR(VLOOKUP(H86,Parameter!$F$44:$H$92,3,0),"") -> 90 | J86: CB | K86: =IFERROR(INDEX(Parameter!$D$122:$M$122,1,MATCH(Process!$J86,Parameter!$D$121:$M$121,0)),"") -> 2.7777778 | L86: =IFERROR(I86/K86,0) -> 32.4 | N86: =L86+M86 -> 32.4 | O86: MHE Driver | P86: =N86*F86/3600/Parameter!$P$6/Parameter!$P$7 -> 0.47424942 | X86: =P86*Parameter!W$8 -> 0.46002193 | Y86: =X86*Parameter!X$8 -> 0.42417795 | Z86: =Y86*Parameter!Y$8 -> 0.40286065 | AA86: =Z86*Parameter!Z$8 -> 0.39409311 | AB86: =VLOOKUP(O86,Parameter!$O$11:$P$22,2,0)*Process!P86 -> 47830.367 | AC86: =VLOOKUP($O86,Parameter!$O$11:$P$22,2,0)*VLOOKUP($O86,Parameter!$O$11:$T$22,6,0)*X86 -> 49643.138 | AD86: =VLOOKUP($O86,Parameter!$O$11:$P$22,2,0)*VLOOKUP($O86,Parameter!$O$11:$T$22,6,0)^2*Y86 -> 48979.297 | AE86: =VLOOKUP($O86,Parameter!$O$11:$P$22,2,0)*VLOOKUP($O86,Parameter!$O$11:$T$22,6,0)^3*Z86 -> 49774.063 | AF86: =VLOOKUP($O86,Parameter!$O$11:$P$22,2,0)*VLOOKUP($O86,Parameter!$O$11:$T$22,6,0)^4*AA86 -> 52099.177
A87: =ROW()-1 -> 86 | B87: Outbound processing | C87: F Picking | D87: Floor_Picking | E87: Find Bin Location | F87: =Parameter!R72 -> 358.32178 | G87: Line | H87: FL | I87: =IFERROR(VLOOKUP(H87,Parameter!$F$44:$H$92,3,0),"") -> 60 | J87: CB | K87: =IFERROR(INDEX(Parameter!$D$122:$M$122,1,MATCH(Process!$J87,Parameter!$D$121:$M$121,0)),"") -> 2.7777778 | L87: =IFERROR(I87/K87,0) -> 21.6 | N87: =L87+M87 -> 21.6 | O87: MHE Driver | P87: =N87*F87/3600/Parameter!$P$6/Parameter!$P$7 -> 0.31616628 | X87: =P87*Parameter!W$8 -> 0.30668129 | Y87: =X87*Parameter!X$8 -> 0.2827853 | Z87: =Y87*Parameter!Y$8 -> 0.26857377 | AA87: =Z87*Parameter!Z$8 -> 0.26272874 | AB87: =VLOOKUP(O87,Parameter!$O$11:$P$22,2,0)*Process!P87 -> 31886.911 | AC87: =VLOOKUP($O87,Parameter!$O$11:$P$22,2,0)*VLOOKUP($O87,Parameter!$O$11:$T$22,6,0)*X87 -> 33095.425 | AD87: =VLOOKUP($O87,Parameter!$O$11:$P$22,2,0)*VLOOKUP($O87,Parameter!$O$11:$T$22,6,0)^2*Y87 -> 32652.865 | AE87: =VLOOKUP($O87,Parameter!$O$11:$P$22,2,0)*VLOOKUP($O87,Parameter!$O$11:$T$22,6,0)^3*Z87 -> 33182.709 | AF87: =VLOOKUP($O87,Parameter!$O$11:$P$22,2,0)*VLOOKUP($O87,Parameter!$O$11:$T$22,6,0)^4*AA87 -> 34732.785
A88: =ROW()-1 -> 87 | B88: Outbound processing | C88: F Picking | D88: Floor_Picking | E88: Check Performance and Shelf Life | F88: =F87*Parameter!R84 -> 32.24896 | G88: Line | H88: HDL | I88: =IFERROR(VLOOKUP(H88,Parameter!$F$44:$H$92,3,0),"") -> 0 | J88: CB | K88: =IFERROR(INDEX(Parameter!$D$122:$M$122,1,MATCH(Process!$J88,Parameter!$D$121:$M$121,0)),"") -> 2.7777778 | L88: =IFERROR(I88/K88,0) -> 0 | M88: 5 | N88: =L88+M88 -> 5 | O88: MHE Driver | P88: =N88*F88/3600/Parameter!$P$6/Parameter!$P$7 -> 0.0065867975 | X88: =P88*Parameter!W$8 -> 0.0063891935 | Y88: =X88*Parameter!X$8 -> 0.0058913604 | Z88: =Y88*Parameter!Y$8 -> 0.0055952869 | AA88: =Z88*Parameter!Z$8 -> 0.0054735155 | AB88: =VLOOKUP(O88,Parameter!$O$11:$P$22,2,0)*Process!P88 -> 664.31065 | AC88: =VLOOKUP($O88,Parameter!$O$11:$P$22,2,0)*VLOOKUP($O88,Parameter!$O$11:$T$22,6,0)*X88 -> 689.48803 | AD88: =VLOOKUP($O88,Parameter!$O$11:$P$22,2,0)*VLOOKUP($O88,Parameter!$O$11:$T$22,6,0)^2*Y88 -> 680.26801 | AE88: =VLOOKUP($O88,Parameter!$O$11:$P$22,2,0)*VLOOKUP($O88,Parameter!$O$11:$T$22,6,0)^3*Z88 -> 691.30643 | AF88: =VLOOKUP($O88,Parameter!$O$11:$P$22,2,0)*VLOOKUP($O88,Parameter!$O$11:$T$22,6,0)^4*AA88 -> 723.59969
A89: =ROW()-1 -> 88 | B89: Outbound processing | C89: F Picking | D89: Floor_Picking | E89: Picking Pallet | F89: =F87 -> 358.32178 | G89: Line | H89: HDL | I89: =IFERROR(VLOOKUP(H89,Parameter!$F$44:$H$92,3,0),"") -> 0 | J89: CB | K89: =IFERROR(INDEX(Parameter!$D$122:$M$122,1,MATCH(Process!$J89,Parameter!$D$121:$M$121,0)),"") -> 2.7777778 | L89: =IFERROR(I89/K89,0) -> 0 | M89: 10 | N89: =L89+M89 -> 10 | O89: MHE Driver | P89: =N89*F89/3600/Parameter!$P$6/Parameter!$P$7 -> 0.14637328 | X89: =P89*Parameter!W$8 -> 0.14198208 | Y89: =X89*Parameter!X$8 -> 0.13091912 | Z89: =Y89*Parameter!Y$8 -> 0.12433971 | AA89: =Z89*Parameter!Z$8 -> 0.12163368 | AB89: =VLOOKUP(O89,Parameter!$O$11:$P$22,2,0)*Process!P89 -> 14762.459 | AC89: =VLOOKUP($O89,Parameter!$O$11:$P$22,2,0)*VLOOKUP($O89,Parameter!$O$11:$T$22,6,0)*X89 -> 15321.956 | AD89: =VLOOKUP($O89,Parameter!$O$11:$P$22,2,0)*VLOOKUP($O89,Parameter!$O$11:$T$22,6,0)^2*Y89 -> 15117.067 | AE89: =VLOOKUP($O89,Parameter!$O$11:$P$22,2,0)*VLOOKUP($O89,Parameter!$O$11:$T$22,6,0)^3*Z89 -> 15362.365 | AF89: =VLOOKUP($O89,Parameter!$O$11:$P$22,2,0)*VLOOKUP($O89,Parameter!$O$11:$T$22,6,0)^4*AA89 -> 16079.993
A90: =ROW()-1 -> 89 | B90: Outbound processing | C90: F Picking | D90: Floor_Picking | E90: Scan Bin Location | F90: =F87 -> 358.32178 | G90: Line | H90: HDL | I90: =IFERROR(VLOOKUP(H90,Parameter!$F$44:$H$92,3,0),"") -> 0 | J90: CB | K90: =IFERROR(INDEX(Parameter!$D$122:$M$122,1,MATCH(Process!$J90,Parameter!$D$121:$M$121,0)),"") -> 2.7777778 | L90: =IFERROR(I90/K90,0) -> 0 | M90: 5 | N90: =L90+M90 -> 5 | O90: MHE Driver | P90: =N90*F90/3600/Parameter!$P$6/Parameter!$P$7 -> 0.073186638 | X90: =P90*Parameter!W$8 -> 0.070991039 | Y90: =X90*Parameter!X$8 -> 0.065459559 | Z90: =Y90*Parameter!Y$8 -> 0.062169854 | AA90: =Z90*Parameter!Z$8 -> 0.060816839 | AB90: =VLOOKUP(O90,Parameter!$O$11:$P$22,2,0)*Process!P90 -> 7381.2295 | AC90: =VLOOKUP($O90,Parameter!$O$11:$P$22,2,0)*VLOOKUP($O90,Parameter!$O$11:$T$22,6,0)*X90 -> 7660.9781 | AD90: =VLOOKUP($O90,Parameter!$O$11:$P$22,2,0)*VLOOKUP($O90,Parameter!$O$11:$T$22,6,0)^2*Y90 -> 7558.5335 | AE90: =VLOOKUP($O90,Parameter!$O$11:$P$22,2,0)*VLOOKUP($O90,Parameter!$O$11:$T$22,6,0)^3*Z90 -> 7681.1826 | AF90: =VLOOKUP($O90,Parameter!$O$11:$P$22,2,0)*VLOOKUP($O90,Parameter!$O$11:$T$22,6,0)^4*AA90 -> 8039.9965
A91: =ROW()-1 -> 90 | B91: Outbound processing | C91: F Picking | D91: Floor_Picking | E91: Back to Packing Area | F91: =F84 -> 358.32178 | G91: Trip | H91: OBFP | I91: =IFERROR(VLOOKUP(H91,Parameter!$F$44:$H$92,3,0),"") -> 11 | J91: CB | K91: =IFERROR(INDEX(Parameter!$D$122:$M$122,1,MATCH(Process!$J91,Parameter!$D$121:$M$121,0)),"") -> 2.7777778 | L91: =IFERROR(I91/K91,0) -> 3.96 | N91: =L91+M91 -> 3.96 | O91: MHE Driver | P91: =N91*F91/3600/Parameter!$P$6/Parameter!$P$7 -> 0.057963818 | X91: =P91*Parameter!W$8 -> 0.056224903 | Y91: =X91*Parameter!X$8 -> 0.051843971 | Z91: =Y91*Parameter!Y$8 -> 0.049238524 | AA91: =Z91*Parameter!Z$8 -> 0.048166936 | AB91: =VLOOKUP(O91,Parameter!$O$11:$P$22,2,0)*Process!P91 -> 5845.9338 | AC91: =VLOOKUP($O91,Parameter!$O$11:$P$22,2,0)*VLOOKUP($O91,Parameter!$O$11:$T$22,6,0)*X91 -> 6067.4946 | AD91: =VLOOKUP($O91,Parameter!$O$11:$P$22,2,0)*VLOOKUP($O91,Parameter!$O$11:$T$22,6,0)^2*Y91 -> 5986.3585 | AE91: =VLOOKUP($O91,Parameter!$O$11:$P$22,2,0)*VLOOKUP($O91,Parameter!$O$11:$T$22,6,0)^3*Z91 -> 6083.4966 | AF91: =VLOOKUP($O91,Parameter!$O$11:$P$22,2,0)*VLOOKUP($O91,Parameter!$O$11:$T$22,6,0)^4*AA91 -> 6367.6772
A92: =ROW()-1 -> 91 | B92: Outbound processing | C92: R Picking | D92: Racking_Move to storage area and back | E92: Check TO List | F92: =Parameter!R75/Parameter!R76 -> 203.84528 | G92: Trip | H92: HDL | I92: =IFERROR(VLOOKUP(H92,Parameter!$F$44:$H$92,3,0),"") -> 0 | J92: Rider on | K92: =IFERROR(INDEX(Parameter!$D$122:$M$122,1,MATCH(Process!$J92,Parameter!$D$121:$M$121,0)),"") -> 2.4 | L92: =IFERROR(I92/K92,0) -> 0 | M92: 5 | N92: =L92+M92 -> 5 | O92: Operator | P92: =N92*F92/3600/Parameter!$P$6/Parameter!$P$7 -> 0.041635065 | X92: =P92*Parameter!W$8 -> 0.040386013 | Y92: =X92*Parameter!X$8 -> 0.037239216 | Z92: =Y92*Parameter!Y$8 -> 0.035367739 | AA92: =Z92*Parameter!Z$8 -> 0.034598024 | AB92: =VLOOKUP(O92,Parameter!$O$11:$P$22,2,0)*Process!P92 -> 3499.2495 | AC92: =VLOOKUP($O92,Parameter!$O$11:$P$22,2,0)*VLOOKUP($O92,Parameter!$O$11:$T$22,6,0)*X92 -> 3631.8711 | AD92: =VLOOKUP($O92,Parameter!$O$11:$P$22,2,0)*VLOOKUP($O92,Parameter!$O$11:$T$22,6,0)^2*Y92 -> 3583.3048 | AE92: =VLOOKUP($O92,Parameter!$O$11:$P$22,2,0)*VLOOKUP($O92,Parameter!$O$11:$T$22,6,0)^3*Z92 -> 3641.4495 | AF92: =VLOOKUP($O92,Parameter!$O$11:$P$22,2,0)*VLOOKUP($O92,Parameter!$O$11:$T$22,6,0)^4*AA92 -> 3811.5539
A93: =ROW()-1 -> 92 | B93: Outbound processing | C93: R Picking | D93: Racking_Picking_Ground Level | E93: Take empty pallet /container | F93: =F92*Parameter!R77 -> 61.153584 | G93: Trip | H93: HDL | I93: =IFERROR(VLOOKUP(H93,Parameter!$F$44:$H$92,3,0),"") -> 0 | J93: Rider on | K93: =IFERROR(INDEX(Parameter!$D$122:$M$122,1,MATCH(Process!$J93,Parameter!$D$121:$M$121,0)),"") -> 2.4 | L93: =IFERROR(I93/K93,0) -> 0 | M93: 30 | N93: =L93+M93 -> 30 | O93: Operator | P93: =N93*F93/3600/Parameter!$P$6/Parameter!$P$7 -> 0.074943118 | X93: =P93*Parameter!W$8 -> 0.072694824 | Y93: =X93*Parameter!X$8 -> 0.067030589 | Z93: =Y93*Parameter!Y$8 -> 0.06366193 | AA93: =Z93*Parameter!Z$8 -> 0.062276443 | AB93: =VLOOKUP(O93,Parameter!$O$11:$P$22,2,0)*Process!P93 -> 6298.6492 | AC93: =VLOOKUP($O93,Parameter!$O$11:$P$22,2,0)*VLOOKUP($O93,Parameter!$O$11:$T$22,6,0)*X93 -> 6537.368 | AD93: =VLOOKUP($O93,Parameter!$O$11:$P$22,2,0)*VLOOKUP($O93,Parameter!$O$11:$T$22,6,0)^2*Y93 -> 6449.9486 | AE93: =VLOOKUP($O93,Parameter!$O$11:$P$22,2,0)*VLOOKUP($O93,Parameter!$O$11:$T$22,6,0)^3*Z93 -> 6554.6091 | AF93: =VLOOKUP($O93,Parameter!$O$11:$P$22,2,0)*VLOOKUP($O93,Parameter!$O$11:$T$22,6,0)^4*AA93 -> 6860.797
A94: =ROW()-1 -> 93 | B94: Outbound processing | C94: R Picking | D94: Racking_Picking_Ground Level | E94: Aisle Distance | F94: =F93 -> 61.153584 | G94: Trip | H94: RA | I94: =IFERROR(VLOOKUP(H94,Parameter!$F$44:$H$92,3,0),"") -> 80 | J94: Rider on | K94: =IFERROR(INDEX(Parameter!$D$122:$M$122,1,MATCH(Process!$J94,Parameter!$D$121:$M$121,0)),"") -> 2.4 | L94: =IFERROR(I94/K94,0) -> 33.333333 | N94: =L94+M94 -> 33.333333 | O94: Operator | P94: =N94*F94/3600/Parameter!$P$6/Parameter!$P$7 -> 0.083270131 | X94: =P94*Parameter!W$8 -> 0.080772027 | Y94: =X94*Parameter!X$8 -> 0.074478432 | Z94: =Y94*Parameter!Y$8 -> 0.070735478 | AA94: =Z94*Parameter!Z$8 -> 0.069196047 | AB94: =VLOOKUP(O94,Parameter!$O$11:$P$22,2,0)*Process!P94 -> 6998.4991 | AC94: =VLOOKUP($O94,Parameter!$O$11:$P$22,2,0)*VLOOKUP($O94,Parameter!$O$11:$T$22,6,0)*X94 -> 7263.7422 | AD94: =VLOOKUP($O94,Parameter!$O$11:$P$22,2,0)*VLOOKUP($O94,Parameter!$O$11:$T$22,6,0)^2*Y94 -> 7166.6095 | AE94: =VLOOKUP($O94,Parameter!$O$11:$P$22,2,0)*VLOOKUP($O94,Parameter!$O$11:$T$22,6,0)^3*Z94 -> 7282.899 | AF94: =VLOOKUP($O94,Parameter!$O$11:$P$22,2,0)*VLOOKUP($O94,Parameter!$O$11:$T$22,6,0)^4*AA94 -> 7623.1078
A95: =ROW()-1 -> 94 | B95: Outbound processing | C95: R Picking | D95: Racking_Picking_Ground Level | E95: Find Bin Location | F95: =Parameter!R75*Parameter!R77 -> 366.9215 | G95: Line | H95: RL | I95: =IFERROR(VLOOKUP(H95,Parameter!$F$44:$H$92,3,0),"") -> 30 | J95: Rider on | K95: =IFERROR(INDEX(Parameter!$D$122:$M$122,1,MATCH(Process!$J95,Parameter!$D$121:$M$121,0)),"") -> 2.4 | L95: =IFERROR(I95/K95,0) -> 12.5 | N95: =L95+M95 -> 12.5 | O95: Operator | P95: =N95*F95/3600/Parameter!$P$6/Parameter!$P$7 -> 0.18735779 | X95: =P95*Parameter!W$8 -> 0.18173706 | Y95: =X95*Parameter!X$8 -> 0.16757647 | Z95: =Y95*Parameter!Y$8 -> 0.15915483 | AA95: =Z95*Parameter!Z$8 -> 0.15569111 | AB95: =VLOOKUP(O95,Parameter!$O$11:$P$22,2,0)*Process!P95 -> 15746.623 | AC95: =VLOOKUP($O95,Parameter!$O$11:$P$22,2,0)*VLOOKUP($O95,Parameter!$O$11:$T$22,6,0)*X95 -> 16343.42 | AD95: =VLOOKUP($O95,Parameter!$O$11:$P$22,2,0)*VLOOKUP($O95,Parameter!$O$11:$T$22,6,0)^2*Y95 -> 16124.871 | AE95: =VLOOKUP($O95,Parameter!$O$11:$P$22,2,0)*VLOOKUP($O95,Parameter!$O$11:$T$22,6,0)^3*Z95 -> 16386.523 | AF95: =VLOOKUP($O95,Parameter!$O$11:$P$22,2,0)*VLOOKUP($O95,Parameter!$O$11:$T$22,6,0)^4*AA95 -> 17151.993
A96: =ROW()-1 -> 95 | B96: Outbound processing | C96: R Picking | D96: Racking_Picking_Ground Level | E96: Picking Parts according to List | F96: =Parameter!R75*Parameter!R79*Parameter!R77 -> 2384.9898 | G96: Piece | H96: HDL | I96: =IFERROR(VLOOKUP(H96,Parameter!$F$44:$H$92,3,0),"") -> 0 | J96: Rider on | K96: =IFERROR(INDEX(Parameter!$D$122:$M$122,1,MATCH(Process!$J96,Parameter!$D$121:$M$121,0)),"") -> 2.4 | L96: =IFERROR(I96/K96,0) -> 0 | M96: 15 | N96: =L96+M96 -> 15 | O96: Operator | P96: =N96*F96/3600/Parameter!$P$6/Parameter!$P$7 -> 1.4613908 | X96: =P96*Parameter!W$8 -> 1.4175491 | Y96: =X96*Parameter!X$8 -> 1.3070965 | Z96: =Y96*Parameter!Y$8 -> 1.2414076 | AA96: =Z96*Parameter!Z$8 -> 1.2143906 | AB96: =VLOOKUP(O96,Parameter!$O$11:$P$22,2,0)*Process!P96 -> 122823.66 | AC96: =VLOOKUP($O96,Parameter!$O$11:$P$22,2,0)*VLOOKUP($O96,Parameter!$O$11:$T$22,6,0)*X96 -> 127478.68 | AD96: =VLOOKUP($O96,Parameter!$O$11:$P$22,2,0)*VLOOKUP($O96,Parameter!$O$11:$T$22,6,0)^2*Y96 -> 125774 | AE96: =VLOOKUP($O96,Parameter!$O$11:$P$22,2,0)*VLOOKUP($O96,Parameter!$O$11:$T$22,6,0)^3*Z96 -> 127814.88 | AF96: =VLOOKUP($O96,Parameter!$O$11:$P$22,2,0)*VLOOKUP($O96,Parameter!$O$11:$T$22,6,0)^4*AA96 -> 133785.54
A97: =ROW()-1 -> 96 | B97: Outbound processing | C97: R Picking | D97: Racking_Picking_Ground Level | E97: Check Performance and Shelf Life | F97: =Parameter!R75*Parameter!R77*Parameter!R84 -> 33.022935 | G97: Line | H97: HDL | I97: =IFERROR(VLOOKUP(H97,Parameter!$F$44:$H$92,3,0),"") -> 0 | J97: Rider on | K97: =IFERROR(INDEX(Parameter!$D$122:$M$122,1,MATCH(Process!$J97,Parameter!$D$121:$M$121,0)),"") -> 2.4 | L97: =IFERROR(I97/K97,0) -> 0 | M97: 5 | N97: =L97+M97 -> 5 | O97: Operator | P97: =N97*F97/3600/Parameter!$P$6/Parameter!$P$7 -> 0.0067448806 | X97: =P97*Parameter!W$8 -> 0.0065425342 | Y97: =X97*Parameter!X$8 -> 0.006032753 | Z97: =Y97*Parameter!Y$8 -> 0.0057295737 | AA97: =Z97*Parameter!Z$8 -> 0.0056048798 | AB97: =VLOOKUP(O97,Parameter!$O$11:$P$22,2,0)*Process!P97 -> 566.87842 | AC97: =VLOOKUP($O97,Parameter!$O$11:$P$22,2,0)*VLOOKUP($O97,Parameter!$O$11:$T$22,6,0)*X97 -> 588.36312 | AD97: =VLOOKUP($O97,Parameter!$O$11:$P$22,2,0)*VLOOKUP($O97,Parameter!$O$11:$T$22,6,0)^2*Y97 -> 580.49537 | AE97: =VLOOKUP($O97,Parameter!$O$11:$P$22,2,0)*VLOOKUP($O97,Parameter!$O$11:$T$22,6,0)^3*Z97 -> 589.91482 | AF97: =VLOOKUP($O97,Parameter!$O$11:$P$22,2,0)*VLOOKUP($O97,Parameter!$O$11:$T$22,6,0)^4*AA97 -> 617.47173
A98: =ROW()-1 -> 97 | B98: Outbound processing | C98: R Picking | D98: Racking_Picking_Ground Level | E98: Scan Bin Location | F98: =Parameter!R75*Parameter!R77 -> 366.9215 | G98: Line | H98: HDL | I98: =IFERROR(VLOOKUP(H98,Parameter!$F$44:$H$92,3,0),"") -> 0 | J98: Rider on | K98: =IFERROR(INDEX(Parameter!$D$122:$M$122,1,MATCH(Process!$J98,Parameter!$D$121:$M$121,0)),"") -> 2.4 | L98: =IFERROR(I98/K98,0) -> 0 | M98: =M81 -> 5 | N98: =L98+M98 -> 5 | O98: Operator | P98: =N98*F98/3600/Parameter!$P$6/Parameter!$P$7 -> 0.074943118 | X98: =P98*Parameter!W$8 -> 0.072694824 | Y98: =X98*Parameter!X$8 -> 0.067030589 | Z98: =Y98*Parameter!Y$8 -> 0.06366193 | AA98: =Z98*Parameter!Z$8 -> 0.062276443 | AB98: =VLOOKUP(O98,Parameter!$O$11:$P$22,2,0)*Process!P98 -> 6298.6492 | AC98: =VLOOKUP($O98,Parameter!$O$11:$P$22,2,0)*VLOOKUP($O98,Parameter!$O$11:$T$22,6,0)*X98 -> 6537.368 | AD98: =VLOOKUP($O98,Parameter!$O$11:$P$22,2,0)*VLOOKUP($O98,Parameter!$O$11:$T$22,6,0)^2*Y98 -> 6449.9486 | AE98: =VLOOKUP($O98,Parameter!$O$11:$P$22,2,0)*VLOOKUP($O98,Parameter!$O$11:$T$22,6,0)^3*Z98 -> 6554.6091 | AF98: =VLOOKUP($O98,Parameter!$O$11:$P$22,2,0)*VLOOKUP($O98,Parameter!$O$11:$T$22,6,0)^4*AA98 -> 6860.797
A99: =ROW()-1 -> 98 | B99: Outbound processing | C99: R Picking | D99: Racking_Picking_Ground Level | E99: Move Picked pallet/container to Packing Area | F99: =F93 -> 61.153584 | G99: Trip | H99: OBRP | I99: =IFERROR(VLOOKUP(H99,Parameter!$F$44:$H$92,3,0),"") -> 77 | J99: Rider on | K99: =IFERROR(INDEX(Parameter!$D$122:$M$122,1,MATCH(Process!$J99,Parameter!$D$121:$M$121,0)),"") -> 2.4 | L99: =IFERROR(I99/K99,0) -> 32.083333 | N99: =L99+M99 -> 32.083333 | O99: Operator | P99: =N99*F99/3600/Parameter!$P$6/Parameter!$P$7 -> 0.080147501 | X99: =P99*Parameter!W$8 -> 0.077743076 | Y99: =X99*Parameter!X$8 -> 0.071685491 | Z99: =Y99*Parameter!Y$8 -> 0.068082898 | AA99: =Z99*Parameter!Z$8 -> 0.066601196 | AB99: =VLOOKUP(O99,Parameter!$O$11:$P$22,2,0)*Process!P99 -> 6736.0554 | AC99: =VLOOKUP($O99,Parameter!$O$11:$P$22,2,0)*VLOOKUP($O99,Parameter!$O$11:$T$22,6,0)*X99 -> 6991.3519 | AD99: =VLOOKUP($O99,Parameter!$O$11:$P$22,2,0)*VLOOKUP($O99,Parameter!$O$11:$T$22,6,0)^2*Y99 -> 6897.8617 | AE99: =VLOOKUP($O99,Parameter!$O$11:$P$22,2,0)*VLOOKUP($O99,Parameter!$O$11:$T$22,6,0)^3*Z99 -> 7009.7903 | AF99: =VLOOKUP($O99,Parameter!$O$11:$P$22,2,0)*VLOOKUP($O99,Parameter!$O$11:$T$22,6,0)^4*AA99 -> 7337.2413
A100: =ROW()-1 -> 99 | B100: Outbound processing | C100: R Picking | D100: Racking_Picking_Ground Level | E100: Move to Racking Staging | F100: =F93 -> 61.153584 | G100: Trip | H100: OBRP | I100: =IFERROR(VLOOKUP(H100,Parameter!$F$44:$H$92,3,0),"") -> 77 | J100: Rider on | K100: =IFERROR(INDEX(Parameter!$D$122:$M$122,1,MATCH(Process!$J100,Parameter!$D$121:$M$121,0)),"") -> 2.4 | L100: =IFERROR(I100/K100,0) -> 32.083333 | N100: =L100+M100 -> 32.083333 | O100: Operator | P100: =N100*F100/3600/Parameter!$P$6/Parameter!$P$7 -> 0.080147501 | X100: =P100*Parameter!W$8 -> 0.077743076 | Y100: =X100*Parameter!X$8 -> 0.071685491 | Z100: =Y100*Parameter!Y$8 -> 0.068082898 | AA100: =Z100*Parameter!Z$8 -> 0.066601196 | AB100: =VLOOKUP(O100,Parameter!$O$11:$P$22,2,0)*Process!P100 -> 6736.0554 | AC100: =VLOOKUP($O100,Parameter!$O$11:$P$22,2,0)*VLOOKUP($O100,Parameter!$O$11:$T$22,6,0)*X100 -> 6991.3519 | AD100: =VLOOKUP($O100,Parameter!$O$11:$P$22,2,0)*VLOOKUP($O100,Parameter!$O$11:$T$22,6,0)^2*Y100 -> 6897.8617 | AE100: =VLOOKUP($O100,Parameter!$O$11:$P$22,2,0)*VLOOKUP($O100,Parameter!$O$11:$T$22,6,0)^3*Z100 -> 7009.7903 | AF100: =VLOOKUP($O100,Parameter!$O$11:$P$22,2,0)*VLOOKUP($O100,Parameter!$O$11:$T$22,6,0)^4*AA100 -> 7337.2413
...

Sheet MHE&INV list
A2: Cate. | B2: Type | C2: Name | D2: 月租金/ 一次性采购成本（单件） | E2: Y1 | F2: Y2 | G2: Y3 | H2: Y4 | I2: Y5 | J2: 折旧 | K2: Cost - Y1 | L2: Cost - Y2 | M2: Cost - Y3 | N2: Cost - Y4 | O2: Cost - Y5
A3: MHE | B3: Lease/Consume | C3: CB | D3: 4300 | E3: =ROUNDUP(SUMIF(Process!J:J,'MHE&INV list'!C3,Process!P:P),0) -> 4 | F3: =ROUND(E3*Parameter!$W$6,0) -> 4 | G3: =ROUND(F3*Parameter!$X$6,0) -> 4 | H3: =ROUND(G3*Parameter!$Y$6,0) -> 4 | I3: =ROUND(H3*Parameter!$Z$6,0) -> 4 | K3: =IF($B3<>"",IF($B3="Lease/Consume",$D3*12*E3,-PMT(Parameter!$E$124,$J3,$D3*E3))) -> 206400 | L3: =IF($B3<>"",IF($B3="Lease/Consume",$D3*12*F3,-PMT(Parameter!$E$124,$J3,$D3*F3))) -> 206400 | M3: =IF($B3<>"",IF($B3="Lease/Consume",$D3*12*G3,-PMT(Parameter!$E$124,$J3,$D3*G3))) -> 206400 | N3: =IF($B3<>"",IF($B3="Lease/Consume",$D3*12*H3,-PMT(Parameter!$E$124,$J3,$D3*H3))) -> 206400 | O3: =IF($B3<>"",IF($B3="Lease/Consume",$D3*12*I3,-PMT(Parameter!$E$124,$J3,$D3*I3))) -> 206400
A4: MHE | B4: Lease/Consume | C4: R-Truck | D4: 6400 | E4: =ROUNDUP(SUMIF(Process!J:J,'MHE&INV list'!C4,Process!P:P),0) -> 3 | F4: =ROUND(E4*Parameter!$W$6,0) -> 3 | G4: =ROUND(F4*Parameter!$X$6,0) -> 3 | H4: =ROUND(G4*Parameter!$Y$6,0) -> 3 | I4: =ROUND(H4*Parameter!$Z$6,0) -> 3 | K4: =IF($B4<>"",IF($B4="Lease/Consume",$D4*12*E4,-PMT(Parameter!$E$124,$J4,$D4*E4))) -> 230400 | L4: =IF($B4<>"",IF($B4="Lease/Consume",$D4*12*F4,-PMT(Parameter!$E$124,$J4,$D4*F4))) -> 230400 | M4: =IF($B4<>"",IF($B4="Lease/Consume",$D4*12*G4,-PMT(Parameter!$E$124,$J4,$D4*G4))) -> 230400 | N4: =IF($B4<>"",IF($B4="Lease/Consume",$D4*12*H4,-PMT(Parameter!$E$124,$J4,$D4*H4))) -> 230400 | O4: =IF($B4<>"",IF($B4="Lease/Consume",$D4*12*I4,-PMT(Parameter!$E$124,$J4,$D4*I4))) -> 230400
A5: MHE | B5: Lease/Consume | C5: K-Truck | D5: 18400 | E5: =ROUNDUP(SUMIF(Process!J:J,'MHE&INV list'!C5,Process!P:P),0) -> 0 | F5: =ROUND(E5*Parameter!$W$6,0) -> 0 | G5: =ROUND(F5*Parameter!$X$6,0) -> 0 | H5: =ROUND(G5*Parameter!$Y$6,0) -> 0 | I5: =ROUND(H5*Parameter!$Z$6,0) -> 0 | K5: =IF($B5<>"",IF($B5="Lease/Consume",$D5*12*E5,-PMT(Parameter!$E$124,$J5,$D5*E5))) -> 0 | L5: =IF($B5<>"",IF($B5="Lease/Consume",$D5*12*F5,-PMT(Parameter!$E$124,$J5,$D5*F5))) -> 0 | M5: =IF($B5<>"",IF($B5="Lease/Consume",$D5*12*G5,-PMT(Parameter!$E$124,$J5,$D5*G5))) -> 0 | N5: =IF($B5<>"",IF($B5="Lease/Consume",$D5*12*H5,-PMT(Parameter!$E$124,$J5,$D5*H5))) -> 0 | O5: =IF($B5<>"",IF($B5="Lease/Consume",$D5*12*I5,-PMT(Parameter!$E$124,$J5,$D5*I5))) -> 0
A6: MHE | B6: Lease/Consume | C6: OP-raise/down | D6: 2800 | E6: =ROUNDUP(SUMIF(Process!J:J,'MHE&INV list'!C6,Process!P:P),0) -> 3 | F6: =ROUND(E6*Parameter!$W$6,0) -> 3 | G6: =ROUND(F6*Parameter!$X$6,0) -> 3 | H6: =ROUND(G6*Parameter!$Y$6,0) -> 3 | I6: =ROUND(H6*Parameter!$Z$6,0) -> 3 | K6: =IF($B6<>"",IF($B6="Lease/Consume",$D6*12*E6,-PMT(Parameter!$E$124,$J6,$D6*E6))) -> 100800 | L6: =IF($B6<>"",IF($B6="Lease/Consume",$D6*12*F6,-PMT(Parameter!$E$124,$J6,$D6*F6))) -> 100800 | M6: =IF($B6<>"",IF($B6="Lease/Consume",$D6*12*G6,-PMT(Parameter!$E$124,$J6,$D6*G6))) -> 100800 | N6: =IF($B6<>"",IF($B6="Lease/Consume",$D6*12*H6,-PMT(Parameter!$E$124,$J6,$D6*H6))) -> 100800 | O6: =IF($B6<>"",IF($B6="Lease/Consume",$D6*12*I6,-PMT(Parameter!$E$124,$J6,$D6*I6))) -> 100800
A7: MHE | B7: Lease/Consume | C7: OP-move | D7: 1730 | E7: =ROUNDUP(SUMIF(Process!J:J,'MHE&INV list'!C7,Process!P:P),0) -> 2 | F7: =ROUND(E7*Parameter!$W$6,0) -> 2 | G7: =ROUND(F7*Parameter!$X$6,0) -> 2 | H7: =ROUND(G7*Parameter!$Y$6,0) -> 2 | I7: =ROUND(H7*Parameter!$Z$6,0) -> 2 | K7: =IF($B7<>"",IF($B7="Lease/Consume",$D7*12*E7,-PMT(Parameter!$E$124,$J7,$D7*E7))) -> 41520 | L7: =IF($B7<>"",IF($B7="Lease/Consume",$D7*12*F7,-PMT(Parameter!$E$124,$J7,$D7*F7))) -> 41520 | M7: =IF($B7<>"",IF($B7="Lease/Consume",$D7*12*G7,-PMT(Parameter!$E$124,$J7,$D7*G7))) -> 41520 | N7: =IF($B7<>"",IF($B7="Lease/Consume",$D7*12*H7,-PMT(Parameter!$E$124,$J7,$D7*H7))) -> 41520 | O7: =IF($B7<>"",IF($B7="Lease/Consume",$D7*12*I7,-PMT(Parameter!$E$124,$J7,$D7*I7))) -> 41520
A8: MHE | B8: Lease/Consume | C8: CB - DG | D8: 5000 | E8: =ROUNDUP(SUMIF(Process!J:J,'MHE&INV list'!C8,Process!P:P),0) -> 2 | F8: =ROUND(E8*Parameter!$W$6,0) -> 2 | G8: =ROUND(F8*Parameter!$X$6,0) -> 2 | H8: =ROUND(G8*Parameter!$Y$6,0) -> 2 | I8: =ROUND(H8*Parameter!$Z$6,0) -> 2 | K8: =IF($B8<>"",IF($B8="Lease/Consume",$D8*12*E8,-PMT(Parameter!$E$124,$J8,$D8*E8))) -> 120000 | L8: =IF($B8<>"",IF($B8="Lease/Consume",$D8*12*F8,-PMT(Parameter!$E$124,$J8,$D8*F8))) -> 120000 | M8: =IF($B8<>"",IF($B8="Lease/Consume",$D8*12*G8,-PMT(Parameter!$E$124,$J8,$D8*G8))) -> 120000 | N8: =IF($B8<>"",IF($B8="Lease/Consume",$D8*12*H8,-PMT(Parameter!$E$124,$J8,$D8*H8))) -> 120000 | O8: =IF($B8<>"",IF($B8="Lease/Consume",$D8*12*I8,-PMT(Parameter!$E$124,$J8,$D8*I8))) -> 120000
A9: MHE | B9: Purchase | C9: Trolley | D9: 2800 | E9: =ROUNDUP(SUMIF(Process!J:J,'MHE&INV list'!C9,Process!P:P),0) -> 4 | F9: =ROUND(E9*Parameter!$W$6,0) -> 4 | G9: =ROUND(F9*Parameter!$X$6,0) -> 4 | H9: =ROUND(G9*Parameter!$Y$6,0) -> 4 | I9: =ROUND(H9*Parameter!$Z$6,0) -> 4 | J9: 3 | K9: =IF($B9<>"",IF($B9="Lease/Consume",$D9*12*E9,-PMT(Parameter!$E$124,$J9,$D9*E9))) -> 4035.9036 | L9: =IF($B9<>"",IF($B9="Lease/Consume",$D9*12*F9,-PMT(Parameter!$E$124,$J9,$D9*F9))) -> 4035.9036 | M9: =IF($B9<>"",IF($B9="Lease/Consume",$D9*12*G9,-PMT(Parameter!$E$124,$J9,$D9*G9))) -> 4035.9036 | N9: 0 | O9: 0 | P9: 这里需要手动调一下，按折旧年限
A10: MHE | B10: Lease/Consume | C10: Rider on | D10: 3500 | E10: =ROUNDUP(SUMIF(Process!J:J,'MHE&INV list'!C10,Process!P:P),0) -> 3 | F10: =ROUND(E10*Parameter!$W$6,0) -> 3 | G10: =ROUND(F10*Parameter!$X$6,0) -> 3 | H10: =ROUND(G10*Parameter!$Y$6,0) -> 3 | I10: =ROUND(H10*Parameter!$Z$6,0) -> 3 | K10: =IF($B10<>"",IF($B10="Lease/Consume",$D10*12*E10,-PMT(Parameter!$E$124,$J10,$D10*E10))) -> 126000 | L10: =IF($B10<>"",IF($B10="Lease/Consume",$D10*12*F10,-PMT(Parameter!$E$124,$J10,$D10*F10))) -> 126000 | M10: =IF($B10<>"",IF($B10="Lease/Consume",$D10*12*G10,-PMT(Parameter!$E$124,$J10,$D10*G10))) -> 126000 | N10: =IF($B10<>"",IF($B10="Lease/Consume",$D10*12*H10,-PMT(Parameter!$E$124,$J10,$D10*H10))) -> 126000 | O10: =IF($B10<>"",IF($B10="Lease/Consume",$D10*12*I10,-PMT(Parameter!$E$124,$J10,$D10*I10))) -> 126000
E11: =ROUNDUP(SUMIF(Process!J:J,'MHE&INV list'!C11,Process!P:P),0) -> 0 | F11: =ROUND(E11*Parameter!$W$6,0) -> 0 | G11: =ROUND(F11*Parameter!$X$6,0) -> 0 | H11: =ROUND(G11*Parameter!$Y$6,0) -> 0 | I11: =ROUND(H11*Parameter!$Z$6,0) -> 0 | K11: =IF($B11<>"",IF($B11="Lease/Consume",$D11*12*E11,-PMT(Parameter!$E$124,$J11,$D11*E11))) -> FALSE | L11: =IF($B11<>"",IF($B11="Lease/Consume",$D11*12*F11,-PMT(Parameter!$E$124,$J11,$D11*F11))) -> FALSE | M11: =IF($B11<>"",IF($B11="Lease/Consume",$D11*12*G11,-PMT(Parameter!$E$124,$J11,$D11*G11))) -> FALSE | N11: =IF($B11<>"",IF($B11="Lease/Consume",$D11*12*H11,-PMT(Parameter!$E$124,$J11,$D11*H11))) -> FALSE | O11: =IF($B11<>"",IF($B11="Lease/Consume",$D11*12*I11,-PMT(Parameter!$E$124,$J11,$D11*I11))) -> FALSE
E12: =ROUNDUP(SUMIF(Process!J:J,'MHE&INV list'!C12,Process!P:P),0) -> 0 | F12: =ROUND(E12*Parameter!$W$6,0) -> 0 | G12: =ROUND(F12*Parameter!$X$6,0) -> 0 | H12: =ROUND(G12*Parameter!$Y$6,0) -> 0 | I12: =ROUND(H12*Parameter!$Z$6,0) -> 0 | K12: =IF($B12<>"",IF($B12="Lease/Consume",$D12*12*E12,-PMT(Parameter!$E$124,$J12,$D12*E12))) -> FALSE | L12: =IF($B12<>"",IF($B12="Lease/Consume",$D12*12*F12,-PMT(Parameter!$E$124,$J12,$D12*F12))) -> FALSE | M12: =IF($B12<>"",IF($B12="Lease/Consume",$D12*12*G12,-PMT(Parameter!$E$124,$J12,$D12*G12))) -> FALSE | N12: =IF($B12<>"",IF($B12="Lease/Consume",$D12*12*H12,-PMT(Parameter!$E$124,$J12,$D12*H12))) -> FALSE | O12: =IF($B12<>"",IF($B12="Lease/Consume",$D12*12*I12,-PMT(Parameter!$E$124,$J12,$D12*I12))) -> FALSE
A13: Packing | B13: Purchase | C13: =Process!Q1 -> Packing Station | D13: 3500 | E13: {=ROUNDUP(SUMPRODUCT((Process!$Q$1:$W$1=C13)*Process!$Q$2:$W$164),0)} -> 9 | F13: =ROUND(E13*Parameter!$W$6,0) -> 9 | G13: =ROUND(F13*Parameter!$W$6,0) -> 9 | H13: =ROUND(G13*Parameter!$W$6,0) -> 9 | I13: =ROUND(H13*Parameter!$W$6,0) -> 9 | J13: 3 | K13: =IF($B13<>"",IF($B13="Lease/Consume",$D13*12*E13,-PMT(Parameter!$E$124,$J13,$D13*E13))) -> 11350.979 | L13: =IF($B13<>"",IF($B13="Lease/Consume",$D13*12*F13,-PMT(Parameter!$E$124,$J13,$D13*F13))) -> 11350.979 | M13: =IF($B13<>"",IF($B13="Lease/Consume",$D13*12*G13,-PMT(Parameter!$E$124,$J13,$D13*G13))) -> 11350.979 | N13: 0 | O13: 0
A14: Packing | B14: Purchase | C14: =Process!R1 -> HPJ with Scale | D14: 4500 | E14: {=ROUNDUP(SUMPRODUCT((Process!$Q$1:$W$1=C14)*Process!$Q$2:$W$164),0)} -> 1 | F14: =ROUND(E14*Parameter!$W$6,0) -> 1 | G14: =ROUND(F14*Parameter!$W$6,0) -> 1 | H14: =ROUND(G14*Parameter!$W$6,0) -> 1 | I14: =ROUND(H14*Parameter!$W$6,0) -> 1 | J14: 1 | K14: =IF($B14<>"",IF($B14="Lease/Consume",$D14*12*E14,-PMT(Parameter!$E$124,$J14,$D14*E14))) -> 4680 | L14: 0 | M14: 0 | N14: 0 | O14: 0
C15: =Process!S1 -> Customize 1 | F15: =ROUND(E15*Parameter!$W$6,0) -> 0 | G15: =ROUND(F15*Parameter!$W$6,0) -> 0 | H15: =ROUND(G15*Parameter!$W$6,0) -> 0 | I15: =ROUND(H15*Parameter!$W$6,0) -> 0 | K15: =IF($B15<>"",IF($B15="Lease/Consume",$D15*12*E15,-PMT(Parameter!$E$124,$J15,$D15*E15))) -> FALSE | L15: =IF($B15<>"",IF($B15="Lease/Consume",$D15*12*F15,-PMT(Parameter!$E$124,$J15,$D15*F15))) -> FALSE | M15: =IF($B15<>"",IF($B15="Lease/Consume",$D15*12*G15,-PMT(Parameter!$E$124,$J15,$D15*G15))) -> FALSE | N15: =IF($B15<>"",IF($B15="Lease/Consume",$D15*12*H15,-PMT(Parameter!$E$124,$J15,$D15*H15))) -> FALSE | O15: =IF($B15<>"",IF($B15="Lease/Consume",$D15*12*I15,-PMT(Parameter!$E$124,$J15,$D15*I15))) -> FALSE
C16: =Process!T1 -> Customize 2 | F16: =ROUND(E16*Parameter!$W$6,0) -> 0 | G16: =ROUND(F16*Parameter!$W$6,0) -> 0 | H16: =ROUND(G16*Parameter!$W$6,0) -> 0 | I16: =ROUND(H16*Parameter!$W$6,0) -> 0 | K16: =IF($B16<>"",IF($B16="Lease/Consume",$D16*12*E16,-PMT(Parameter!$E$124,$J16,$D16*E16))) -> FALSE | L16: =IF($B16<>"",IF($B16="Lease/Consume",$D16*12*F16,-PMT(Parameter!$E$124,$J16,$D16*F16))) -> FALSE | M16: =IF($B16<>"",IF($B16="Lease/Consume",$D16*12*G16,-PMT(Parameter!$E$124,$J16,$D16*G16))) -> FALSE | N16: =IF($B16<>"",IF($B16="Lease/Consume",$D16*12*H16,-PMT(Parameter!$E$124,$J16,$D16*H16))) -> FALSE | O16: =IF($B16<>"",IF($B16="Lease/Consume",$D16*12*I16,-PMT(Parameter!$E$124,$J16,$D16*I16))) -> FALSE
C17: =Process!U1 -> Customize 3 | F17: =ROUND(E17*Parameter!$W$6,0) -> 0 | G17: =ROUND(F17*Parameter!$W$6,0) -> 0 | H17: =ROUND(G17*Parameter!$W$6,0) -> 0 | I17: =ROUND(H17*Parameter!$W$6,0) -> 0 | K17: =IF($B17<>"",IF($B17="Lease/Consume",$D17*12*E17,-PMT(Parameter!$E$124,$J17,$D17*E17))) -> FALSE | L17: =IF($B17<>"",IF($B17="Lease/Consume",$D17*12*F17,-PMT(Parameter!$E$124,$J17,$D17*F17))) -> FALSE | M17: =IF($B17<>"",IF($B17="Lease/Consume",$D17*12*G17,-PMT(Parameter!$E$124,$J17,$D17*G17))) -> FALSE | N17: =IF($B17<>"",IF($B17="Lease/Consume",$D17*12*H17,-PMT(Parameter!$E$124,$J17,$D17*H17))) -> FALSE | O17: =IF($B17<>"",IF($B17="Lease/Consume",$D17*12*I17,-PMT(Parameter!$E$124,$J17,$D17*I17))) -> FALSE
C18: =Process!V1 -> Customize 4 | F18: =ROUND(E18*Parameter!$W$6,0) -> 0 | G18: =ROUND(F18*Parameter!$W$6,0) -> 0 | H18: =ROUND(G18*Parameter!$W$6,0) -> 0 | I18: =ROUND(H18*Parameter!$W$6,0) -> 0 | K18: =IF($B18<>"",IF($B18="Lease/Consume",$D18*12*E18,-PMT(Parameter!$E$124,$J18,$D18*E18))) -> FALSE | L18: =IF($B18<>"",IF($B18="Lease/Consume",$D18*12*F18,-PMT(Parameter!$E$124,$J18,$D18*F18))) -> FALSE | M18: =IF($B18<>"",IF($B18="Lease/Consume",$D18*12*G18,-PMT(Parameter!$E$124,$J18,$D18*G18))) -> FALSE | N18: =IF($B18<>"",IF($B18="Lease/Consume",$D18*12*H18,-PMT(Parameter!$E$124,$J18,$D18*H18))) -> FALSE | O18: =IF($B18<>"",IF($B18="Lease/Consume",$D18*12*I18,-PMT(Parameter!$E$124,$J18,$D18*I18))) -> FALSE
C19: =Process!W1 -> Customize 5 | F19: =ROUND(E19*Parameter!$W$6,0) -> 0 | G19: =ROUND(F19*Parameter!$W$6,0) -> 0 | H19: =ROUND(G19*Parameter!$W$6,0) -> 0 | I19: =ROUND(H19*Parameter!$W$6,0) -> 0 | K19: =IF($B19<>"",IF($B19="Lease/Consume",$D19*12*E19,-PMT(Parameter!$E$124,$J19,$D19*E19))) -> FALSE | L19: =IF($B19<>"",IF($B19="Lease/Consume",$D19*12*F19,-PMT(Parameter!$E$124,$J19,$D19*F19))) -> FALSE | M19: =IF($B19<>"",IF($B19="Lease/Consume",$D19*12*G19,-PMT(Parameter!$E$124,$J19,$D19*G19))) -> FALSE | N19: =IF($B19<>"",IF($B19="Lease/Consume",$D19*12*H19,-PMT(Parameter!$E$124,$J19,$D19*H19))) -> FALSE | O19: =IF($B19<>"",IF($B19="Lease/Consume",$D19*12*I19,-PMT(Parameter!$E$124,$J19,$D19*I19))) -> FALSE
A20: Packing | B20: Purchase | C20: Floor weigher for big part | D20: 3500 | E20: 2 | F20: =ROUND(E20*Parameter!$W$6,0) -> 2 | G20: =ROUND(F20*Parameter!$W$6,0) -> 2 | H20: =ROUND(G20*Parameter!$W$6,0) -> 2 | I20: =ROUND(H20*Parameter!$W$6,0) -> 2 | J20: 3 | K20: =IF($B20<>"",IF($B20="Lease/Consume",$D20*12*E20,-PMT(Parameter!$E$124,$J20,$D20*E20))) -> 2522.4398 | L20: =IF($B20<>"",IF($B20="Lease/Consume",$D20*12*F20,-PMT(Parameter!$E$124,$J20,$D20*F20))) -> 2522.4398 | M20: =IF($B20<>"",IF($B20="Lease/Consume",$D20*12*G20,-PMT(Parameter!$E$124,$J20,$D20*G20))) -> 2522.4398 | N20: 0 | O20: 0
A21: Packing | B21: Purchase | C21: Carton shipping label prineter | D21: 7000 | E21: =ROUNDUP(E13/2,0) -> 5 | F21: =ROUND(E21*Parameter!$W$6,0) -> 5 | G21: =ROUND(F21*Parameter!$W$6,0) -> 5 | H21: =ROUND(G21*Parameter!$W$6,0) -> 5 | I21: =ROUND(H21*Parameter!$W$6,0) -> 5 | J21: 3 | K21: =IF($B21<>"",IF($B21="Lease/Consume",$D21*12*E21,-PMT(Parameter!$E$124,$J21,$D21*E21))) -> 12612.199 | L21: =IF($B21<>"",IF($B21="Lease/Consume",$D21*12*F21,-PMT(Parameter!$E$124,$J21,$D21*F21))) -> 12612.199 | M21: =IF($B21<>"",IF($B21="Lease/Consume",$D21*12*G21,-PMT(Parameter!$E$124,$J21,$D21*G21))) -> 12612.199 | N21: 0 | O21: 0
A22: Packing | B22: Purchase | C22: Air Nail Gun | D22: 100 | E22: =ROUNDUP(SUM(Process!P141:P146),0) -> 4 | F22: =ROUND(E22*Parameter!$W$6,0) -> 4 | G22: =ROUND(F22*Parameter!$W$6,0) -> 4 | H22: =ROUND(G22*Parameter!$W$6,0) -> 4 | I22: =ROUND(H22*Parameter!$W$6,0) -> 4 | J22: 3 | K22: =IF($B22<>"",IF($B22="Lease/Consume",$D22*12*E22,-PMT(Parameter!$E$124,$J22,$D22*E22))) -> 144.13942 | L22: =IF($B22<>"",IF($B22="Lease/Consume",$D22*12*F22,-PMT(Parameter!$E$124,$J22,$D22*F22))) -> 144.13942 | M22: =IF($B22<>"",IF($B22="Lease/Consume",$D22*12*G22,-PMT(Parameter!$E$124,$J22,$D22*G22))) -> 144.13942 | N22: 0 | O22: 0
A23: Packing | B23: Purchase | C23: Air Nail pump | D23: 2000 | E23: 1 | F23: =ROUND(E23*Parameter!$W$6,0) -> 1 | G23: =ROUND(F23*Parameter!$W$6,0) -> 1 | H23: =ROUND(G23*Parameter!$W$6,0) -> 1 | I23: =ROUND(H23*Parameter!$W$6,0) -> 1 | J23: 3 | K23: =IF($B23<>"",IF($B23="Lease/Consume",$D23*12*E23,-PMT(Parameter!$E$124,$J23,$D23*E23))) -> 720.69708 | L23: =IF($B23<>"",IF($B23="Lease/Consume",$D23*12*F23,-PMT(Parameter!$E$124,$J23,$D23*F23))) -> 720.69708 | M23: =IF($B23<>"",IF($B23="Lease/Consume",$D23*12*G23,-PMT(Parameter!$E$124,$J23,$D23*G23))) -> 720.69708 | N23: 0 | O23: 0
A24: Packing | B24: Purchase | C24: Tapper/table scale | D24: 1000 | E24: =E13 -> 9 | F24: =ROUND(E24*Parameter!$W$6,0) -> 9 | G24: =ROUND(F24*Parameter!$W$6,0) -> 9 | H24: =ROUND(G24*Parameter!$W$6,0) -> 9 | I24: =ROUND(H24*Parameter!$W$6,0) -> 9 | J24: 1 | K24: =IF($B24<>"",IF($B24="Lease/Consume",$D24*12*E24,-PMT(Parameter!$E$124,$J24,$D24*E24))) -> 9360 | L24: 0 | M24: 0 | N24: 0 | O24: 0
A25: Others | B25: Purchase | C25: HPJ | D25: 2000 | E25: 6 | F25: =ROUND(E25*Parameter!$W$6,0) -> 6 | G25: =ROUND(F25*Parameter!$W$6,0) -> 6 | H25: =ROUND(G25*Parameter!$W$6,0) -> 6 | I25: =ROUND(H25*Parameter!$W$6,0) -> 6 | J25: 1 | K25: =IF($B25<>"",IF($B25="Lease/Consume",$D25*12*E25,-PMT(Parameter!$E$124,$J25,$D25*E25))) -> 12480 | L25: 0 | M25: 0 | N25: 0 | O25: 0
A26: Startup | B26: Purchase | C26: Security system (CCTV, etc.） | D26: =161*3500 -> 563500 | E26: 1 | F26: =ROUND(E26*Parameter!$W$6,0) -> 1 | G26: =ROUND(F26*Parameter!$W$6,0) -> 1 | H26: =ROUND(G26*Parameter!$W$6,0) -> 1 | I26: =ROUND(H26*Parameter!$W$6,0) -> 1 | J26: 1 | K26: =IF($B26<>"",IF($B26="Lease/Consume",$D26*12*E26,-PMT(Parameter!$E$124,$J26,$D26*E26))) -> 586040 | L26: 0 | M26: 0 | N26: 0 | O26: 0
A27: Others | B27: Lease/Consume | C27: Security guard service | D27: 5500 | E27: 1
A28: Others | B28: Purchase | C28: IT infrasturcture | D28: 100000 | E28: 1 | F28: =ROUND(E28*Parameter!$W$6,0) -> 1 | G28: =ROUND(F28*Parameter!$W$6,0) -> 1 | H28: =ROUND(G28*Parameter!$W$6,0) -> 1 | I28: =ROUND(H28*Parameter!$W$6,0) -> 1 | J28: 3 | K28: =IF($B28<>"",IF($B28="Lease/Consume",$D28*12*E28,-PMT(Parameter!$E$124,$J28,$D28*E28))) -> 36034.854 | L28: =IF($B28<>"",IF($B28="Lease/Consume",$D28*12*F28,-PMT(Parameter!$E$124,$J28,$D28*F28))) -> 36034.854 | M28: =IF($B28<>"",IF($B28="Lease/Consume",$D28*12*G28,-PMT(Parameter!$E$124,$J28,$D28*G28))) -> 36034.854 | N28: 0 | O28: 0
A29: Others | B29: Lease/Consume | C29: IT running | D29: 10000 | E29: 1 | F29: =ROUND(E29*Parameter!$W$6,0) -> 1 | G29: =ROUND(F29*Parameter!$W$6,0) -> 1 | H29: =ROUND(G29*Parameter!$W$6,0) -> 1 | I29: =ROUND(H29*Parameter!$W$6,0) -> 1 | K29: =IF($B29<>"",IF($B29="Lease/Consume",$D29*12*E29,-PMT(Parameter!$E$124,$J29,$D29*E29))) -> 120000 | L29: =IF($B29<>"",IF($B29="Lease/Consume",$D29*12*F29,-PMT(Parameter!$E$124,$J29,$D29*F29))) -> 120000 | M29: =IF($B29<>"",IF($B29="Lease/Consume",$D29*12*G29,-PMT(Parameter!$E$124,$J29,$D29*G29))) -> 120000 | N29: =IF($B29<>"",IF($B29="Lease/Consume",$D29*12*H29,-PMT(Parameter!$E$124,$J29,$D29*H29))) -> 120000 | O29: =IF($B29<>"",IF($B29="Lease/Consume",$D29*12*I29,-PMT(Parameter!$E$124,$J29,$D29*I29))) -> 120000
A30: Startup | B30: Purchase | C30: 3PL office furniture and setup | D30: 400000 | E30: 1 | F30: =ROUND(E30*Parameter!$W$6,0) -> 1 | G30: =ROUND(F30*Parameter!$W$6,0) -> 1 | H30: =ROUND(G30*Parameter!$W$6,0) -> 1 | I30: =ROUND(H30*Parameter!$W$6,0) -> 1 | J30: 1 | K30: =IF($B30<>"",IF($B30="Lease/Consume",$D30*12*E30,-PMT(Parameter!$E$124,$J30,$D30*E30))) -> 416000 | L30: 0 | M30: 0 | N30: 0 | O30: 0
A31: Others | B31: Lease/Consume | C31: 3PL office supplies | D31: 5000 | E31: 1 | F31: =ROUND(E31*Parameter!$W$6,0) -> 1 | G31: =ROUND(F31*Parameter!$W$6,0) -> 1 | H31: =ROUND(G31*Parameter!$W$6,0) -> 1 | I31: =ROUND(H31*Parameter!$W$6,0) -> 1 | K31: =IF($B31<>"",IF($B31="Lease/Consume",$D31*12*E31,-PMT(Parameter!$E$124,$J31,$D31*E31))) -> 60000 | L31: =IF($B31<>"",IF($B31="Lease/Consume",$D31*12*F31,-PMT(Parameter!$E$124,$J31,$D31*F31))) -> 60000 | M31: =IF($B31<>"",IF($B31="Lease/Consume",$D31*12*G31,-PMT(Parameter!$E$124,$J31,$D31*G31))) -> 60000 | N31: =IF($B31<>"",IF($B31="Lease/Consume",$D31*12*H31,-PMT(Parameter!$E$124,$J31,$D31*H31))) -> 60000 | O31: =IF($B31<>"",IF($B31="Lease/Consume",$D31*12*I31,-PMT(Parameter!$E$124,$J31,$D31*I31))) -> 60000
A32: Others | B32: Purchase | C32: Locker | D32: 9000 | E32: =ROUNDUP(SUM(Parameter!U11:U22)/12,0) -> 4 | F32: =ROUND(E32*Parameter!$W$6,0) -> 4 | G32: =ROUND(F32*Parameter!$W$6,0) -> 4 | H32: =ROUND(G32*Parameter!$W$6,0) -> 4 | I32: =ROUND(H32*Parameter!$W$6,0) -> 4 | J32: 3 | K32: =IF($B32<>"",IF($B32="Lease/Consume",$D32*12*E32,-PMT(Parameter!$E$124,$J32,$D32*E32))) -> 12972.547 | L32: =IF($B32<>"",IF($B32="Lease/Consume",$D32*12*F32,-PMT(Parameter!$E$124,$J32,$D32*F32))) -> 12972.547 | M32: =IF($B32<>"",IF($B32="Lease/Consume",$D32*12*G32,-PMT(Parameter!$E$124,$J32,$D32*G32))) -> 12972.547 | N32: 0 | O32: 0
A33: Others | B33: Purchase | C33: Floor Marking and signals | D33: 50000 | E33: 1 | F33: =ROUND(E33*Parameter!$W$6,0) -> 1 | G33: =ROUND(F33*Parameter!$W$6,0) -> 1 | H33: =ROUND(G33*Parameter!$W$6,0) -> 1 | I33: =ROUND(H33*Parameter!$W$6,0) -> 1 | J33: 3 | K33: =IF($B33<>"",IF($B33="Lease/Consume",$D33*12*E33,-PMT(Parameter!$E$124,$J33,$D33*E33))) -> 18017.427 | L33: =IF($B33<>"",IF($B33="Lease/Consume",$D33*12*F33,-PMT(Parameter!$E$124,$J33,$D33*F33))) -> 18017.427 | M33: =IF($B33<>"",IF($B33="Lease/Consume",$D33*12*G33,-PMT(Parameter!$E$124,$J33,$D33*G33))) -> 18017.427 | N33: 0 | O33: 0
A34: Others | B34: Lease/Consume | C34: Floor Marking and signals maintenance | D34: 500 | E34: 1 | F34: =ROUND(E34*Parameter!$W$6,0) -> 1 | G34: =ROUND(F34*Parameter!$W$6,0) -> 1 | H34: =ROUND(G34*Parameter!$W$6,0) -> 1 | I34: =ROUND(H34*Parameter!$W$6,0) -> 1 | K34: =IF($B34<>"",IF($B34="Lease/Consume",$D34*12*E34,-PMT(Parameter!$E$124,$J34,$D34*E34))) -> 6000 | L34: =IF($B34<>"",IF($B34="Lease/Consume",$D34*12*F34,-PMT(Parameter!$E$124,$J34,$D34*F34))) -> 6000 | M34: =IF($B34<>"",IF($B34="Lease/Consume",$D34*12*G34,-PMT(Parameter!$E$124,$J34,$D34*G34))) -> 6000 | N34: =IF($B34<>"",IF($B34="Lease/Consume",$D34*12*H34,-PMT(Parameter!$E$124,$J34,$D34*H34))) -> 6000 | O34: =IF($B34<>"",IF($B34="Lease/Consume",$D34*12*I34,-PMT(Parameter!$E$124,$J34,$D34*I34))) -> 6000
A35: Others | B35: Purchase | C35: Cleaning machine | D35: 35000 | E35: 1 | F35: =ROUND(E35*Parameter!$W$6,0) -> 1 | G35: =ROUND(F35*Parameter!$W$6,0) -> 1 | H35: =ROUND(G35*Parameter!$W$6,0) -> 1 | I35: =ROUND(H35*Parameter!$W$6,0) -> 1 | J35: 3 | K35: =IF($B35<>"",IF($B35="Lease/Consume",$D35*12*E35,-PMT(Parameter!$E$124,$J35,$D35*E35))) -> 12612.199 | L35: =IF($B35<>"",IF($B35="Lease/Consume",$D35*12*F35,-PMT(Parameter!$E$124,$J35,$D35*F35))) -> 12612.199 | M35: =IF($B35<>"",IF($B35="Lease/Consume",$D35*12*G35,-PMT(Parameter!$E$124,$J35,$D35*G35))) -> 12612.199 | N35: 0 | O35: 0
A36: Others | B36: Lease/Consume | C36: Racking maintenance | D36: =2000000*0.4% -> 8000 | E36: 1 | F36: =ROUND(E36*Parameter!$W$6,0) -> 1 | G36: =ROUND(F36*Parameter!$W$6,0) -> 1 | H36: =ROUND(G36*Parameter!$W$6,0) -> 1 | I36: =ROUND(H36*Parameter!$W$6,0) -> 1 | K36: =IF($B36<>"",IF($B36="Lease/Consume",$D36*12*E36,-PMT(Parameter!$E$124,$J36,$D36*E36))) -> 96000 | L36: =IF($B36<>"",IF($B36="Lease/Consume",$D36*12*F36,-PMT(Parameter!$E$124,$J36,$D36*F36))) -> 96000 | M36: =IF($B36<>"",IF($B36="Lease/Consume",$D36*12*G36,-PMT(Parameter!$E$124,$J36,$D36*G36))) -> 96000 | N36: =IF($B36<>"",IF($B36="Lease/Consume",$D36*12*H36,-PMT(Parameter!$E$124,$J36,$D36*H36))) -> 96000 | O36: =IF($B36<>"",IF($B36="Lease/Consume",$D36*12*I36,-PMT(Parameter!$E$124,$J36,$D36*I36))) -> 96000
